Workbook
Name BankList: Banks!$A$2:$A$21
Name BankRegion: Banks!$C$2:$C$21
Name D_Bank: Data!$A$2:$A$5761
Name D_Month: Data!$B$2:$B$5761
Name D_Vol: Data!$E$2:$E$5761
Name Rate: Control!$B$4
Name SelBank: Control!$B$2
Name SelMonth: Control!$B$3
Name SelRegion: Control!$B$5
Name TaxRate: 0.24
Name VolSel: SUMIFS(D_Vol,D_Bank,SelBank,D_Month,SelMonth)

Sheet Control
A1: Parametro
A2: Banca | B2: Banca Tirrena
A3: Mese (indice) | B3: 13
A4: Tasso scenario | B4: 0.03
A5: Regione | B5: Centro
A6: Indice banca | B6: =MATCH(B2,Banks!$A$2:$A$21,0) -> 3
A7: Codice | B7: =VLOOKUP(B2,Banks!$A$2:$H$21,2,FALSE) -> B103
A8: Regione banca | B8: =_xlfn.XLOOKUP(B2,Banks!$A$2:$A$21,Banks!$C$2:$C$21,"n.d.",0) -> Centro
A9: Data rif. | B9: =EOMONTH(DATE(2024,B3,1),0) -> 45688
A10: Etichetta | B10: =TEXT(B9,"mmmm aaaa") -> gennaio 2025
A11: Anno | B11: =YEAR(B9) -> 2025
A12: Mese anno | B12: =MONTH(B9) -> 1
A13: Mese prec. | B13: =MAX(1,B3-1) -> 12
A14: Anno prec. | B14: =MAX(1,B3-12) -> 1
A15: Cambio USD | B15: =_xlfn.XLOOKUP(B3,FX!$A$2:$A$37,FX!$C$2:$C$37) -> 1.0719
A16: Titolo | B16: =B2&" ("&B7&") - "&B10 -> Banca Tirrena (B103) - gennaio 2025
A17: Oggi | B17: =TODAY() -> 46312
A18: Gap peer | B18: =[1]Summary!$B$2 -> 0.057912768
A19: Totale regioni | B19: =[2]Summary!$B$2 -> 343560.2
A20: Trimestre | B20: =ROUNDUP(B12/3,0) -> 1
A21: Inizio trimestre | B21: =B3-MOD(B12-1,3) -> 13
A22: Primo mese anno | B22: =B3-B12+1 -> 13
A23: Responsabile | B23: {=TRIM(INDEX(Banks!$D$2:$D$21,B6))} -> Verdi
A24: Segmento | B24: {=INDEX(Banks!$E$2:$E$21,B6)} -> Grande
A25: Tasso mensile | B25: =(1+B4)^(1/12)-1 -> 0.0024662698

Sheet Data
A1: Banca | B1: Mese | C1: Prodotto | D1: Data | E1: Volumi | F1: Ricavi | G1: Costi | H1: Clienti | I1: Regione | J1: Anno | K1: Margine | L1: Chiave
A2: Banca Alpi | B2: 1 | C2: Mutui | D2: 45322 | E2: 346 | F2: 15.89 | G2: 10.09 | H2: 50 | I2: Nord-Ovest | J2: 2024 | K2: =F2-G2 -> 5.8 | L2: =A2&"|"&B2&"|"&C2 -> Banca Alpi|1|Mutui
A3: Banca Alpi | B3: 1 | C3: Prestiti | D3: 45322 | E3: 465.8 | F3: 22.55 | G3: 13.66 | H3: 65 | I3: Nord-Ovest | J3: 2024 | K3: =F3-G3 -> 8.89 | L3: =A3&"|"&B3&"|"&C3 -> Banca Alpi|1|Prestiti
A4: Banca Alpi | B4: 1 | C4: Conti | D4: 45322 | E4: 536.6 | F4: 26.52 | G4: 16.42 | H4: 90 | I4: Nord-Ovest | J4: 2024 | K4: =F4-G4 -> 10.1 | L4: =A4&"|"&B4&"|"&C4 -> Banca Alpi|1|Conti
A5: Banca Alpi | B5: 1 | C5: Carte | D5: 45322 | E5: 686.6 | F5: 35.92 | G5: 21.52 | H5: 68 | I5: Nord-Ovest | J5: 2024 | K5: =F5-G5 -> 14.4 | L5: =A5&"|"&B5&"|"&C5 -> Banca Alpi|1|Carte
A6: Banca Alpi | B6: 1 | C6: Leasing | D6: 45322 | E6: 780.2 | F6: 41.73 | G6: 25.8 | H6: 85 | I6: Nord-Ovest | J6: 2024 | K6: =F6-G6 -> 15.93 | L6: =A6&"|"&B6&"|"&C6 -> Banca Alpi|1|Leasing
A7: Banca Alpi | B7: 1 | C7: Factoring | D7: 45322 | E7: 923.8 | F7: 50.9 | G7: 31.24 | H7: 109 | I7: Nord-Ovest | J7: 2024 | K7: =F7-G7 -> 19.66 | L7: =A7&"|"&B7&"|"&C7 -> Banca Alpi|1|Factoring
A8: Banca Alpi | B8: 1 | C8: Risparmio | D8: 45322 | E8: 1059.9 | F8: 61.23 | G8: 36.35 | H8: 130 | I8: Nord-Ovest | J8: 2024 | K8: =F8-G8 -> 24.88 | L8: =A8&"|"&B8&"|"&C8 -> Banca Alpi|1|Risparmio
A9: Banca Alpi | B9: 1 | C9: Assicurazioni | D9: 45322 | E9: 1142.7 | F9: 67.94 | G9: 40.18 | H9: 147 | I9: Nord-Ovest | J9: 2024 | K9: =F9-G9 -> 27.76 | L9: =A9&"|"&B9&"|"&C9 -> Banca Alpi|1|Assicurazioni
A10: Banca Alpi | B10: 2 | C10: Mutui | D10: 45351 | E10: 301.3 | F10: 13.67 | G10: 8.45 | H10: 32 | I10: Nord-Ovest | J10: 2024 | K10: =F10-G10 -> 5.22 | L10: =A10&"|"&B10&"|"&C10 -> Banca Alpi|2|Mutui
A11: Banca Alpi | B11: 2 | C11: Prestiti | D11: 45351 | E11: 447.6 | F11: 21.46 | G11: 13.03 | H11: 47 | I11: Nord-Ovest | J11: 2024 | K11: =F11-G11 -> 8.43 | L11: =A11&"|"&B11&"|"&C11 -> Banca Alpi|2|Prestiti
A12: Banca Alpi | B12: 2 | C12: Conti | D12: 45351 | E12: 570.2 | F12: 28.2 | G12: 18.02 | H12: 88 | I12: Nord-Ovest | J12: 2024 | K12: =F12-G12 -> 10.18 | L12: =A12&"|"&B12&"|"&C12 -> Banca Alpi|2|Conti
A13: Banca Alpi | B13: 2 | C13: Carte | D13: 45351 | E13: 663.9 | F13: 34.35 | G13: 20.86 | H13: 68 | I13: Nord-Ovest | J13: 2024 | K13: =F13-G13 -> 13.49 | L13: =A13&"|"&B13&"|"&C13 -> Banca Alpi|2|Carte
... A5761: Banca Città | B5761: 36 | C5761: Assicurazioni | D5761: 46387 | E5761: 6339.9 | F5761: 374.28 | G5761: 222.35 | H5761: 493 | I5761: Centro | J5761: 2026 | K5761: =F5761-G5761 -> 151.93 | L5761: =A5761&"|"&B5761&"|"&C5761 -> Banca Città|36|Assicurazioni

Sheet Banks
A1: Banca | B1: Codice | C1: Regione | D1: Responsabile | E1: Segmento | F1: Fondazione | G1: Obiettivo | H1: Peso
A2: Banca Alpi | B2: B101 | C2: Nord-Ovest | D2: Rossi | E2: Grande | F2: 1850 | G2: 4480 | H2: 0.02
A3: Banca Adriatica | B3: B102 | C3: Nord-Est | D3: Bianchi Anna | E3: Media | F3: 1857 | G3: 5247 | H3: 0.023
A4: Banca Tirrena | B4: B103 | C4: Centro | D4: Verdi | E4: Grande | F4: 1864 | G4: 6014 | H4: 0.026
A5: Banca Padana | B5: B104 | C5: Nord-Ovest | D5: Ferrari | E5: Grande | F5: 1871 | G5: 6782 | H5: 0.029
A6: Banca Etrusca | B6: B105 | C6: Centro | D6: Russo | E6: Media | F6: 1878 | G6: 7549 | H6: 0.032
A7: Banca Lariana | B7: B106 | C7: Nord-Ovest | D7: Colombo Luca | E7: Piccola | F7: 1885 | G7: 8316 | H7: 0.035
A8: Banca Sabina | B8: B107 | C8: Centro | D8: Ricci | E8: Piccola | F8: 1892 | G8: 9083 | H8: 0.038
A9: Banca Irpina | B9: B108 | C9: Sud | D9: Marino | E9: Piccola | F9: 1899 | G9: 9850 | H9: 0.041
A10: Banca Sannita | B10: B109 | C10: Sud | D10: Greco | E10: Media | F10: 1906 | G10: 10618 | H10: 0.044
A11: Banca Ligure | B11: B110 | C11: Nord-Ovest | D11: Bruno | E11: Media | F11: 1913 | G11: 11385 | H11: 0.047
A12: Banca Veneta | B12: B111 | C12: Nord-Est | D12: Gallo | E12: Grande | F12: 1920 | G12: 12152 | H12: 0.05
A13: Banca Friulana | B13: B112 | C13: Nord-Est | D13: Conti | E13: Media | F13: 1927 | G13: 12919 | H13: 0.053
... A21: Banca Città | B21: B120 | C21: Centro | D21: Barbieri | E21: Grande | F21: 1983 | G21: 19057 | H21: 0.077

Sheet FX
A1: Mese | B1: Data | C1: USD | D1: GBP | E1: CHF
A2: 1 | B2: 45322 | C2: 1.058 | D2: 0.8597 | E2: 0.948
A3: 2 | B3: 45351 | C3: 1.0658 | D3: 0.8588 | E3: 0.946
A4: 3 | B4: 45382 | C4: 1.0729 | D4: 0.8573 | E4: 0.944
A5: 4 | B5: 45412 | C5: 1.0791 | D5: 0.8554 | E5: 0.942
A6: 5 | B6: 45443 | C6: 1.0842 | D6: 0.8532 | E6: 0.94
A7: 6 | B7: 45473 | C7: 1.0879 | D7: 0.8507 | E7: 0.938
A8: 7 | B8: 45504 | C8: 1.0901 | D8: 0.8482 | E8: 0.936
A9: 8 | B9: 45535 | C9: 1.0908 | D9: 0.8458 | E9: 0.934
A10: 9 | B10: 45565 | C10: 1.0899 | D10: 0.8437 | E10: 0.932
A11: 10 | B11: 45596 | C11: 1.0874 | D11: 0.842 | E11: 0.93
A12: 11 | B12: 45626 | C12: 1.0834 | D12: 0.8408 | E12: 0.928
A13: 12 | B13: 45657 | C13: 1.0782 | D13: 0.8401 | E13: 0.926
... A37: 36 | B37: 46387 | C37: 1.0853 | D37: 0.8409 | E37: 0.878
A40: Mese | B40: 1 | C40: 2 | D40: 3 | E40: 4 | F40: 5 | G40: 6 | H40: 7 | I40: 8 | J40: 9 | K40: 10 | L40: 11 | M40: 12 | N40: 13 | O40: 14 | P40: 15 | Q40: 16 | R40: 17 | S40: 18 | T40: 19 | U40: 20 | V40: 21 | W40: 22 | X40: 23 | Y40: 24 | Z40: 25 | AA40: 26 | AB40: 27 | AC40: 28 | AD40: 29 | AE40: 30 | AF40: 31 | AG40: 32 | AH40: 33 | AI40: 34 | AJ40: 35 | AK40: 36
A41: USD | B41: 1.058 | C41: 1.0658 | D41: 1.0729 | E41: 1.0791 | F41: 1.0842 | G41: 1.0879 | H41: 1.0901 | I41: 1.0908 | J41: 1.0899 | K41: 1.0874 | L41: 1.0834 | M41: 1.0782 | N41: 1.0719 | O41: 1.0648 | P41: 1.0571 | Q41: 1.0493 | R41: 1.0415 | S41: 1.0341 | T41: 1.0274 | U41: 1.0217 | V41: 1.0172 | W41: 1.0141 | X41: 1.0126 | Y41: 1.0126 | Z41: 1.0141 | AA41: 1.0173 | AB41: 1.0218 | AC41: 1.0275 | AD41: 1.0343 | AE41: 1.0418 | AF41: 1.0498 | AG41: 1.0579 | AH41: 1.0658 | AI41: 1.0732 | AJ41: 1.0798 | AK41: 1.0853
A42: GBP | B42: 0.8597 | C42: 0.8588 | D42: 0.8573 | E42: 0.8554 | F42: 0.8532 | G42: 0.8507 | H42: 0.8482 | I42: 0.8458 | J42: 0.8437 | K42: 0.842 | L42: 0.8408 | M42: 0.8401 | N42: 0.8401 | O42: 0.8406 | P42: 0.8418 | Q42: 0.8435 | R42: 0.8455 | S42: 0.8479 | T42: 0.8504 | U42: 0.8528 | V42: 0.8551 | W42: 0.8571 | X42: 0.8586 | Y42: 0.8596 | Z42: 0.86 | AA42: 0.8598 | AB42: 0.8589 | AC42: 0.8575 | AD42: 0.8557 | AE42: 0.8535 | AF42: 0.851 | AG42: 0.8485 | AH42: 0.8461 | AI42: 0.844 | AJ42: 0.8422 | AK42: 0.8409
A43: CHF | B43: 0.948 | C43: 0.946 | D43: 0.944 | E43: 0.942 | F43: 0.94 | G43: 0.938 | H43: 0.936 | I43: 0.934 | J43: 0.932 | K43: 0.93 | L43: 0.928 | M43: 0.926 | N43: 0.924 | O43: 0.922 | P43: 0.92 | Q43: 0.918 | R43: 0.916 | S43: 0.914 | T43: 0.912 | U43: 0.91 | V43: 0.908 | W43: 0.906 | X43: 0.904 | Y43: 0.902 | Z43: 0.9 | AA43: 0.898 | AB43: 0.896 | AC43: 0.894 | AD43: 0.892 | AE43: 0.89 | AF43: 0.888 | AG43: 0.886 | AH43: 0.884 | AI43: 0.882 | AJ43: 0.88 | AK43: 0.878

Sheet Budget
A1: Budget volumi | B1: 1 | C1: 2 | D1: 3 | E1: 4 | F1: 5 | G1: 6 | H1: 7 | I1: 8 | J1: 9 | K1: 10 | L1: 11 | M1: 12 | N1: 13 | O1: 14 | P1: 15 | Q1: 16 | R1: 17 | S1: 18 | T1: 19 | U1: 20 | V1: 21 | W1: 22 | X1: 23 | Y1: 24 | Z1: 25 | AA1: 26 | AB1: 27 | AC1: 28 | AD1: 29 | AE1: 30 | AF1: 31 | AG1: 32 | AH1: 33 | AI1: 34 | AJ1: 35 | AK1: 36
A2: Banca Alpi | B2: 5973 | C2: 6027 | D2: 6080 | E2: 6133 | F2: 6186 | G2: 6240 | H2: 6293 | I2: 6346 | J2: 6400 | K2: 6453 | L2: 6506 | M2: 6559 | N2: 6613 | O2: 6666 | P2: 6719 | Q2: 6772 | R2: 6826 | S2: 6879 | T2: 6932 | U2: 6986 | V2: 7039 | W2: 7092 | X2: 7145 | Y2: 7199 | Z2: 7252 | AA2: 7305 | AB2: 7359 | AC2: 7412 | AD2: 7465 | AE2: 7518 | AF2: 7572 | AG2: 7625 | AH2: 7678 | AI2: 7732 | AJ2: 7785 | AK2: 7838
A3: Banca Adriatica | B3: 6996 | C3: 7059 | D3: 7121 | E3: 7183 | F3: 7246 | G3: 7308 | H3: 7371 | I3: 7433 | J3: 7495 | K3: 7558 | L3: 7620 | M3: 7683 | N3: 7745 | O3: 7807 | P3: 7870 | Q3: 7932 | R3: 7995 | S3: 8057 | T3: 8119 | U3: 8182 | V3: 8244 | W3: 8307 | X3: 8369 | Y3: 8432 | Z3: 8494 | AA3: 8556 | AB3: 8619 | AC3: 8681 | AD3: 8744 | AE3: 8806 | AF3: 8868 | AG3: 8931 | AH3: 8993 | AI3: 9056 | AJ3: 9118 | AK3: 9180
A4: Banca Tirrena | B4: 8019 | C4: 8091 | D4: 8162 | E4: 8234 | F4: 8305 | G4: 8377 | H4: 8448 | I4: 8520 | J4: 8591 | K4: 8663 | L4: 8734 | M4: 8806 | N4: 8877 | O4: 8949 | P4: 9021 | Q4: 9092 | R4: 9164 | S4: 9235 | T4: 9307 | U4: 9378 | V4: 9450 | W4: 9521 | X4: 9593 | Y4: 9664 | Z4: 9736 | AA4: 9807 | AB4: 9879 | AC4: 9950 | AD4: 10022 | AE4: 10093 | AF4: 10165 | AG4: 10237 | AH4: 10308 | AI4: 10380 | AJ4: 10451 | AK4: 10523
A5: Banca Padana | B5: 9042 | C5: 9123 | D5: 9203 | E5: 9284 | F5: 9365 | G5: 9445 | H5: 9526 | I5: 9607 | J5: 9687 | K5: 9768 | L5: 9849 | M5: 9929 | N5: 10010 | O5: 10091 | P5: 10171 | Q5: 10252 | R5: 10332 | S5: 10413 | T5: 10494 | U5: 10574 | V5: 10655 | W5: 10736 | X5: 10816 | Y5: 10897 | Z5: 10978 | AA5: 11058 | AB5: 11139 | AC5: 11220 | AD5: 11300 | AE5: 11381 | AF5: 11462 | AG5: 11542 | AH5: 11623 | AI5: 11704 | AJ5: 11784 | AK5: 11865
A6: Banca Etrusca | B6: 10065 | C6: 10155 | D6: 10245 | E6: 10334 | F6: 10424 | G6: 10514 | H6: 10604 | I6: 10693 | J6: 10783 | K6: 10873 | L6: 10963 | M6: 11053 | N6: 11142 | O6: 11232 | P6: 11322 | Q6: 11412 | R6: 11501 | S6: 11591 | T6: 11681 | U6: 11771 | V6: 11861 | W6: 11950 | X6: 12040 | Y6: 12130 | Z6: 12220 | AA6: 12309 | AB6: 12399 | AC6: 12489 | AD6: 12579 | AE6: 12669 | AF6: 12758 | AG6: 12848 | AH6: 12938 | AI6: 13028 | AJ6: 13117 | AK6: 13207
A7: Banca Lariana | B7: 11088 | C7: 11187 | D7: 11286 | E7: 11385 | F7: 11484 | G7: 11582 | H7: 11681 | I7: 11780 | J7: 11879 | K7: 11978 | L7: 12077 | M7: 12176 | N7: 12275 | O7: 12374 | P7: 12473 | Q7: 12571 | R7: 12670 | S7: 12769 | T7: 12868 | U7: 12967 | V7: 13066 | W7: 13165 | X7: 13264 | Y7: 13363 | Z7: 13462 | AA7: 13560 | AB7: 13659 | AC7: 13758 | AD7: 13857 | AE7: 13956 | AF7: 14055 | AG7: 14154 | AH7: 14253 | AI7: 14352 | AJ7: 14451 | AK7: 14549
A8: Banca Sabina | B8: 12111 | C8: 12219 | D8: 12327 | E8: 12435 | F8: 12543 | G8: 12651 | H8: 12759 | I8: 12867 | J8: 12975 | K8: 13083 | L8: 13191 | M8: 13299 | N8: 13407 | O8: 13515 | P8: 13623 | Q8: 13731 | R8: 13839 | S8: 13947 | T8: 14055 | U8: 14163 | V8: 14271 | W8: 14379 | X8: 14487 | Y8: 14595 | Z8: 14703 | AA8: 14811 | AB8: 14919 | AC8: 15028 | AD8: 15136 | AE8: 15244 | AF8: 15352 | AG8: 15460 | AH8: 15568 | AI8: 15676 | AJ8: 15784 | AK8: 15892
A9: Banca Irpina | B9: 13134 | C9: 13251 | D9: 13368 | E9: 13485 | F9: 13602 | G9: 13719 | H9: 13837 | I9: 13954 | J9: 14071 | K9: 14188 | L9: 14305 | M9: 14422 | N9: 14540 | O9: 14657 | P9: 14774 | Q9: 14891 | R9: 15008 | S9: 15125 | T9: 15242 | U9: 15360 | V9: 15477 | W9: 15594 | X9: 15711 | Y9: 15828 | Z9: 15945 | AA9: 16062 | AB9: 16180 | AC9: 16297 | AD9: 16414 | AE9: 16531 | AF9: 16648 | AG9: 16765 | AH9: 16883 | AI9: 17000 | AJ9: 17117 | AK9: 17234
A10: Banca Sannita | B10: 14157 | C10: 14283 | D10: 14409 | E10: 14535 | F10: 14662 | G10: 14788 | H10: 14914 | I10: 15041 | J10: 15167 | K10: 15293 | L10: 15419 | M10: 15546 | N10: 15672 | O10: 15798 | P10: 15925 | Q10: 16051 | R10: 16177 | S10: 16303 | T10: 16430 | U10: 16556 | V10: 16682 | W10: 16808 | X10: 16935 | Y10: 17061 | Z10: 17187 | AA10: 17314 | AB10: 17440 | AC10: 17566 | AD10: 17692 | AE10: 17819 | AF10: 17945 | AG10: 18071 | AH10: 18197 | AI10: 18324 | AJ10: 18450 | AK10: 18576
A11: Banca Ligure | B11: 15180 | C11: 15315 | D11: 15450 | E11: 15586 | F11: 15721 | G11: 15857 | H11: 15992 | I11: 16127 | J11: 16263 | K11: 16398 | L11: 16534 | M11: 16669 | N11: 16804 | O11: 16940 | P11: 17075 | Q11: 17211 | R11: 17346 | S11: 17481 | T11: 17617 | U11: 17752 | V11: 17888 | W11: 18023 | X11: 18158 | Y11: 18294 | Z11: 18429 | AA11: 18565 | AB11: 18700 | AC11: 18835 | AD11: 18971 | AE11: 19106 | AF11: 19242 | AG11: 19377 | AH11: 19512 | AI11: 19648 | AJ11: 19783 | AK11: 19919
A12: Banca Veneta | B12: 16203 | C12: 16347 | D12: 16492 | E12: 16636 | F12: 16781 | G12: 16925 | H12: 17070 | I12: 17214 | J12: 17359 | K12: 17503 | L12: 17648 | M12: 17792 | N12: 17937 | O12: 18081 | P12: 18226 | Q12: 18370 | R12: 18515 | S12: 18659 | T12: 18804 | U12: 18948 | V12: 19093 | W12: 19237 | X12: 19382 | Y12: 19527 | Z12: 19671 | AA12: 19816 | AB12: 19960 | AC12: 20105 | AD12: 20249 | AE12: 20394 | AF12: 20538 | AG12: 20683 | AH12: 20827 | AI12: 20972 | AJ12: 21116 | AK12: 21261
... A44: Banca Città | B44: 1321.3 | C44: 1333 | D44: 1344.8 | E44: 1356.6 | F44: 1368.4 | G44: 1380.2 | H44: 1392 | I44: 1403.8 | J44: 1415.5 | K44: 1427.3 | L44: 1439.1 | M44: 1450.9 | N44: 1462.7 | O44: 1474.5 | P44: 1486.3 | Q44: 1498 | R44: 1509.8 | S44: 1521.6 | T44: 1533.4 | U44: 1545.2 | V44: 1557 | W44: 1568.8 | X44: 1580.5 | Y44: 1592.3 | Z44: 1604.1 | AA44: 1615.9 | AB44: 1627.7 | AC44: 1639.5 | AD44: 1651.2 | AE44: 1663 | AF44: 1674.8 | AG44: 1686.6 | AH44: 1698.4 | AI44: 1710.2 | AJ44: 1722 | AK44: 1733.7

Sheet Products
A1: Prodotto | B1: Categoria | C1: Peso margine | D1: Codice
A2: Mutui | B2: Credito | C2: 0.6 | D2: P1
A3: Prestiti | B3: Credito | C3: 0.65 | D3: P2
A4: Conti | B4: Raccolta | C4: 0.7 | D4: P3
A5: Carte | B5: Servizi | C5: 0.75 | D5: P4
A6: Leasing | B6: Credito | C6: 0.8 | D6: P5
A7: Factoring | B7: Credito | C7: 0.85 | D7: P6
A8: Risparmio | B8: Raccolta | C8: 0.9 | D8: P7
A9: Assicurazioni | B9: Servizi | C9: 0.95 | D9: P8

Sheet Aree
A1: Regione | B1: Responsabile | C1: Obiettivo
A2: Nord-Ovest | B2: Galli | C2: 42000
A3: Nord-Est | B3: Fontana | C3: 30000
A4: Centro | B4: Santoro | C4: 47000
A5: Sud | B5: Marini | C5: 26000
A6: Isole | B6: Caruso | C6: 16000

Sheet Calc_Month
A1: Mese | B1: Data | C1: Volumi | D1: Ricavi | E1: Costi | F1: Clienti | G1: Margine | H1: Budget | I1: Scost. % | J1: YTD volumi | K1: Anno | L1: Media mobile 3m | M1: Volumi USD | N1: Scenario | O1: Rango | P1: Var. m/m | Q1: Cost/income | R1: Ricavo/cliente | S1: Esito | T1: Trimestre | U1: Media 12m
A2: =ROW()-1 -> 1 | B2: =EOMONTH(DATE(2024,A2,1),0) -> 45322 | C2: =SUMIFS(Data!$E$2:$E$5761,Data!$A$2:$A$5761,Control!$B$2,Data!$B$2:$B$5761,A2) -> 8012.1 | D2: =SUMIFS(Data!$F$2:$F$5761,Data!$A$2:$A$5761,Control!$B$2,Data!$B$2:$B$5761,A2) -> 433.36 | E2: =SUMIFS(Data!$G$2:$G$5761,Data!$A$2:$A$5761,Control!$B$2,Data!$B$2:$B$5761,A2) -> 263.59 | F2: =SUMIFS(Data!$H$2:$H$5761,Data!$A$2:$A$5761,Control!$B$2,Data!$B$2:$B$5761,A2) -> 980 | G2: =D2-E2 -> 169.77 | H2: {=INDEX(Budget!$B$2:$AK$21,Control!$B$6,MATCH(A2,Budget!$B$1:$AK$1,0))} -> 8019 | I2: =IFERROR(C2/H2-1,0) -> -0.00086045642 | J2: =SUMIFS($C$2:$C$37,$K$2:$K$37,K2,$A$2:$A$37,"<="&A2) -> 8012.1 | K2: =YEAR(B2) -> 2024 | L2: =AVERAGE(OFFSET(C2,-MIN(2,A2-1),0,MIN(3,A2),1)) -> 8012.1 | M2: =C2*_xlfn.XLOOKUP(A2,FX!$A$2:$A$37,FX!$C$2:$C$37) -> 8476.8018 | N2: =C2*(1+Control!$B$4)^(A2/12) -> 8031.86 | O2: =RANK(C2,$C$2:$C$37,0) -> 36 | P2: =IFERROR(C2-C1,0) -> 0 | Q2: =IFERROR(E2/D2,0) -> 0.60824718 | R2: =ROUND(IFERROR(D2/F2,0),2) -> 0.44 | S2: =IF(AND(I2>0,G2>0),"sopra",IF(OR(I2<-0.05,G2<0),"sotto","in linea")) -> in linea | T2: ="T"&ROUNDUP(MONTH(B2)/3,0)&"-"&YEAR(B2) -> T1-2024 | U2: =AVERAGEIFS($C$2:$C$37,$A$2:$A$37,">"&(A2-12),$A$2:$A$37,"<="&A2) -> 8012.1
A3: =ROW()-1 -> 2 | B3: =EOMONTH(DATE(2024,A3,1),0) -> 45351 | C3: =SUMIFS(Data!$E$2:$E$5761,Data!$A$2:$A$5761,Control!$B$2,Data!$B$2:$B$5761,A3) -> 8126.5 | D3: =SUMIFS(Data!$F$2:$F$5761,Data!$A$2:$A$5761,Control!$B$2,Data!$B$2:$B$5761,A3) -> 440.86 | E3: =SUMIFS(Data!$G$2:$G$5761,Data!$A$2:$A$5761,Control!$B$2,Data!$B$2:$B$5761,A3) -> 266.66 | F3: =SUMIFS(Data!$H$2:$H$5761,Data!$A$2:$A$5761,Control!$B$2,Data!$B$2:$B$5761,A3) -> 951 | G3: =D3-E3 -> 174.2 | H3: {=INDEX(Budget!$B$2:$AK$21,Control!$B$6,MATCH(A3,Budget!$B$1:$AK$1,0))} -> 8091 | I3: =IFERROR(C3/H3-1,0) -> 0.0043875912 | J3: =SUMIFS($C$2:$C$37,$K$2:$K$37,K3,$A$2:$A$37,"<="&A3) -> 16138.6 | K3: =YEAR(B3) -> 2024 | L3: =AVERAGE(OFFSET(C3,-MIN(2,A3-1),0,MIN(3,A3),1)) -> 8069.3 | M3: =C3*_xlfn.XLOOKUP(A3,FX!$A$2:$A$37,FX!$C$2:$C$37) -> 8661.2237 | N3: =C3*(1+Control!$B$4)^(A3/12) -> 8166.6337 | O3: =RANK(C3,$C$2:$C$37,0) -> 35 | P3: =IFERROR(C3-C2,0) -> 114.4 | Q3: =IFERROR(E3/D3,0) -> 0.60486322 | R3: =ROUND(IFERROR(D3/F3,0),2) -> 0.46 | S3: =IF(AND(I3>0,G3>0),"sopra",IF(OR(I3<-0.05,G3<0),"sotto","in linea")) -> sopra | T3: ="T"&ROUNDUP(MONTH(B3)/3,0)&"-"&YEAR(B3) -> T1-2024 | U3: =AVERAGEIFS($C$2:$C$37,$A$2:$A$37,">"&(A3-12),$A$2:$A$37,"<="&A3) -> 8069.3
A4: =ROW()-1 -> 3 | B4: =EOMONTH(DATE(2024,A4,1),0) -> 45382 | C4: =SUMIFS(Data!$E$2:$E$5761,Data!$A$2:$A$5761,Control!$B$2,Data!$B$2:$B$5761,A4) -> 8163.5 | D4: =SUMIFS(Data!$F$2:$F$5761,Data!$A$2:$A$5761,Control!$B$2,Data!$B$2:$B$5761,A4) -> 443.09 | E4: =SUMIFS(Data!$G$2:$G$5761,Data!$A$2:$A$5761,Control!$B$2,Data!$B$2:$B$5761,A4) -> 268.36 | F4: =SUMIFS(Data!$H$2:$H$5761,Data!$A$2:$A$5761,Control!$B$2,Data!$B$2:$B$5761,A4) -> 906 | G4: =D4-E4 -> 174.73 | H4: {=INDEX(Budget!$B$2:$AK$21,Control!$B$6,MATCH(A4,Budget!$B$1:$AK$1,0))} -> 8162 | I4: =IFERROR(C4/H4-1,0) -> 0.00018377849 | J4: =SUMIFS($C$2:$C$37,$K$2:$K$37,K4,$A$2:$A$37,"<="&A4) -> 24302.1 | K4: =YEAR(B4) -> 2024 | L4: =AVERAGE(OFFSET(C4,-MIN(2,A4-1),0,MIN(3,A4),1)) -> 8100.7 | M4: =C4*_xlfn.XLOOKUP(A4,FX!$A$2:$A$37,FX!$C$2:$C$37) -> 8758.6192 | N4: =C4*(1+Control!$B$4)^(A4/12) -> 8224.0493 | O4: =RANK(C4,$C$2:$C$37,0) -> 34 | P4: =IFERROR(C4-C3,0) -> 37 | Q4: =IFERROR(E4/D4,0) -> 0.60565574 | R4: =ROUND(IFERROR(D4/F4,0),2) -> 0.49 | S4: =IF(AND(I4>0,G4>0),"sopra",IF(OR(I4<-0.05,G4<0),"sotto","in linea")) -> sopra | T4: ="T"&ROUNDUP(MONTH(B4)/3,0)&"-"&YEAR(B4) -> T1-2024 | U4: =AVERAGEIFS($C$2:$C$37,$A$2:$A$37,">"&(A4-12),$A$2:$A$37,"<="&A4) -> 8100.7
A5: =ROW()-1 -> 4 | B5: =EOMONTH(DATE(2024,A5,1),0) -> 45412 | C5: =SUMIFS(Data!$E$2:$E$5761,Data!$A$2:$A$5761,Control!$B$2,Data!$B$2:$B$5761,A5) -> 8209.7 | D5: =SUMIFS(Data!$F$2:$F$5761,Data!$A$2:$A$5761,Control!$B$2,Data!$B$2:$B$5761,A5) -> 444.15 | E5: =SUMIFS(Data!$G$2:$G$5761,Data!$A$2:$A$5761,Control!$B$2,Data!$B$2:$B$5761,A5) -> 268.62 | F5: =SUMIFS(Data!$H$2:$H$5761,Data!$A$2:$A$5761,Control!$B$2,Data!$B$2:$B$5761,A5) -> 925 | G5: =D5-E5 -> 175.53 | H5: {=INDEX(Budget!$B$2:$AK$21,Control!$B$6,MATCH(A5,Budget!$B$1:$AK$1,0))} -> 8234 | I5: =IFERROR(C5/H5-1,0) -> -0.002951178 | J5: =SUMIFS($C$2:$C$37,$K$2:$K$37,K5,$A$2:$A$37,"<="&A5) -> 32511.8 | K5: =YEAR(B5) -> 2024 | L5: =AVERAGE(OFFSET(C5,-MIN(2,A5-1),0,MIN(3,A5),1)) -> 8166.5667 | M5: =C5*_xlfn.XLOOKUP(A5,FX!$A$2:$A$37,FX!$C$2:$C$37) -> 8859.0873 | N5: =C5*(1+Control!$B$4)^(A5/12) -> 8290.9894 | O5: =RANK(C5,$C$2:$C$37,0) -> 33 | P5: =IFERROR(C5-C4,0) -> 46.2 | Q5: =IFERROR(E5/D5,0) -> 0.60479568 | R5: =ROUND(IFERROR(D5/F5,0),2) -> 0.48 | S5: =IF(AND(I5>0,G5>0),"sopra",IF(OR(I5<-0.05,G5<0),"sotto","in linea")) -> in linea | T5: ="T"&ROUNDUP(MONTH(B5)/3,0)&"-"&YEAR(B5) -> T2-2024 | U5: =AVERAGEIFS($C$2:$C$37,$A$2:$A$37,">"&(A5-12),$A$2:$A$37,"<="&A5) -> 8127.95
A6: =ROW()-1 -> 5 | B6: =EOMONTH(DATE(2024,A6,1),0) -> 45443 | C6: =SUMIFS(Data!$E$2:$E$5761,Data!$A$2:$A$5761,Control!$B$2,Data!$B$2:$B$5761,A6) -> 8325.2 | D6: =SUMIFS(Data!$F$2:$F$5761,Data!$A$2:$A$5761,Control!$B$2,Data!$B$2:$B$5761,A6) -> 451.45 | E6: =SUMIFS(Data!$G$2:$G$5761,Data!$A$2:$A$5761,Control!$B$2,Data!$B$2:$B$5761,A6) -> 271.5 | F6: =SUMIFS(Data!$H$2:$H$5761,Data!$A$2:$A$5761,Control!$B$2,Data!$B$2:$B$5761,A6) -> 901 | G6: =D6-E6 -> 179.95 | H6: {=INDEX(Budget!$B$2:$AK$21,Control!$B$6,MATCH(A6,Budget!$B$1:$AK$1,0))} -> 8305 | I6: =IFERROR(C6/H6-1,0) -> 0.0024322697 | J6: =SUMIFS($C$2:$C$37,$K$2:$K$37,K6,$A$2:$A$37,"<="&A6) -> 40837 | K6: =YEAR(B6) -> 2024 | L6: =AVERAGE(OFFSET(C6,-MIN(2,A6-1),0,MIN(3,A6),1)) -> 8232.8 | M6: =C6*_xlfn.XLOOKUP(A6,FX!$A$2:$A$37,FX!$C$2:$C$37) -> 9026.1818 | N6: =C6*(1+Control!$B$4)^(A6/12) -> 8428.3686 | O6: =RANK(C6,$C$2:$C$37,0) -> 32 | P6: =IFERROR(C6-C5,0) -> 115.5 | Q6: =IFERROR(E6/D6,0) -> 0.6013955 | R6: =ROUND(IFERROR(D6/F6,0),2) -> 0.5 | S6: =IF(AND(I6>0,G6>0),"sopra",IF(OR(I6<-0.05,G6<0),"sotto","in linea")) -> sopra | T6: ="T"&ROUNDUP(MONTH(B6)/3,0)&"-"&YEAR(B6) -> T2-2024 | U6: =AVERAGEIFS($C$2:$C$37,$A$2:$A$37,">"&(A6-12),$A$2:$A$37,"<="&A6) -> 8167.4
A7: =ROW()-1 -> 6 | B7: =EOMONTH(DATE(2024,A7,1),0) -> 45473 | C7: =SUMIFS(Data!$E$2:$E$5761,Data!$A$2:$A$5761,Control!$B$2,Data!$B$2:$B$5761,A7) -> 8343.3 | D7: =SUMIFS(Data!$F$2:$F$5761,Data!$A$2:$A$5761,Control!$B$2,Data!$B$2:$B$5761,A7) -> 451.67 | E7: =SUMIFS(Data!$G$2:$G$5761,Data!$A$2:$A$5761,Control!$B$2,Data!$B$2:$B$5761,A7) -> 275.01 | F7: =SUMIFS(Data!$H$2:$H$5761,Data!$A$2:$A$5761,Control!$B$2,Data!$B$2:$B$5761,A7) -> 974 | G7: =D7-E7 -> 176.66 | H7: {=INDEX(Budget!$B$2:$AK$21,Control!$B$6,MATCH(A7,Budget!$B$1:$AK$1,0))} -> 8377 | I7: =IFERROR(C7/H7-1,0) -> -0.0040229199 | J7: =SUMIFS($C$2:$C$37,$K$2:$K$37,K7,$A$2:$A$37,"<="&A7) -> 49180.3 | K7: =YEAR(B7) -> 2024 | L7: =AVERAGE(OFFSET(C7,-MIN(2,A7-1),0,MIN(3,A7),1)) -> 8292.7333 | M7: =C7*_xlfn.XLOOKUP(A7,FX!$A$2:$A$37,FX!$C$2:$C$37) -> 9076.6761 | N7: =C7*(1+Control!$B$4)^(A7/12) -> 8467.5247 | O7: =RANK(C7,$C$2:$C$37,0) -> 31 | P7: =IFERROR(C7-C6,0) -> 18.1 | Q7: =IFERROR(E7/D7,0) -> 0.60887374 | R7: =ROUND(IFERROR(D7/F7,0),2) -> 0.46 | S7: =IF(AND(I7>0,G7>0),"sopra",IF(OR(I7<-0.05,G7<0),"sotto","in linea")) -> in linea | T7: ="T"&ROUNDUP(MONTH(B7)/3,0)&"-"&YEAR(B7) -> T2-2024 | U7: =AVERAGEIFS($C$2:$C$37,$A$2:$A$37,">"&(A7-12),$A$2:$A$37,"<="&A7) -> 8196.7167
A8: =ROW()-1 -> 7 | B8: =EOMONTH(DATE(2024,A8,1),0) -> 45504 | C8: =SUMIFS(Data!$E$2:$E$5761,Data!$A$2:$A$5761,Control!$B$2,Data!$B$2:$B$5761,A8) -> 8405 | D8: =SUMIFS(Data!$F$2:$F$5761,Data!$A$2:$A$5761,Control!$B$2,Data!$B$2:$B$5761,A8) -> 455.92 | E8: =SUMIFS(Data!$G$2:$G$5761,Data!$A$2:$A$5761,Control!$B$2,Data!$B$2:$B$5761,A8) -> 276.09 | F8: =SUMIFS(Data!$H$2:$H$5761,Data!$A$2:$A$5761,Control!$B$2,Data!$B$2:$B$5761,A8) -> 935 | G8: =D8-E8 -> 179.83 | H8: {=INDEX(Budget!$B$2:$AK$21,Control!$B$6,MATCH(A8,Budget!$B$1:$AK$1,0))} -> 8448 | I8: =IFERROR(C8/H8-1,0) -> -0.0050899621 | J8: =SUMIFS($C$2:$C$37,$K$2:$K$37,K8,$A$2:$A$37,"<="&A8) -> 57585.3 | K8: =YEAR(B8) -> 2024 | L8: =AVERAGE(OFFSET(C8,-MIN(2,A8-1),0,MIN(3,A8),1)) -> 8357.8333 | M8: =C8*_xlfn.XLOOKUP(A8,FX!$A$2:$A$37,FX!$C$2:$C$37) -> 9162.2905 | N8: =C8*(1+Control!$B$4)^(A8/12) -> 8551.181 | O8: =RANK(C8,$C$2:$C$37,0) -> 30 | P8: =IFERROR(C8-C7,0) -> 61.7 | Q8: =IFERROR(E8/D8,0) -> 0.60556677 | R8: =ROUND(IFERROR(D8/F8,0),2) -> 0.49 | S8: =IF(AND(I8>0,G8>0),"sopra",IF(OR(I8<-0.05,G8<0),"sotto","in linea")) -> in linea | T8: ="T"&ROUNDUP(MONTH(B8)/3,0)&"-"&YEAR(B8) -> T3-2024 | U8: =AVERAGEIFS($C$2:$C$37,$A$2:$A$37,">"&(A8-12),$A$2:$A$37,"<="&A8) -> 8226.4714
A9: =ROW()-1 -> 8 | B9: =EOMONTH(DATE(2024,A9,1),0) -> 45535 | C9: =SUMIFS(Data!$E$2:$E$5761,Data!$A$2:$A$5761,Control!$B$2,Data!$B$2:$B$5761,A9) -> 8440.6 | D9: =SUMIFS(Data!$F$2:$F$5761,Data!$A$2:$A$5761,Control!$B$2,Data!$B$2:$B$5761,A9) -> 457.53 | E9: =SUMIFS(Data!$G$2:$G$5761,Data!$A$2:$A$5761,Control!$B$2,Data!$B$2:$B$5761,A9) -> 276.42 | F9: =SUMIFS(Data!$H$2:$H$5761,Data!$A$2:$A$5761,Control!$B$2,Data!$B$2:$B$5761,A9) -> 937 | G9: =D9-E9 -> 181.11 | H9: {=INDEX(Budget!$B$2:$AK$21,Control!$B$6,MATCH(A9,Budget!$B$1:$AK$1,0))} -> 8520 | I9: =IFERROR(C9/H9-1,0) -> -0.0093192488 | J9: =SUMIFS($C$2:$C$37,$K$2:$K$37,K9,$A$2:$A$37,"<="&A9) -> 66025.9 | K9: =YEAR(B9) -> 2024 | L9: =AVERAGE(OFFSET(C9,-MIN(2,A9-1),0,MIN(3,A9),1)) -> 8396.3 | M9: =C9*_xlfn.XLOOKUP(A9,FX!$A$2:$A$37,FX!$C$2:$C$37) -> 9207.0065 | N9: =C9*(1+Control!$B$4)^(A9/12) -> 8608.579 | O9: =RANK(C9,$C$2:$C$37,0) -> 29 | P9: =IFERROR(C9-C8,0) -> 35.6 | Q9: =IFERROR(E9/D9,0) -> 0.6041571 | R9: =ROUND(IFERROR(D9/F9,0),2) -> 0.49 | S9: =IF(AND(I9>0,G9>0),"sopra",IF(OR(I9<-0.05,G9<0),"sotto","in linea")) -> in linea | T9: ="T"&ROUNDUP(MONTH(B9)/3,0)&"-"&YEAR(B9) -> T3-2024 | U9: =AVERAGEIFS($C$2:$C$37,$A$2:$A$37,">"&(A9-12),$A$2:$A$37,"<="&A9) -> 8253.2375
A10: =ROW()-1 -> 9 | B10: =EOMONTH(DATE(2024,A10,1),0) -> 45565 | C10: =SUMIFS(Data!$E$2:$E$5761,Data!$A$2:$A$5761,Control!$B$2,Data!$B$2:$B$5761,A10) -> 8499.6 | D10: =SUMIFS(Data!$F$2:$F$5761,Data!$A$2:$A$5761,Control!$B$2,Data!$B$2:$B$5761,A10) -> 458.84 | E10: =SUMIFS(Data!$G$2:$G$5761,Data!$A$2:$A$5761,Control!$B$2,Data!$B$2:$B$5761,A10) -> 279.94 | F10: =SUMIFS(Data!$H$2:$H$5761,Data!$A$2:$A$5761,Control!$B$2,Data!$B$2:$B$5761,A10) -> 994 | G10: =D10-E10 -> 178.9 | H10: {=INDEX(Budget!$B$2:$AK$21,Control!$B$6,MATCH(A10,Budget!$B$1:$AK$1,0))} -> 8591 | I10: =IFERROR(C10/H10-1,0) -> -0.010639041 | J10: =SUMIFS($C$2:$C$37,$K$2:$K$37,K10,$A$2:$A$37,"<="&A10) -> 74525.5 | K10: =YEAR(B10) -> 2024 | L10: =AVERAGE(OFFSET(C10,-MIN(2,A10-1),0,MIN(3,A10),1)) -> 8448.4 | M10: =C10*_xlfn.XLOOKUP(A10,FX!$A$2:$A$37,FX!$C$2:$C$37) -> 9263.714 | N10: =C10*(1+Control!$B$4)^(A10/12) -> 8690.1327 | O10: =RANK(C10,$C$2:$C$37,0) -> 28 | P10: =IFERROR(C10-C9,0) -> 59 | Q10: =IFERROR(E10/D10,0) -> 0.61010374 | R10: =ROUND(IFERROR(D10/F10,0),2) -> 0.46 | S10: =IF(AND(I10>0,G10>0),"sopra",IF(OR(I10<-0.05,G10<0),"sotto","in linea")) -> in linea | T10: ="T"&ROUNDUP(MONTH(B10)/3,0)&"-"&YEAR(B10) -> T3-2024 | U10: =AVERAGEIFS($C$2:$C$37,$A$2:$A$37,">"&(A10-12),$A$2:$A$37,"<="&A10) -> 8280.6111
A11: =ROW()-1 -> 10 | B11: =EOMONTH(DATE(2024,A11,1),0) -> 45596 | C11: =SUMIFS(Data!$E$2:$E$5761,Data!$A$2:$A$5761,Control!$B$2,Data!$B$2:$B$5761,A11) -> 8590.6 | D11: =SUMIFS(Data!$F$2:$F$5761,Data!$A$2:$A$5761,Control!$B$2,Data!$B$2:$B$5761,A11) -> 465 | E11: =SUMIFS(Data!$G$2:$G$5761,Data!$A$2:$A$5761,Control!$B$2,Data!$B$2:$B$5761,A11) -> 281.33 | F11: =SUMIFS(Data!$H$2:$H$5761,Data!$A$2:$A$5761,Control!$B$2,Data!$B$2:$B$5761,A11) -> 965 | G11: =D11-E11 -> 183.67 | H11: {=INDEX(Budget!$B$2:$AK$21,Control!$B$6,MATCH(A11,Budget!$B$1:$AK$1,0))} -> 8663 | I11: =IFERROR(C11/H11-1,0) -> -0.008357382 | J11: =SUMIFS($C$2:$C$37,$K$2:$K$37,K11,$A$2:$A$37,"<="&A11) -> 83116.1 | K11: =YEAR(B11) -> 2024 | L11: =AVERAGE(OFFSET(C11,-MIN(2,A11-1),0,MIN(3,A11),1)) -> 8510.2667 | M11: =C11*_xlfn.XLOOKUP(A11,FX!$A$2:$A$37,FX!$C$2:$C$37) -> 9341.4184 | N11: =C11*(1+Control!$B$4)^(A11/12) -> 8804.8343 | O11: =RANK(C11,$C$2:$C$37,0) -> 27 | P11: =IFERROR(C11-C10,0) -> 91 | Q11: =IFERROR(E11/D11,0) -> 0.60501075 | R11: =ROUND(IFERROR(D11/F11,0),2) -> 0.48 | S11: =IF(AND(I11>0,G11>0),"sopra",IF(OR(I11<-0.05,G11<0),"sotto","in linea")) -> in linea | T11: ="T"&ROUNDUP(MONTH(B11)/3,0)&"-"&YEAR(B11) -> T4-2024 | U11: =AVERAGEIFS($C$2:$C$37,$A$2:$A$37,">"&(A11-12),$A$2:$A$37,"<="&A11) -> 8311.61
A12: =ROW()-1 -> 11 | B12: =EOMONTH(DATE(2024,A12,1),0) -> 45626 | C12: =SUMIFS(Data!$E$2:$E$5761,Data!$A$2:$A$5761,Control!$B$2,Data!$B$2:$B$5761,A12) -> 8644.9 | D12: =SUMIFS(Data!$F$2:$F$5761,Data!$A$2:$A$5761,Control!$B$2,Data!$B$2:$B$5761,A12) -> 468.26 | E12: =SUMIFS(Data!$G$2:$G$5761,Data!$A$2:$A$5761,Control!$B$2,Data!$B$2:$B$5761,A12) -> 284.77 | F12: =SUMIFS(Data!$H$2:$H$5761,Data!$A$2:$A$5761,Control!$B$2,Data!$B$2:$B$5761,A12) -> 927 | G12: =D12-E12 -> 183.49 | H12: {=INDEX(Budget!$B$2:$AK$21,Control!$B$6,MATCH(A12,Budget!$B$1:$AK$1,0))} -> 8734 | I12: =IFERROR(C12/H12-1,0) -> -0.010201511 | J12: =SUMIFS($C$2:$C$37,$K$2:$K$37,K12,$A$2:$A$37,"<="&A12) -> 91761 | K12: =YEAR(B12) -> 2024 | L12: =AVERAGE(OFFSET(C12,-MIN(2,A12-1),0,MIN(3,A12),1)) -> 8578.3667 | M12: =C12*_xlfn.XLOOKUP(A12,FX!$A$2:$A$37,FX!$C$2:$C$37) -> 9365.8847 | N12: =C12*(1+Control!$B$4)^(A12/12) -> 8882.3408 | O12: =RANK(C12,$C$2:$C$37,0) -> 26 | P12: =IFERROR(C12-C11,0) -> 54.3 | Q12: =IFERROR(E12/D12,0) -> 0.60814505 | R12: =ROUND(IFERROR(D12/F12,0),2) -> 0.51 | S12: =IF(AND(I12>0,G12>0),"sopra",IF(OR(I12<-0.05,G12<0),"sotto","in linea")) -> in linea | T12: ="T"&ROUNDUP(MONTH(B12)/3,0)&"-"&YEAR(B12) -> T4-2024 | U12: =AVERAGEIFS($C$2:$C$37,$A$2:$A$37,">"&(A12-12),$A$2:$A$37,"<="&A12) -> 8341.9091
A13: =ROW()-1 -> 12 | B13: =EOMONTH(DATE(2024,A13,1),0) -> 45657 | C13: =SUMIFS(Data!$E$2:$E$5761,Data!$A$2:$A$5761,Control!$B$2,Data!$B$2:$B$5761,A13) -> 8718.7 | D13: =SUMIFS(Data!$F$2:$F$5761,Data!$A$2:$A$5761,Control!$B$2,Data!$B$2:$B$5761,A13) -> 472.51 | E13: =SUMIFS(Data!$G$2:$G$5761,Data!$A$2:$A$5761,Control!$B$2,Data!$B$2:$B$5761,A13) -> 285.29 | F13: =SUMIFS(Data!$H$2:$H$5761,Data!$A$2:$A$5761,Control!$B$2,Data!$B$2:$B$5761,A13) -> 972 | G13: =D13-E13 -> 187.22 | H13: {=INDEX(Budget!$B$2:$AK$21,Control!$B$6,MATCH(A13,Budget!$B$1:$AK$1,0))} -> 8806 | I13: =IFERROR(C13/H13-1,0) -> -0.0099136952 | J13: =SUMIFS($C$2:$C$37,$K$2:$K$37,K13,$A$2:$A$37,"<="&A13) -> 100479.7 | K13: =YEAR(B13) -> 2024 | L13: =AVERAGE(OFFSET(C13,-MIN(2,A13-1),0,MIN(3,A13),1)) -> 8651.4 | M13: =C13*_xlfn.XLOOKUP(A13,FX!$A$2:$A$37,FX!$C$2:$C$37) -> 9400.5023 | N13: =C13*(1+Control!$B$4)^(A13/12) -> 8980.261 | O13: =RANK(C13,$C$2:$C$37,0) -> 25 | P13: =IFERROR(C13-C12,0) -> 73.8 | Q13: =IFERROR(E13/D13,0) -> 0.60377558 | R13: =ROUND(IFERROR(D13/F13,0),2) -> 0.49 | S13: =IF(AND(I13>0,G13>0),"sopra",IF(OR(I13<-0.05,G13<0),"sotto","in linea")) -> in linea | T13: ="T"&ROUNDUP(MONTH(B13)/3,0)&"-"&YEAR(B13) -> T4-2024 | U13: =AVERAGEIFS($C$2:$C$37,$A$2:$A$37,">"&(A13-12),$A$2:$A$37,"<="&A13) -> 8373.3083
... A37: =ROW()-1 -> 36 | B37: =EOMONTH(DATE(2024,A37,1),0) -> 46387 | C37: =SUMIFS(Data!$E$2:$E$5761,Data!$A$2:$A$5761,Control!$B$2,Data!$B$2:$B$5761,A37) -> 10243.3 | D37: =SUMIFS(Data!$F$2:$F$5761,Data!$A$2:$A$5761,Control!$B$2,Data!$B$2:$B$5761,A37) -> 555.09 | E37: =SUMIFS(Data!$G$2:$G$5761,Data!$A$2:$A$5761,Control!$B$2,Data!$B$2:$B$5761,A37) -> 334.49 | F37: =SUMIFS(Data!$H$2:$H$5761,Data!$A$2:$A$5761,Control!$B$2,Data!$B$2:$B$5761,A37) -> 975 | G37: =D37-E37 -> 220.6 | H37: {=INDEX(Budget!$B$2:$AK$21,Control!$B$6,MATCH(A37,Budget!$B$1:$AK$1,0))} -> 10523 | I37: =IFERROR(C37/H37-1,0) -> -0.026579873 | J37: =SUMIFS($C$2:$C$37,$K$2:$K$37,K37,$A$2:$A$37,"<="&A37) -> 118690.4 | K37: =YEAR(B37) -> 2026 | L37: =AVERAGE(OFFSET(C37,-MIN(2,A37-1),0,MIN(3,A37),1)) -> 10194.233 | M37: =C37*_xlfn.XLOOKUP(A37,FX!$A$2:$A$37,FX!$C$2:$C$37) -> 11117.053 | N37: =C37*(1+Control!$B$4)^(A37/12) -> 11193.13 | O37: =RANK(C37,$C$2:$C$37,0) -> 2 | P37: =IFERROR(C37-C36,0) -> -8.9 | Q37: =IFERROR(E37/D37,0) -> 0.60258697 | R37: =ROUND(IFERROR(D37/F37,0),2) -> 0.57 | S37: =IF(AND(I37>0,G37>0),"sopra",IF(OR(I37<-0.05,G37<0),"sotto","in linea")) -> in linea | T37: ="T"&ROUNDUP(MONTH(B37)/3,0)&"-"&YEAR(B37) -> T4-2026 | U37: =AVERAGEIFS($C$2:$C$37,$A$2:$A$37,">"&(A37-12),$A$2:$A$37,"<="&A37) -> 9890.8667

Sheet Calc_Bank
A1: Banca | B1: Regione | C1: Volumi | D1: Ricavi | E1: Costi | F1: Margine | G1: Mese prec. | H1: Var. % | I1: Anno prec. | J1: YoY | K1: Quota | L1: Rango | M1: Max mutui | N1: Media prodotti | O1: Prodotti sopra media | P1: Budget | Q1: Gap budget | R1: Segmento | S1: Classe | T1: Codice area | U1: Quartile | V1: Selezionata | W1: Clienti | X1: Ricavo/cliente | Y1: Scenario | Z1: In regione sel. | AA1: Scost. LET | AB1: YTD
A2: =Banks!A2 -> Banca Alpi | B2: =VLOOKUP(A2,Banks!$A$2:$C$21,3,FALSE) -> Nord-Ovest | C2: =SUMIFS(Data!$E:$E,Data!$A:$A,A2,Data!$B:$B,Control!$B$3) -> 6542.2 | D2: =SUMIFS(Data!$F$2:$F$5761,Data!$A$2:$A$5761,A2,Data!$B$2:$B$5761,Control!$B$3) -> 355.72 | E2: =SUMIFS(Data!$G$2:$G$5761,Data!$A$2:$A$5761,A2,Data!$B$2:$B$5761,Control!$B$3) -> 216.07 | F2: =D2-E2 -> 139.65 | G2: =SUMIFS(Data!$E$2:$E$5761,Data!$A$2:$A$5761,A2,Data!$B$2:$B$5761,Control!$B$13) -> 6551.1 | H2: =IFERROR(C2/G2-1,0) -> -0.0013585505 | I2: =SUMIFS(Data!$E$2:$E$5761,Data!$A$2:$A$5761,A2,Data!$B$2:$B$5761,Control!$B$14) -> 5941.6 | J2: =IFERROR(C2/I2-1,0) -> 0.10108388 | K2: =C2/SUM($C$2:$C$21) -> 0.019042369 | L2: =RANK(C2,$C$2:$C$21) -> 20 | M2: =_xlfn.MAXIFS(Data!$E$2:$E$5761,Data!$A$2:$A$5761,A2,Data!$C$2:$C$5761,"Mutui") -> 425.1 | N2: =AVERAGEIFS(Data!$E$2:$E$5761,Data!$A$2:$A$5761,A2,Data!$B$2:$B$5761,Control!$B$3) -> 817.775 | O2: =COUNTIFS(Data!$A$2:$A$5761,A2,Data!$B$2:$B$5761,Control!$B$3,Data!$E$2:$E$5761,">"&N2) -> 4 | P2: =INDEX(Budget!$B$2:$AK$21,MATCH(A2,Budget!$A$2:$A$21,0),MATCH(Control!$B$3,Budget!$B$1:$AK$1,0)) -> 6613 | Q2: =C2-P2 -> -70.8 | R2: =_xlfn.XLOOKUP(A2,Banks!$A$2:$A$21,Banks!$E$2:$E$21) -> Grande | S2: =CHOOSE(IF(R2="Grande",1,IF(R2="Media",2,3)),"A","B","C") -> A | T2: {=_xlfn.SWITCH(B2,"Nord-Ovest","NO","Nord-Est","NE","Centro","CE","Sud","SU","IS")} -> NO | U2: =IF(C2>=PERCENTILE($C$2:$C$21,0.75),"primo quartile",IF(C2<=PERCENTILE($C$2:$C$21,0.25),"ultimo quartile","centrale")) -> ultimo quartile | V2: =IF(A2=Control!$B$2,"<<","") | W2: =SUMIFS(Data!$H$2:$H$5761,Data!$A$2:$A$5761,A2,Data!$B$2:$B$5761,Control!$B$3) -> 690 | X2: =IFERROR(D2/W2,0) -> 0.51553623 | Y2: =C2*(1+Control!$B$4) -> 6738.466 | Z2: =IF(B2=Control!$B$5,C2,0) -> 0 | AA2: =_xlfn.LET(_xlpm.v,C2,_xlpm.b,P2,IF(_xlpm.b=0,0,ROUND((_xlpm.v-_xlpm.b)/_xlpm.b,4))) -> -0.0107 | AB2: {=SUMPRODUCT((Data!$A$2:$A$5761=A2)*(Data!$B$2:$B$5761<=Control!$B$3)*(Data!$J$2:$J$5761=Control!$B$11)*Data!$E$2:$E$5761)} -> 6542.2
A3: =Banks!A3 -> Banca Adriatica | B3: =VLOOKUP(A3,Banks!$A$2:$C$21,3,FALSE) -> Nord-Est | C3: =SUMIFS(Data!$E:$E,Data!$A:$A,A3,Data!$B:$B,Control!$B$3) -> 7649.6 | D3: =SUMIFS(Data!$F$2:$F$5761,Data!$A$2:$A$5761,A3,Data!$B$2:$B$5761,Control!$B$3) -> 415.13 | E3: =SUMIFS(Data!$G$2:$G$5761,Data!$A$2:$A$5761,A3,Data!$B$2:$B$5761,Control!$B$3) -> 250.61 | F3: =D3-E3 -> 164.52 | G3: =SUMIFS(Data!$E$2:$E$5761,Data!$A$2:$A$5761,A3,Data!$B$2:$B$5761,Control!$B$13) -> 7666.8 | H3: =IFERROR(C3/G3-1,0) -> -0.0022434392 | I3: =SUMIFS(Data!$E$2:$E$5761,Data!$A$2:$A$5761,A3,Data!$B$2:$B$5761,Control!$B$14) -> 6980.2 | J3: =IFERROR(C3/I3-1,0) -> 0.095899831 | K3: =C3/SUM($C$2:$C$21) -> 0.022265676 | L3: =RANK(C3,$C$2:$C$21) -> 19 | M3: =_xlfn.MAXIFS(Data!$E$2:$E$5761,Data!$A$2:$A$5761,A3,Data!$C$2:$C$5761,"Mutui") -> 493.7 | N3: =AVERAGEIFS(Data!$E$2:$E$5761,Data!$A$2:$A$5761,A3,Data!$B$2:$B$5761,Control!$B$3) -> 956.2 | O3: =COUNTIFS(Data!$A$2:$A$5761,A3,Data!$B$2:$B$5761,Control!$B$3,Data!$E$2:$E$5761,">"&N3) -> 4 | P3: =INDEX(Budget!$B$2:$AK$21,MATCH(A3,Budget!$A$2:$A$21,0),MATCH(Control!$B$3,Budget!$B$1:$AK$1,0)) -> 7745 | Q3: =C3-P3 -> -95.4 | R3: =_xlfn.XLOOKUP(A3,Banks!$A$2:$A$21,Banks!$E$2:$E$21) -> Media | S3: =CHOOSE(IF(R3="Grande",1,IF(R3="Media",2,3)),"A","B","C") -> B | T3: {=_xlfn.SWITCH(B3,"Nord-Ovest","NO","Nord-Est","NE","Centro","CE","Sud","SU","IS")} -> NE | U3: =IF(C3>=PERCENTILE($C$2:$C$21,0.75),"primo quartile",IF(C3<=PERCENTILE($C$2:$C$21,0.25),"ultimo quartile","centrale")) -> ultimo quartile | V3: =IF(A3=Control!$B$2,"<<","") | W3: =SUMIFS(Data!$H$2:$H$5761,Data!$A$2:$A$5761,A3,Data!$B$2:$B$5761,Control!$B$3) -> 840 | X3: =IFERROR(D3/W3,0) -> 0.49420238 | Y3: =C3*(1+Control!$B$4) -> 7879.088 | Z3: =IF(B3=Control!$B$5,C3,0) -> 0 | AA3: =_xlfn.LET(_xlpm.v,C3,_xlpm.b,P3,IF(_xlpm.b=0,0,ROUND((_xlpm.v-_xlpm.b)/_xlpm.b,4))) -> -0.0123 | AB3: {=SUMPRODUCT((Data!$A$2:$A$5761=A3)*(Data!$B$2:$B$5761<=Control!$B$3)*(Data!$J$2:$J$5761=Control!$B$11)*Data!$E$2:$E$5761)} -> 7649.6
A4: =Banks!A4 -> Banca Tirrena | B4: =VLOOKUP(A4,Banks!$A$2:$C$21,3,FALSE) -> Centro | C4: =SUMIFS(Data!$E:$E,Data!$A:$A,A4,Data!$B:$B,Control!$B$3) -> 8739.1 | D4: =SUMIFS(Data!$F$2:$F$5761,Data!$A$2:$A$5761,A4,Data!$B$2:$B$5761,Control!$B$3) -> 472.04 | E4: =SUMIFS(Data!$G$2:$G$5761,Data!$A$2:$A$5761,A4,Data!$B$2:$B$5761,Control!$B$3) -> 287.57 | F4: =D4-E4 -> 184.47 | G4: =SUMIFS(Data!$E$2:$E$5761,Data!$A$2:$A$5761,A4,Data!$B$2:$B$5761,Control!$B$13) -> 8718.7 | H4: =IFERROR(C4/G4-1,0) -> 0.0023397984 | I4: =SUMIFS(Data!$E$2:$E$5761,Data!$A$2:$A$5761,A4,Data!$B$2:$B$5761,Control!$B$14) -> 8012.1 | J4: =IFERROR(C4/I4-1,0) -> 0.090737759 | K4: =C4/SUM($C$2:$C$21) -> 0.025436881 | L4: =RANK(C4,$C$2:$C$21) -> 18 | M4: =_xlfn.MAXIFS(Data!$E$2:$E$5761,Data!$A$2:$A$5761,A4,Data!$C$2:$C$5761,"Mutui") -> 571.2 | N4: =AVERAGEIFS(Data!$E$2:$E$5761,Data!$A$2:$A$5761,A4,Data!$B$2:$B$5761,Control!$B$3) -> 1092.3875 | O4: =COUNTIFS(Data!$A$2:$A$5761,A4,Data!$B$2:$B$5761,Control!$B$3,Data!$E$2:$E$5761,">"&N4) -> 4 | P4: =INDEX(Budget!$B$2:$AK$21,MATCH(A4,Budget!$A$2:$A$21,0),MATCH(Control!$B$3,Budget!$B$1:$AK$1,0)) -> 8877 | Q4: =C4-P4 -> -137.9 | R4: =_xlfn.XLOOKUP(A4,Banks!$A$2:$A$21,Banks!$E$2:$E$21) -> Grande | S4: =CHOOSE(IF(R4="Grande",1,IF(R4="Media",2,3)),"A","B","C") -> A | T4: {=_xlfn.SWITCH(B4,"Nord-Ovest","NO","Nord-Est","NE","Centro","CE","Sud","SU","IS")} -> CE | U4: =IF(C4>=PERCENTILE($C$2:$C$21,0.75),"primo quartile",IF(C4<=PERCENTILE($C$2:$C$21,0.25),"ultimo quartile","centrale")) -> ultimo quartile | V4: =IF(A4=Control!$B$2,"<<","") -> << | W4: =SUMIFS(Data!$H$2:$H$5761,Data!$A$2:$A$5761,A4,Data!$B$2:$B$5761,Control!$B$3) -> 986 | X4: =IFERROR(D4/W4,0) -> 0.47874239 | Y4: =C4*(1+Control!$B$4) -> 9001.273 | Z4: =IF(B4=Control!$B$5,C4,0) -> 8739.1 | AA4: =_xlfn.LET(_xlpm.v,C4,_xlpm.b,P4,IF(_xlpm.b=0,0,ROUND((_xlpm.v-_xlpm.b)/_xlpm.b,4))) -> -0.0155 | AB4: {=SUMPRODUCT((Data!$A$2:$A$5761=A4)*(Data!$B$2:$B$5761<=Control!$B$3)*(Data!$J$2:$J$5761=Control!$B$11)*Data!$E$2:$E$5761)} -> 8739.1
A5: =Banks!A5 -> Banca Padana | B5: =VLOOKUP(A5,Banks!$A$2:$C$21,3,FALSE) -> Nord-Ovest | C5: =SUMIFS(Data!$E:$E,Data!$A:$A,A5,Data!$B:$B,Control!$B$3) -> 9892.6 | D5: =SUMIFS(Data!$F$2:$F$5761,Data!$A$2:$A$5761,A5,Data!$B$2:$B$5761,Control!$B$3) -> 534.73 | E5: =SUMIFS(Data!$G$2:$G$5761,Data!$A$2:$A$5761,A5,Data!$B$2:$B$5761,Control!$B$3) -> 322.31 | F5: =D5-E5 -> 212.42 | G5: =SUMIFS(Data!$E$2:$E$5761,Data!$A$2:$A$5761,A5,Data!$B$2:$B$5761,Control!$B$13) -> 9822.9 | H5: =IFERROR(C5/G5-1,0) -> 0.0070956642 | I5: =SUMIFS(Data!$E$2:$E$5761,Data!$A$2:$A$5761,A5,Data!$B$2:$B$5761,Control!$B$14) -> 9024.4 | J5: =IFERROR(C5/I5-1,0) -> 0.096205842 | K5: =C5/SUM($C$2:$C$21) -> 0.028794371 | L5: =RANK(C5,$C$2:$C$21) -> 17 | M5: =_xlfn.MAXIFS(Data!$E$2:$E$5761,Data!$A$2:$A$5761,A5,Data!$C$2:$C$5761,"Mutui") -> 624 | N5: =AVERAGEIFS(Data!$E$2:$E$5761,Data!$A$2:$A$5761,A5,Data!$B$2:$B$5761,Control!$B$3) -> 1236.575 | O5: =COUNTIFS(Data!$A$2:$A$5761,A5,Data!$B$2:$B$5761,Control!$B$3,Data!$E$2:$E$5761,">"&N5) -> 4 | P5: =INDEX(Budget!$B$2:$AK$21,MATCH(A5,Budget!$A$2:$A$21,0),MATCH(Control!$B$3,Budget!$B$1:$AK$1,0)) -> 10010 | Q5: =C5-P5 -> -117.4 | R5: =_xlfn.XLOOKUP(A5,Banks!$A$2:$A$21,Banks!$E$2:$E$21) -> Grande | S5: =CHOOSE(IF(R5="Grande",1,IF(R5="Media",2,3)),"A","B","C") -> A | T5: {=_xlfn.SWITCH(B5,"Nord-Ovest","NO","Nord-Est","NE","Centro","CE","Sud","SU","IS")} -> NO | U5: =IF(C5>=PERCENTILE($C$2:$C$21,0.75),"primo quartile",IF(C5<=PERCENTILE($C$2:$C$21,0.25),"ultimo quartile","centrale")) -> ultimo quartile | V5: =IF(A5=Control!$B$2,"<<","") | W5: =SUMIFS(Data!$H$2:$H$5761,Data!$A$2:$A$5761,A5,Data!$B$2:$B$5761,Control!$B$3) -> 1047 | X5: =IFERROR(D5/W5,0) -> 0.51072588 | Y5: =C5*(1+Control!$B$4) -> 10189.378 | Z5: =IF(B5=Control!$B$5,C5,0) -> 0 | AA5: =_xlfn.LET(_xlpm.v,C5,_xlpm.b,P5,IF(_xlpm.b=0,0,ROUND((_xlpm.v-_xlpm.b)/_xlpm.b,4))) -> -0.0117 | AB5: {=SUMPRODUCT((Data!$A$2:$A$5761=A5)*(Data!$B$2:$B$5761<=Control!$B$3)*(Data!$J$2:$J$5761=Control!$B$11)*Data!$E$2:$E$5761)} -> 9892.6
A6: =Banks!A6 -> Banca Etrusca | B6: =VLOOKUP(A6,Banks!$A$2:$C$21,3,FALSE) -> Centro | C6: =SUMIFS(Data!$E:$E,Data!$A:$A,A6,Data!$B:$B,Control!$B$3) -> 10989.1 | D6: =SUMIFS(Data!$F$2:$F$5761,Data!$A$2:$A$5761,A6,Data!$B$2:$B$5761,Control!$B$3) -> 594.2 | E6: =SUMIFS(Data!$G$2:$G$5761,Data!$A$2:$A$5761,A6,Data!$B$2:$B$5761,Control!$B$3) -> 360.56 | F6: =D6-E6 -> 233.64 | G6: =SUMIFS(Data!$E$2:$E$5761,Data!$A$2:$A$5761,A6,Data!$B$2:$B$5761,Control!$B$13) -> 10956.1 | H6: =IFERROR(C6/G6-1,0) -> 0.0030120207 | I6: =SUMIFS(Data!$E$2:$E$5761,Data!$A$2:$A$5761,A6,Data!$B$2:$B$5761,Control!$B$14) -> 9970.8 | J6: =IFERROR(C6/I6-1,0) -> 0.10212821 | K6: =C6/SUM($C$2:$C$21) -> 0.031985952 | L6: =RANK(C6,$C$2:$C$21) -> 16 | M6: =_xlfn.MAXIFS(Data!$E$2:$E$5761,Data!$A$2:$A$5761,A6,Data!$C$2:$C$5761,"Mutui") -> 699.2 | N6: =AVERAGEIFS(Data!$E$2:$E$5761,Data!$A$2:$A$5761,A6,Data!$B$2:$B$5761,Control!$B$3) -> 1373.6375 | O6: =COUNTIFS(Data!$A$2:$A$5761,A6,Data!$B$2:$B$5761,Control!$B$3,Data!$E$2:$E$5761,">"&N6) -> 4 | P6: =INDEX(Budget!$B$2:$AK$21,MATCH(A6,Budget!$A$2:$A$21,0),MATCH(Control!$B$3,Budget!$B$1:$AK$1,0)) -> 11142 | Q6: =C6-P6 -> -152.9 | R6: =_xlfn.XLOOKUP(A6,Banks!$A$2:$A$21,Banks!$E$2:$E$21) -> Media | S6: =CHOOSE(IF(R6="Grande",1,IF(R6="Media",2,3)),"A","B","C") -> B | T6: {=_xlfn.SWITCH(B6,"Nord-Ovest","NO","Nord-Est","NE","Centro","CE","Sud","SU","IS")} -> CE | U6: =IF(C6>=PERCENTILE($C$2:$C$21,0.75),"primo quartile",IF(C6<=PERCENTILE($C$2:$C$21,0.25),"ultimo quartile","centrale")) -> ultimo quartile | V6: =IF(A6=Control!$B$2,"<<","") | W6: =SUMIFS(Data!$H$2:$H$5761,Data!$A$2:$A$5761,A6,Data!$B$2:$B$5761,Control!$B$3) -> 1127 | X6: =IFERROR(D6/W6,0) -> 0.52724046 | Y6: =C6*(1+Control!$B$4) -> 11318.773 | Z6: =IF(B6=Control!$B$5,C6,0) -> 10989.1 | AA6: =_xlfn.LET(_xlpm.v,C6,_xlpm.b,P6,IF(_xlpm.b=0,0,ROUND((_xlpm.v-_xlpm.b)/_xlpm.b,4))) -> -0.0137 | AB6: {=SUMPRODUCT((Data!$A$2:$A$5761=A6)*(Data!$B$2:$B$5761<=Control!$B$3)*(Data!$J$2:$J$5761=Control!$B$11)*Data!$E$2:$E$5761)} -> 10989.1
A7: =Banks!A7 -> Banca Lariana | B7: =VLOOKUP(A7,Banks!$A$2:$C$21,3,FALSE) -> Nord-Ovest | C7: =SUMIFS(Data!$E:$E,Data!$A:$A,A7,Data!$B:$B,Control!$B$3) -> 12105.6 | D7: =SUMIFS(Data!$F$2:$F$5761,Data!$A$2:$A$5761,A7,Data!$B$2:$B$5761,Control!$B$3) -> 653.86 | E7: =SUMIFS(Data!$G$2:$G$5761,Data!$A$2:$A$5761,A7,Data!$B$2:$B$5761,Control!$B$3) -> 394.85 | F7: =D7-E7 -> 259.01 | G7: =SUMIFS(Data!$E$2:$E$5761,Data!$A$2:$A$5761,A7,Data!$B$2:$B$5761,Control!$B$13) -> 12114.3 | H7: =IFERROR(C7/G7-1,0) -> -0.00071815953 | I7: =SUMIFS(Data!$E$2:$E$5761,Data!$A$2:$A$5761,A7,Data!$B$2:$B$5761,Control!$B$14) -> 11120.3 | J7: =IFERROR(C7/I7-1,0) -> 0.088603725 | K7: =C7/SUM($C$2:$C$21) -> 0.035235746 | L7: =RANK(C7,$C$2:$C$21) -> 15 | M7: =_xlfn.MAXIFS(Data!$E$2:$E$5761,Data!$A$2:$A$5761,A7,Data!$C$2:$C$5761,"Mutui") -> 786.7 | N7: =AVERAGEIFS(Data!$E$2:$E$5761,Data!$A$2:$A$5761,A7,Data!$B$2:$B$5761,Control!$B$3) -> 1513.2 | O7: =COUNTIFS(Data!$A$2:$A$5761,A7,Data!$B$2:$B$5761,Control!$B$3,Data!$E$2:$E$5761,">"&N7) -> 4 | P7: =INDEX(Budget!$B$2:$AK$21,MATCH(A7,Budget!$A$2:$A$21,0),MATCH(Control!$B$3,Budget!$B$1:$AK$1,0)) -> 12275 | Q7: =C7-P7 -> -169.4 | R7: =_xlfn.XLOOKUP(A7,Banks!$A$2:$A$21,Banks!$E$2:$E$21) -> Piccola | S7: =CHOOSE(IF(R7="Grande",1,IF(R7="Media",2,3)),"A","B","C") -> C | T7: {=_xlfn.SWITCH(B7,"Nord-Ovest","NO","Nord-Est","NE","Centro","CE","Sud","SU","IS")} -> NO | U7: =IF(C7>=PERCENTILE($C$2:$C$21,0.75),"primo quartile",IF(C7<=PERCENTILE($C$2:$C$21,0.25),"ultimo quartile","centrale")) -> centrale | V7: =IF(A7=Control!$B$2,"<<","") | W7: =SUMIFS(Data!$H$2:$H$5761,Data!$A$2:$A$5761,A7,Data!$B$2:$B$5761,Control!$B$3) -> 1277 | X7: =IFERROR(D7/W7,0) -> 0.51202819 | Y7: =C7*(1+Control!$B$4) -> 12468.768 | Z7: =IF(B7=Control!$B$5,C7,0) -> 0 | AA7: =_xlfn.LET(_xlpm.v,C7,_xlpm.b,P7,IF(_xlpm.b=0,0,ROUND((_xlpm.v-_xlpm.b)/_xlpm.b,4))) -> -0.0138 | AB7: {=SUMPRODUCT((Data!$A$2:$A$5761=A7)*(Data!$B$2:$B$5761<=Control!$B$3)*(Data!$J$2:$J$5761=Control!$B$11)*Data!$E$2:$E$5761)} -> 12105.6
A8: =Banks!A8 -> Banca Sabina | B8: =VLOOKUP(A8,Banks!$A$2:$C$21,3,FALSE) -> Centro | C8: =SUMIFS(Data!$E:$E,Data!$A:$A,A8,Data!$B:$B,Control!$B$3) -> 13300.5 | D8: =SUMIFS(Data!$F$2:$F$5761,Data!$A$2:$A$5761,A8,Data!$B$2:$B$5761,Control!$B$3) -> 718.87 | E8: =SUMIFS(Data!$G$2:$G$5761,Data!$A$2:$A$5761,A8,Data!$B$2:$B$5761,Control!$B$3) -> 434.17 | F8: =D8-E8 -> 284.7 | G8: =SUMIFS(Data!$E$2:$E$5761,Data!$A$2:$A$5761,A8,Data!$B$2:$B$5761,Control!$B$13) -> 13117.7 | H8: =IFERROR(C8/G8-1,0) -> 0.01393537 | I8: =SUMIFS(Data!$E$2:$E$5761,Data!$A$2:$A$5761,A8,Data!$B$2:$B$5761,Control!$B$14) -> 12033 | J8: =IFERROR(C8/I8-1,0) -> 0.10533533 | K8: =C8/SUM($C$2:$C$21) -> 0.038713739 | L8: =RANK(C8,$C$2:$C$21) -> 14 | M8: =_xlfn.MAXIFS(Data!$E$2:$E$5761,Data!$A$2:$A$5761,A8,Data!$C$2:$C$5761,"Mutui") -> 847.9 | N8: =AVERAGEIFS(Data!$E$2:$E$5761,Data!$A$2:$A$5761,A8,Data!$B$2:$B$5761,Control!$B$3) -> 1662.5625 | O8: =COUNTIFS(Data!$A$2:$A$5761,A8,Data!$B$2:$B$5761,Control!$B$3,Data!$E$2:$E$5761,">"&N8) -> 4 | P8: =INDEX(Budget!$B$2:$AK$21,MATCH(A8,Budget!$A$2:$A$21,0),MATCH(Control!$B$3,Budget!$B$1:$AK$1,0)) -> 13407 | Q8: =C8-P8 -> -106.5 | R8: =_xlfn.XLOOKUP(A8,Banks!$A$2:$A$21,Banks!$E$2:$E$21) -> Piccola | S8: =CHOOSE(IF(R8="Grande",1,IF(R8="Media",2,3)),"A","B","C") -> C | T8: {=_xlfn.SWITCH(B8,"Nord-Ovest","NO","Nord-Est","NE","Centro","CE","Sud","SU","IS")} -> CE | U8: =IF(C8>=PERCENTILE($C$2:$C$21,0.75),"primo quartile",IF(C8<=PERCENTILE($C$2:$C$21,0.25),"ultimo quartile","centrale")) -> centrale | V8: =IF(A8=Control!$B$2,"<<","") | W8: =SUMIFS(Data!$H$2:$H$5761,Data!$A$2:$A$5761,A8,Data!$B$2:$B$5761,Control!$B$3) -> 1381 | X8: =IFERROR(D8/W8,0) -> 0.52054308 | Y8: =C8*(1+Control!$B$4) -> 13699.515 | Z8: =IF(B8=Control!$B$5,C8,0) -> 13300.5 | AA8: =_xlfn.LET(_xlpm.v,C8,_xlpm.b,P8,IF(_xlpm.b=0,0,ROUND((_xlpm.v-_xlpm.b)/_xlpm.b,4))) -> -0.0079 | AB8: {=SUMPRODUCT((Data!$A$2:$A$5761=A8)*(Data!$B$2:$B$5761<=Control!$B$3)*(Data!$J$2:$J$5761=Control!$B$11)*Data!$E$2:$E$5761)} -> 13300.5
A9: =Banks!A9 -> Banca Irpina | B9: =VLOOKUP(A9,Banks!$A$2:$C$21,3,FALSE) -> Sud | C9: =SUMIFS(Data!$E:$E,Data!$A:$A,A9,Data!$B:$B,Control!$B$3) -> 14379.3 | D9: =SUMIFS(Data!$F$2:$F$5761,Data!$A$2:$A$5761,A9,Data!$B$2:$B$5761,Control!$B$3) -> 776.25 | E9: =SUMIFS(Data!$G$2:$G$5761,Data!$A$2:$A$5761,A9,Data!$B$2:$B$5761,Control!$B$3) -> 470.41 | F9: =D9-E9 -> 305.84 | G9: =SUMIFS(Data!$E$2:$E$5761,Data!$A$2:$A$5761,A9,Data!$B$2:$B$5761,Control!$B$13) -> 14263.4 | H9: =IFERROR(C9/G9-1,0) -> 0.0081256923 | I9: =SUMIFS(Data!$E$2:$E$5761,Data!$A$2:$A$5761,A9,Data!$B$2:$B$5761,Control!$B$14) -> 13187.6 | J9: =IFERROR(C9/I9-1,0) -> 0.090365192 | K9: =C9/SUM($C$2:$C$21) -> 0.0418538 | L9: =RANK(C9,$C$2:$C$21) -> 13 | M9: =_xlfn.MAXIFS(Data!$E$2:$E$5761,Data!$A$2:$A$5761,A9,Data!$C$2:$C$5761,"Mutui") -> 908.5 | N9: =AVERAGEIFS(Data!$E$2:$E$5761,Data!$A$2:$A$5761,A9,Data!$B$2:$B$5761,Control!$B$3) -> 1797.4125 | O9: =COUNTIFS(Data!$A$2:$A$5761,A9,Data!$B$2:$B$5761,Control!$B$3,Data!$E$2:$E$5761,">"&N9) -> 4 | P9: =INDEX(Budget!$B$2:$AK$21,MATCH(A9,Budget!$A$2:$A$21,0),MATCH(Control!$B$3,Budget!$B$1:$AK$1,0)) -> 14540 | Q9: =C9-P9 -> -160.7 | R9: =_xlfn.XLOOKUP(A9,Banks!$A$2:$A$21,Banks!$E$2:$E$21) -> Piccola | S9: =CHOOSE(IF(R9="Grande",1,IF(R9="Media",2,3)),"A","B","C") -> C | T9: {=_xlfn.SWITCH(B9,"Nord-Ovest","NO","Nord-Est","NE","Centro","CE","Sud","SU","IS")} -> SU | U9: =IF(C9>=PERCENTILE($C$2:$C$21,0.75),"primo quartile",IF(C9<=PERCENTILE($C$2:$C$21,0.25),"ultimo quartile","centrale")) -> centrale | V9: =IF(A9=Control!$B$2,"<<","") | W9: =SUMIFS(Data!$H$2:$H$5761,Data!$A$2:$A$5761,A9,Data!$B$2:$B$5761,Control!$B$3) -> 1514 | X9: =IFERROR(D9/W9,0) -> 0.51271466 | Y9: =C9*(1+Control!$B$4) -> 14810.679 | Z9: =IF(B9=Control!$B$5,C9,0) -> 0 | AA9: =_xlfn.LET(_xlpm.v,C9,_xlpm.b,P9,IF(_xlpm.b=0,0,ROUND((_xlpm.v-_xlpm.b)/_xlpm.b,4))) -> -0.0111 | AB9: {=SUMPRODUCT((Data!$A$2:$A$5761=A9)*(Data!$B$2:$B$5761<=Control!$B$3)*(Data!$J$2:$J$5761=Control!$B$11)*Data!$E$2:$E$5761)} -> 14379.3
A10: =Banks!A10 -> Banca Sannita | B10: =VLOOKUP(A10,Banks!$A$2:$C$21,3,FALSE) -> Sud | C10: =SUMIFS(Data!$E:$E,Data!$A:$A,A10,Data!$B:$B,Control!$B$3) -> 15489.6 | D10: =SUMIFS(Data!$F$2:$F$5761,Data!$A$2:$A$5761,A10,Data!$B$2:$B$5761,Control!$B$3) -> 837.25 | E10: =SUMIFS(Data!$G$2:$G$5761,Data!$A$2:$A$5761,A10,Data!$B$2:$B$5761,Control!$B$3) -> 504.85 | F10: =D10-E10 -> 332.4 | G10: =SUMIFS(Data!$E$2:$E$5761,Data!$A$2:$A$5761,A10,Data!$B$2:$B$5761,Control!$B$13) -> 15359.6 | H10: =IFERROR(C10/G10-1,0) -> 0.0084637621 | I10: =SUMIFS(Data!$E$2:$E$5761,Data!$A$2:$A$5761,A10,Data!$B$2:$B$5761,Control!$B$14) -> 14125.8 | J10: =IFERROR(C10/I10-1,0) -> 0.096546744 | K10: =C10/SUM($C$2:$C$21) -> 0.045085548 | L10: =RANK(C10,$C$2:$C$21) -> 12 | M10: =_xlfn.MAXIFS(Data!$E$2:$E$5761,Data!$A$2:$A$5761,A10,Data!$C$2:$C$5761,"Mutui") -> 958.8 | N10: =AVERAGEIFS(Data!$E$2:$E$5761,Data!$A$2:$A$5761,A10,Data!$B$2:$B$5761,Control!$B$3) -> 1936.2 | O10: =COUNTIFS(Data!$A$2:$A$5761,A10,Data!$B$2:$B$5761,Control!$B$3,Data!$E$2:$E$5761,">"&N10) -> 4 | P10: =INDEX(Budget!$B$2:$AK$21,MATCH(A10,Budget!$A$2:$A$21,0),MATCH(Control!$B$3,Budget!$B$1:$AK$1,0)) -> 15672 | Q10: =C10-P10 -> -182.4 | R10: =_xlfn.XLOOKUP(A10,Banks!$A$2:$A$21,Banks!$E$2:$E$21) -> Media | S10: =CHOOSE(IF(R10="Grande",1,IF(R10="Media",2,3)),"A","B","C") -> B | T10: {=_xlfn.SWITCH(B10,"Nord-Ovest","NO","Nord-Est","NE","Centro","CE","Sud","SU","IS")} -> SU | U10: =IF(C10>=PERCENTILE($C$2:$C$21,0.75),"primo quartile",IF(C10<=PERCENTILE($C$2:$C$21,0.25),"ultimo quartile","centrale")) -> centrale | V10: =IF(A10=Control!$B$2,"<<","") | W10: =SUMIFS(Data!$H$2:$H$5761,Data!$A$2:$A$5761,A10,Data!$B$2:$B$5761,Control!$B$3) -> 1619 | X10: =IFERROR(D10/W10,0) -> 0.51714021 | Y10: =C10*(1+Control!$B$4) -> 15954.288 | Z10: =IF(B10=Control!$B$5,C10,0) -> 0 | AA10: =_xlfn.LET(_xlpm.v,C10,_xlpm.b,P10,IF(_xlpm.b=0,0,ROUND((_xlpm.v-_xlpm.b)/_xlpm.b,4))) -> -0.0116 | AB10: {=SUMPRODUCT((Data!$A$2:$A$5761=A10)*(Data!$B$2:$B$5761<=Control!$B$3)*(Data!$J$2:$J$5761=Control!$B$11)*Data!$E$2:$E$5761)} -> 15489.6
A11: =Banks!A11 -> Banca Ligure | B11: =VLOOKUP(A11,Banks!$A$2:$C$21,3,FALSE) -> Nord-Ovest | C11: =SUMIFS(Data!$E:$E,Data!$A:$A,A11,Data!$B:$B,Control!$B$3) -> 16648 | D11: =SUMIFS(Data!$F$2:$F$5761,Data!$A$2:$A$5761,A11,Data!$B$2:$B$5761,Control!$B$3) -> 897.79 | E11: =SUMIFS(Data!$G$2:$G$5761,Data!$A$2:$A$5761,A11,Data!$B$2:$B$5761,Control!$B$3) -> 540.39 | F11: =D11-E11 -> 357.4 | G11: =SUMIFS(Data!$E$2:$E$5761,Data!$A$2:$A$5761,A11,Data!$B$2:$B$5761,Control!$B$13) -> 16477 | H11: =IFERROR(C11/G11-1,0) -> 0.010378103 | I11: =SUMIFS(Data!$E$2:$E$5761,Data!$A$2:$A$5761,A11,Data!$B$2:$B$5761,Control!$B$14) -> 15173.2 | J11: =IFERROR(C11/I11-1,0) -> 0.097197691 | K11: =C11/SUM($C$2:$C$21) -> 0.048457301 | L11: =RANK(C11,$C$2:$C$21) -> 11 | M11: =_xlfn.MAXIFS(Data!$E$2:$E$5761,Data!$A$2:$A$5761,A11,Data!$C$2:$C$5761,"Mutui") -> 1062.4 | N11: =AVERAGEIFS(Data!$E$2:$E$5761,Data!$A$2:$A$5761,A11,Data!$B$2:$B$5761,Control!$B$3) -> 2081 | O11: =COUNTIFS(Data!$A$2:$A$5761,A11,Data!$B$2:$B$5761,Control!$B$3,Data!$E$2:$E$5761,">"&N11) -> 4 | P11: =INDEX(Budget!$B$2:$AK$21,MATCH(A11,Budget!$A$2:$A$21,0),MATCH(Control!$B$3,Budget!$B$1:$AK$1,0)) -> 16804 | Q11: =C11-P11 -> -156 | R11: =_xlfn.XLOOKUP(A11,Banks!$A$2:$A$21,Banks!$E$2:$E$21) -> Media | S11: =CHOOSE(IF(R11="Grande",1,IF(R11="Media",2,3)),"A","B","C") -> B | T11: {=_xlfn.SWITCH(B11,"Nord-Ovest","NO","Nord-Est","NE","Centro","CE","Sud","SU","IS")} -> NO | U11: =IF(C11>=PERCENTILE($C$2:$C$21,0.75),"primo quartile",IF(C11<=PERCENTILE($C$2:$C$21,0.25),"ultimo quartile","centrale")) -> centrale | V11: =IF(A11=Control!$B$2,"<<","") | W11: =SUMIFS(Data!$H$2:$H$5761,Data!$A$2:$A$5761,A11,Data!$B$2:$B$5761,Control!$B$3) -> 1679 | X11: =IFERROR(D11/W11,0) -> 0.53471709 | Y11: =C11*(1+Control!$B$4) -> 17147.44 | Z11: =IF(B11=Control!$B$5,C11,0) -> 0 | AA11: =_xlfn.LET(_xlpm.v,C11,_xlpm.b,P11,IF(_xlpm.b=0,0,ROUND((_xlpm.v-_xlpm.b)/_xlpm.b,4))) -> -0.0093 | AB11: {=SUMPRODUCT((Data!$A$2:$A$5761=A11)*(Data!$B$2:$B$5761<=Control!$B$3)*(Data!$J$2:$J$5761=Control!$B$11)*Data!$E$2:$E$5761)} -> 16648
A12: =Banks!A12 -> Banca Veneta | B12: =VLOOKUP(A12,Banks!$A$2:$C$21,3,FALSE) -> Nord-Est | C12: =SUMIFS(Data!$E:$E,Data!$A:$A,A12,Data!$B:$B,Control!$B$3) -> 17663.9 | D12: =SUMIFS(Data!$F$2:$F$5761,Data!$A$2:$A$5761,A12,Data!$B$2:$B$5761,Control!$B$3) -> 952.44 | E12: =SUMIFS(Data!$G$2:$G$5761,Data!$A$2:$A$5761,A12,Data!$B$2:$B$5761,Control!$B$3) -> 575.91 | F12: =D12-E12 -> 376.53 | G12: =SUMIFS(Data!$E$2:$E$5761,Data!$A$2:$A$5761,A12,Data!$B$2:$B$5761,Control!$B$13) -> 17610.2 | H12: =IFERROR(C12/G12-1,0) -> 0.0030493691 | I12: =SUMIFS(Data!$E$2:$E$5761,Data!$A$2:$A$5761,A12,Data!$B$2:$B$5761,Control!$B$14) -> 16227.5 | J12: =IFERROR(C12/I12-1,0) -> 0.088516407 | K12: =C12/SUM($C$2:$C$21) -> 0.051414279 | L12: =RANK(C12,$C$2:$C$21) -> 10 | M12: =_xlfn.MAXIFS(Data!$E$2:$E$5761,Data!$A$2:$A$5761,A12,Data!$C$2:$C$5761,"Mutui") -> 1135.6 | N12: =AVERAGEIFS(Data!$E$2:$E$5761,Data!$A$2:$A$5761,A12,Data!$B$2:$B$5761,Control!$B$3) -> 2207.9875 | O12: =COUNTIFS(Data!$A$2:$A$5761,A12,Data!$B$2:$B$5761,Control!$B$3,Data!$E$2:$E$5761,">"&N12) -> 4 | P12: =INDEX(Budget!$B$2:$AK$21,MATCH(A12,Budget!$A$2:$A$21,0),MATCH(Control!$B$3,Budget!$B$1:$AK$1,0)) -> 17937 | Q12: =C12-P12 -> -273.1 | R12: =_xlfn.XLOOKUP(A12,Banks!$A$2:$A$21,Banks!$E$2:$E$21) -> Grande | S12: =CHOOSE(IF(R12="Grande",1,IF(R12="Media",2,3)),"A","B","C") -> A | T12: {=_xlfn.SWITCH(B12,"Nord-Ovest","NO","Nord-Est","NE","Centro","CE","Sud","SU","IS")} -> NE | U12: =IF(C12>=PERCENTILE($C$2:$C$21,0.75),"primo quartile",IF(C12<=PERCENTILE($C$2:$C$21,0.25),"ultimo quartile","centrale")) -> centrale | V12: =IF(A12=Control!$B$2,"<<","") | W12: =SUMIFS(Data!$H$2:$H$5761,Data!$A$2:$A$5761,A12,Data!$B$2:$B$5761,Control!$B$3) -> 1831 | X12: =IFERROR(D12/W12,0) -> 0.52017477 | Y12: =C12*(1+Control!$B$4) -> 18193.817 | Z12: =IF(B12=Control!$B$5,C12,0) -> 0 | AA12: =_xlfn.LET(_xlpm.v,C12,_xlpm.b,P12,IF(_xlpm.b=0,0,ROUND((_xlpm.v-_xlpm.b)/_xlpm.b,4))) -> -0.0152 | AB12: {=SUMPRODUCT((Data!$A$2:$A$5761=A12)*(Data!$B$2:$B$5761<=Control!$B$3)*(Data!$J$2:$J$5761=Control!$B$11)*Data!$E$2:$E$5761)} -> 17663.9
A13: =Banks!A13 -> Banca Friulana | B13: =VLOOKUP(A13,Banks!$A$2:$C$21,3,FALSE) -> Nord-Est | C13: =SUMIFS(Data!$E:$E,Data!$A:$A,A13,Data!$B:$B,Control!$B$3) -> 18941.6 | D13: =SUMIFS(Data!$F$2:$F$5761,Data!$A$2:$A$5761,A13,Data!$B$2:$B$5761,Control!$B$3) -> 1020.23 | E13: =SUMIFS(Data!$G$2:$G$5761,Data!$A$2:$A$5761,A13,Data!$B$2:$B$5761,Control!$B$3) -> 615.31 | F13: =D13-E13 -> 404.92 | G13: =SUMIFS(Data!$E$2:$E$5761,Data!$A$2:$A$5761,A13,Data!$B$2:$B$5761,Control!$B$13) -> 18661.5 | H13: =IFERROR(C13/G13-1,0) -> 0.015009512 | I13: =SUMIFS(Data!$E$2:$E$5761,Data!$A$2:$A$5761,A13,Data!$B$2:$B$5761,Control!$B$14) -> 17231.8 | J13: =IFERROR(C13/I13-1,0) -> 0.099223529 | K13: =C13/SUM($C$2:$C$21) -> 0.055133278 | L13: =RANK(C13,$C$2:$C$21) -> 9 | M13: =_xlfn.MAXIFS(Data!$E$2:$E$5761,Data!$A$2:$A$5761,A13,Data!$C$2:$C$5761,"Mutui") -> 1207 | N13: =AVERAGEIFS(Data!$E$2:$E$5761,Data!$A$2:$A$5761,A13,Data!$B$2:$B$5761,Control!$B$3) -> 2367.7 | O13: =COUNTIFS(Data!$A$2:$A$5761,A13,Data!$B$2:$B$5761,Control!$B$3,Data!$E$2:$E$5761,">"&N13) -> 4 | P13: =INDEX(Budget!$B$2:$AK$21,MATCH(A13,Budget!$A$2:$A$21,0),MATCH(Control!$B$3,Budget!$B$1:$AK$1,0)) -> 19069 | Q13: =C13-P13 -> -127.4 | R13: =_xlfn.XLOOKUP(A13,Banks!$A$2:$A$21,Banks!$E$2:$E$21) -> Media | S13: =CHOOSE(IF(R13="Grande",1,IF(R13="Media",2,3)),"A","B","C") -> B | T13: {=_xlfn.SWITCH(B13,"Nord-Ovest","NO","Nord-Est","NE","Centro","CE","Sud","SU","IS")} -> NE | U13: =IF(C13>=PERCENTILE($C$2:$C$21,0.75),"primo quartile",IF(C13<=PERCENTILE($C$2:$C$21,0.25),"ultimo quartile","centrale")) -> centrale | V13: =IF(A13=Control!$B$2,"<<","") | W13: =SUMIFS(Data!$H$2:$H$5761,Data!$A$2:$A$5761,A13,Data!$B$2:$B$5761,Control!$B$3) -> 1888 | X13: =IFERROR(D13/W13,0) -> 0.54037606 | Y13: =C13*(1+Control!$B$4) -> 19509.848 | Z13: =IF(B13=Control!$B$5,C13,0) -> 0 | AA13: =_xlfn.LET(_xlpm.v,C13,_xlpm.b,P13,IF(_xlpm.b=0,0,ROUND((_xlpm.v-_xlpm.b)/_xlpm.b,4))) -> -0.0067 | AB13: {=SUMPRODUCT((Data!$A$2:$A$5761=A13)*(Data!$B$2:$B$5761<=Control!$B$3)*(Data!$J$2:$J$5761=Control!$B$11)*Data!$E$2:$E$5761)} -> 18941.6
... A21: =Banks!A21 -> Banca Città | B21: =VLOOKUP(A21,Banks!$A$2:$C$21,3,FALSE) -> Centro | C21: =SUMIFS(Data!$E:$E,Data!$A:$A,A21,Data!$B:$B,Control!$B$3) -> 27692.4 | D21: =SUMIFS(Data!$F$2:$F$5761,Data!$A$2:$A$5761,A21,Data!$B$2:$B$5761,Control!$B$3) -> 1493.04 | E21: =SUMIFS(Data!$G$2:$G$5761,Data!$A$2:$A$5761,A21,Data!$B$2:$B$5761,Control!$B$3) -> 899.93 | F21: =D21-E21 -> 593.11 | G21: =SUMIFS(Data!$E$2:$E$5761,Data!$A$2:$A$5761,A21,Data!$B$2:$B$5761,Control!$B$13) -> 27565 | H21: =IFERROR(C21/G21-1,0) -> 0.004621803 | I21: =SUMIFS(Data!$E$2:$E$5761,Data!$A$2:$A$5761,A21,Data!$B$2:$B$5761,Control!$B$14) -> 25464.4 | J21: =IFERROR(C21/I21-1,0) -> 0.087494698 | K21: =C21/SUM($C$2:$C$21) -> 0.080604214 | L21: =RANK(C21,$C$2:$C$21) -> 1 | M21: =_xlfn.MAXIFS(Data!$E$2:$E$5761,Data!$A$2:$A$5761,A21,Data!$C$2:$C$5761,"Mutui") -> 1762 | N21: =AVERAGEIFS(Data!$E$2:$E$5761,Data!$A$2:$A$5761,A21,Data!$B$2:$B$5761,Control!$B$3) -> 3461.55 | O21: =COUNTIFS(Data!$A$2:$A$5761,A21,Data!$B$2:$B$5761,Control!$B$3,Data!$E$2:$E$5761,">"&N21) -> 4 | P21: =INDEX(Budget!$B$2:$AK$21,MATCH(A21,Budget!$A$2:$A$21,0),MATCH(Control!$B$3,Budget!$B$1:$AK$1,0)) -> 28129 | Q21: =C21-P21 -> -436.6 | R21: =_xlfn.XLOOKUP(A21,Banks!$A$2:$A$21,Banks!$E$2:$E$21) -> Grande | S21: =CHOOSE(IF(R21="Grande",1,IF(R21="Media",2,3)),"A","B","C") -> A | T21: {=_xlfn.SWITCH(B21,"Nord-Ovest","NO","Nord-Est","NE","Centro","CE","Sud","SU","IS")} -> CE | U21: =IF(C21>=PERCENTILE($C$2:$C$21,0.75),"primo quartile",IF(C21<=PERCENTILE($C$2:$C$21,0.25),"ultimo quartile","centrale")) -> primo quartile | V21: =IF(A21=Control!$B$2,"<<","") | W21: =SUMIFS(Data!$H$2:$H$5761,Data!$A$2:$A$5761,A21,Data!$B$2:$B$5761,Control!$B$3) -> 2670 | X21: =IFERROR(D21/W21,0) -> 0.55919101 | Y21: =C21*(1+Control!$B$4) -> 28523.172 | Z21: =IF(B21=Control!$B$5,C21,0) -> 27692.4 | AA21: =_xlfn.LET(_xlpm.v,C21,_xlpm.b,P21,IF(_xlpm.b=0,0,ROUND((_xlpm.v-_xlpm.b)/_xlpm.b,4))) -> -0.0155 | AB21: {=SUMPRODUCT((Data!$A$2:$A$5761=A21)*(Data!$B$2:$B$5761<=Control!$B$3)*(Data!$J$2:$J$5761=Control!$B$11)*Data!$E$2:$E$5761)} -> 27692.4
A23: Totale | C23: =SUM(C2:C21) -> 343560.2 | D23: =SUM(D2:D21) -> 18530.43 | E23: =SUM(E2:E21) -> 11192.29 | F23: =SUM(F2:F21) -> 7338.14 | G23: =SUM(G2:G21) -> 340849.5 | K23: =SUM(K2:K21) -> 1

Sheet Calc_Product
A1: Prodotto | B1: Volumi | C1: Ricavi | D1: Costi | E1: Margine | F1: Peso | G1: Margine pesato | H1: Quota | I1: Rango | J1: YTD | K1: Mercato | L1: Quota mercato | M1: Categoria | N1: Riga chiave | O1: Volumi da chiave
A2: =Products!A2 -> Mutui | B2: =SUMIFS(Data!$E$2:$E$5761,Data!$A$2:$A$5761,Control!$B$2,Data!$B$2:$B$5761,Control!$B$3,Data!$C$2:$C$5761,A2) -> 497.8 | C2: =SUMIFS(Data!$F$2:$F$5761,Data!$A$2:$A$5761,Control!$B$2,Data!$B$2:$B$5761,Control!$B$3,Data!$C$2:$C$5761,A2) -> 22.64 | D2: =SUMIFS(Data!$G$2:$G$5761,Data!$A$2:$A$5761,Control!$B$2,Data!$B$2:$B$5761,Control!$B$3,Data!$C$2:$C$5761,A2) -> 14.37 | E2: =C2-D2 -> 8.27 | F2: =VLOOKUP(A2,Products!$A$2:$C$9,3,FALSE) -> 0.6 | G2: =E2*F2 -> 4.962 | H2: =B2/SUM($B$2:$B$9) -> 0.056962387 | I2: =RANK(B2,$B$2:$B$9) -> 8 | J2: =SUMIFS(Data!$E$2:$E$5761,Data!$A$2:$A$5761,Control!$B$2,Data!$B$2:$B$5761,"<="&Control!$B$3,Data!$B$2:$B$5761,">="&Control!$B$22,Data!$C$2:$C$5761,A2) -> 497.8 | K2: =SUMIFS(Data!$E$2:$E$5761,Data!$C$2:$C$5761,A2,Data!$B$2:$B$5761,Control!$B$3) -> 18720 | L2: =B2/K2 -> 0.02659188 | M2: =_xlfn.XLOOKUP(A2,Products!$A$2:$A$9,Products!$B$2:$B$9) -> Credito | N2: =IFERROR(MATCH(Control!$B$2&"|"&Control!$B$3&"|"&A2,Data!$L$2:$L$5761,0),"n.d.") -> 673 | O2: {=INDEX(Data!$E$2:$E$5761,N2)} -> 497.8
A3: =Products!A3 -> Prestiti | B3: =SUMIFS(Data!$E$2:$E$5761,Data!$A$2:$A$5761,Control!$B$2,Data!$B$2:$B$5761,Control!$B$3,Data!$C$2:$C$5761,A3) -> 663.1 | C3: =SUMIFS(Data!$F$2:$F$5761,Data!$A$2:$A$5761,Control!$B$2,Data!$B$2:$B$5761,Control!$B$3,Data!$C$2:$C$5761,A3) -> 31.7 | D3: =SUMIFS(Data!$G$2:$G$5761,Data!$A$2:$A$5761,Control!$B$2,Data!$B$2:$B$5761,Control!$B$3,Data!$C$2:$C$5761,A3) -> 20.08 | E3: =C3-D3 -> 11.62 | F3: =VLOOKUP(A3,Products!$A$2:$C$9,3,FALSE) -> 0.65 | G3: =E3*F3 -> 7.553 | H3: =B3/SUM($B$2:$B$9) -> 0.075877379 | I3: =RANK(B3,$B$2:$B$9) -> 7 | J3: =SUMIFS(Data!$E$2:$E$5761,Data!$A$2:$A$5761,Control!$B$2,Data!$B$2:$B$5761,"<="&Control!$B$3,Data!$B$2:$B$5761,">="&Control!$B$22,Data!$C$2:$C$5761,A3) -> 663.1 | K3: =SUMIFS(Data!$E$2:$E$5761,Data!$C$2:$C$5761,A3,Data!$B$2:$B$5761,Control!$B$3) -> 25649.5 | L3: =B3/K3 -> 0.025852356 | M3: =_xlfn.XLOOKUP(A3,Products!$A$2:$A$9,Products!$B$2:$B$9) -> Credito | N3: =IFERROR(MATCH(Control!$B$2&"|"&Control!$B$3&"|"&A3,Data!$L$2:$L$5761,0),"n.d.") -> 674 | O3: {=INDEX(Data!$E$2:$E$5761,N3)} -> 663.1
A4: =Products!A4 -> Conti | B4: =SUMIFS(Data!$E$2:$E$5761,Data!$A$2:$A$5761,Control!$B$2,Data!$B$2:$B$5761,Control!$B$3,Data!$C$2:$C$5761,A4) -> 855.8 | C4: =SUMIFS(Data!$F$2:$F$5761,Data!$A$2:$A$5761,Control!$B$2,Data!$B$2:$B$5761,Control!$B$3,Data!$C$2:$C$5761,A4) -> 42.37 | D4: =SUMIFS(Data!$G$2:$G$5761,Data!$A$2:$A$5761,Control!$B$2,Data!$B$2:$B$5761,Control!$B$3,Data!$C$2:$C$5761,A4) -> 26.49 | E4: =C4-D4 -> 15.88 | F4: =VLOOKUP(A4,Products!$A$2:$C$9,3,FALSE) -> 0.7 | G4: =E4*F4 -> 11.116 | H4: =B4/SUM($B$2:$B$9) -> 0.097927704 | I4: =RANK(B4,$B$2:$B$9) -> 6 | J4: =SUMIFS(Data!$E$2:$E$5761,Data!$A$2:$A$5761,Control!$B$2,Data!$B$2:$B$5761,"<="&Control!$B$3,Data!$B$2:$B$5761,">="&Control!$B$22,Data!$C$2:$C$5761,A4) -> 855.8 | K4: =SUMIFS(Data!$E$2:$E$5761,Data!$C$2:$C$5761,A4,Data!$B$2:$B$5761,Control!$B$3) -> 32444.9 | L4: =B4/K4 -> 0.026377027 | M4: =_xlfn.XLOOKUP(A4,Products!$A$2:$A$9,Products!$B$2:$B$9) -> Raccolta | N4: =IFERROR(MATCH(Control!$B$2&"|"&Control!$B$3&"|"&A4,Data!$L$2:$L$5761,0),"n.d.") -> 675 | O4: {=INDEX(Data!$E$2:$E$5761,N4)} -> 855.8
A5: =Products!A5 -> Carte | B5: =SUMIFS(Data!$E$2:$E$5761,Data!$A$2:$A$5761,Control!$B$2,Data!$B$2:$B$5761,Control!$B$3,Data!$C$2:$C$5761,A5) -> 1001.7 | C5: =SUMIFS(Data!$F$2:$F$5761,Data!$A$2:$A$5761,Control!$B$2,Data!$B$2:$B$5761,Control!$B$3,Data!$C$2:$C$5761,A5) -> 51.66 | D5: =SUMIFS(Data!$G$2:$G$5761,Data!$A$2:$A$5761,Control!$B$2,Data!$B$2:$B$5761,Control!$B$3,Data!$C$2:$C$5761,A5) -> 31.73 | E5: =C5-D5 -> 19.93 | F5: =VLOOKUP(A5,Products!$A$2:$C$9,3,FALSE) -> 0.75 | G5: =E5*F5 -> 14.9475 | H5: =B5/SUM($B$2:$B$9) -> 0.11462279 | I5: =RANK(B5,$B$2:$B$9) -> 5 | J5: =SUMIFS(Data!$E$2:$E$5761,Data!$A$2:$A$5761,Control!$B$2,Data!$B$2:$B$5761,"<="&Control!$B$3,Data!$B$2:$B$5761,">="&Control!$B$22,Data!$C$2:$C$5761,A5) -> 1001.7 | K5: =SUMIFS(Data!$E$2:$E$5761,Data!$C$2:$C$5761,A5,Data!$B$2:$B$5761,Control!$B$3) -> 39407.4 | L5: =B5/K5 -> 0.025419084 | M5: =_xlfn.XLOOKUP(A5,Products!$A$2:$A$9,Products!$B$2:$B$9) -> Servizi | N5: =IFERROR(MATCH(Control!$B$2&"|"&Control!$B$3&"|"&A5,Data!$L$2:$L$5761,0),"n.d.") -> 676 | O5: {=INDEX(Data!$E$2:$E$5761,N5)} -> 1001.7
A6: =Products!A6 -> Leasing | B6: =SUMIFS(Data!$E$2:$E$5761,Data!$A$2:$A$5761,Control!$B$2,Data!$B$2:$B$5761,Control!$B$3,Data!$C$2:$C$5761,A6) -> 1158.4 | C6: =SUMIFS(Data!$F$2:$F$5761,Data!$A$2:$A$5761,Control!$B$2,Data!$B$2:$B$5761,Control!$B$3,Data!$C$2:$C$5761,A6) -> 61.44 | D6: =SUMIFS(Data!$G$2:$G$5761,Data!$A$2:$A$5761,Control!$B$2,Data!$B$2:$B$5761,Control!$B$3,Data!$C$2:$C$5761,A6) -> 37.91 | E6: =C6-D6 -> 23.53 | F6: =VLOOKUP(A6,Products!$A$2:$C$9,3,FALSE) -> 0.8 | G6: =E6*F6 -> 18.824 | H6: =B6/SUM($B$2:$B$9) -> 0.1325537 | I6: =RANK(B6,$B$2:$B$9) -> 4 | J6: =SUMIFS(Data!$E$2:$E$5761,Data!$A$2:$A$5761,Control!$B$2,Data!$B$2:$B$5761,"<="&Control!$B$3,Data!$B$2:$B$5761,">="&Control!$B$22,Data!$C$2:$C$5761,A6) -> 1158.4 | K6: =SUMIFS(Data!$E$2:$E$5761,Data!$C$2:$C$5761,A6,Data!$B$2:$B$5761,Control!$B$3) -> 46392.1 | L6: =B6/K6 -> 0.024969769 | M6: =_xlfn.XLOOKUP(A6,Products!$A$2:$A$9,Products!$B$2:$B$9) -> Credito | N6: =IFERROR(MATCH(Control!$B$2&"|"&Control!$B$3&"|"&A6,Data!$L$2:$L$5761,0),"n.d.") -> 677 | O6: {=INDEX(Data!$E$2:$E$5761,N6)} -> 1158.4
A7: =Products!A7 -> Factoring | B7: =SUMIFS(Data!$E$2:$E$5761,Data!$A$2:$A$5761,Control!$B$2,Data!$B$2:$B$5761,Control!$B$3,Data!$C$2:$C$5761,A7) -> 1348.1 | C7: =SUMIFS(Data!$F$2:$F$5761,Data!$A$2:$A$5761,Control!$B$2,Data!$B$2:$B$5761,Control!$B$3,Data!$C$2:$C$5761,A7) -> 74.92 | D7: =SUMIFS(Data!$G$2:$G$5761,Data!$A$2:$A$5761,Control!$B$2,Data!$B$2:$B$5761,Control!$B$3,Data!$C$2:$C$5761,A7) -> 44.8 | E7: =C7-D7 -> 30.12 | F7: =VLOOKUP(A7,Products!$A$2:$C$9,3,FALSE) -> 0.85 | G7: =E7*F7 -> 25.602 | H7: =B7/SUM($B$2:$B$9) -> 0.15426074 | I7: =RANK(B7,$B$2:$B$9) -> 3 | J7: =SUMIFS(Data!$E$2:$E$5761,Data!$A$2:$A$5761,Control!$B$2,Data!$B$2:$B$5761,"<="&Control!$B$3,Data!$B$2:$B$5761,">="&Control!$B$22,Data!$C$2:$C$5761,A7) -> 1348.1 | K7: =SUMIFS(Data!$E$2:$E$5761,Data!$C$2:$C$5761,A7,Data!$B$2:$B$5761,Control!$B$3) -> 53441 | L7: =B7/K7 -> 0.02522595 | M7: =_xlfn.XLOOKUP(A7,Products!$A$2:$A$9,Products!$B$2:$B$9) -> Credito | N7: =IFERROR(MATCH(Control!$B$2&"|"&Control!$B$3&"|"&A7,Data!$L$2:$L$5761,0),"n.d.") -> 678 | O7: {=INDEX(Data!$E$2:$E$5761,N7)} -> 1348.1
A8: =Products!A8 -> Risparmio | B8: =SUMIFS(Data!$E$2:$E$5761,Data!$A$2:$A$5761,Control!$B$2,Data!$B$2:$B$5761,Control!$B$3,Data!$C$2:$C$5761,A8) -> 1520.9 | C8: =SUMIFS(Data!$F$2:$F$5761,Data!$A$2:$A$5761,Control!$B$2,Data!$B$2:$B$5761,Control!$B$3,Data!$C$2:$C$5761,A8) -> 87.3 | D8: =SUMIFS(Data!$G$2:$G$5761,Data!$A$2:$A$5761,Control!$B$2,Data!$B$2:$B$5761,Control!$B$3,Data!$C$2:$C$5761,A8) -> 52.62 | E8: =C8-D8 -> 34.68 | F8: =VLOOKUP(A8,Products!$A$2:$C$9,3,FALSE) -> 0.9 | G8: =E8*F8 -> 31.212 | H8: =B8/SUM($B$2:$B$9) -> 0.17403394 | I8: =RANK(B8,$B$2:$B$9) -> 2 | J8: =SUMIFS(Data!$E$2:$E$5761,Data!$A$2:$A$5761,Control!$B$2,Data!$B$2:$B$5761,"<="&Control!$B$3,Data!$B$2:$B$5761,">="&Control!$B$22,Data!$C$2:$C$5761,A8) -> 1520.9 | K8: =SUMIFS(Data!$E$2:$E$5761,Data!$C$2:$C$5761,A8,Data!$B$2:$B$5761,Control!$B$3) -> 60344.3 | L8: =B8/K8 -> 0.025203706 | M8: =_xlfn.XLOOKUP(A8,Products!$A$2:$A$9,Products!$B$2:$B$9) -> Raccolta | N8: =IFERROR(MATCH(Control!$B$2&"|"&Control!$B$3&"|"&A8,Data!$L$2:$L$5761,0),"n.d.") -> 679 | O8: {=INDEX(Data!$E$2:$E$5761,N8)} -> 1520.9
A9: =Products!A9 -> Assicurazioni | B9: =SUMIFS(Data!$E$2:$E$5761,Data!$A$2:$A$5761,Control!$B$2,Data!$B$2:$B$5761,Control!$B$3,Data!$C$2:$C$5761,A9) -> 1693.3 | C9: =SUMIFS(Data!$F$2:$F$5761,Data!$A$2:$A$5761,Control!$B$2,Data!$B$2:$B$5761,Control!$B$3,Data!$C$2:$C$5761,A9) -> 100.01 | D9: =SUMIFS(Data!$G$2:$G$5761,Data!$A$2:$A$5761,Control!$B$2,Data!$B$2:$B$5761,Control!$B$3,Data!$C$2:$C$5761,A9) -> 59.57 | E9: =C9-D9 -> 40.44 | F9: =VLOOKUP(A9,Products!$A$2:$C$9,3,FALSE) -> 0.95 | G9: =E9*F9 -> 38.418 | H9: =B9/SUM($B$2:$B$9) -> 0.19376137 | I9: =RANK(B9,$B$2:$B$9) -> 1 | J9: =SUMIFS(Data!$E$2:$E$5761,Data!$A$2:$A$5761,Control!$B$2,Data!$B$2:$B$5761,"<="&Control!$B$3,Data!$B$2:$B$5761,">="&Control!$B$22,Data!$C$2:$C$5761,A9) -> 1693.3 | K9: =SUMIFS(Data!$E$2:$E$5761,Data!$C$2:$C$5761,A9,Data!$B$2:$B$5761,Control!$B$3) -> 67161 | L9: =B9/K9 -> 0.025212549 | M9: =_xlfn.XLOOKUP(A9,Products!$A$2:$A$9,Products!$B$2:$B$9) -> Servizi | N9: =IFERROR(MATCH(Control!$B$2&"|"&Control!$B$3&"|"&A9,Data!$L$2:$L$5761,0),"n.d.") -> 680 | O9: {=INDEX(Data!$E$2:$E$5761,N9)} -> 1693.3

Sheet Calc_Region
A1: Regione | B1: Banche | C1: Volumi | D1: Ricavi | E1: Margine | F1: Media banca | G1: Max banca | H1: Min banca | I1: Obiettivo | J1: Gap | K1: Quota | L1: Selezionata | M1: Migliore
A2: =Aree!A2 -> Nord-Ovest | B2: =COUNTIF(Banks!$C$2:$C$21,A2) -> 4 | C2: =SUMIFS(Data!$E$2:$E$5761,Data!$I$2:$I$5761,A2,Data!$B$2:$B$5761,Control!$B$3) -> 45188.4 | D2: =SUMIFS(Data!$F$2:$F$5761,Data!$I$2:$I$5761,A2,Data!$B$2:$B$5761,Control!$B$3) -> 2442.1 | E2: =SUMIF(Calc_Bank!$B$2:$B$21,A2,Calc_Bank!$F$2:$F$21) -> 968.48 | F2: =IFERROR(C2/B2,0) -> 11297.1 | G2: =_xlfn.MAXIFS(Calc_Bank!$C$2:$C$21,Calc_Bank!$B$2:$B$21,A2) -> 16648 | H2: =_xlfn.MINIFS(Calc_Bank!$C$2:$C$21,Calc_Bank!$B$2:$B$21,A2) -> 6542.2 | I2: =VLOOKUP(A2,Aree!$A$2:$C$6,3,FALSE) -> 42000 | J2: =C2-I2 -> 3188.4 | K2: =C2/SUM($C$2:$C$6) -> 0.13152979 | L2: =IF(A2=Control!$B$5,"sì","no") -> no | M2: =INDEX(Calc_Bank!$A$2:$A$21,MATCH(G2,Calc_Bank!$C$2:$C$21,0)) -> Banca Ligure
A3: =Aree!A3 -> Nord-Est | B3: =COUNTIF(Banks!$C$2:$C$21,A3) -> 4 | C3: =SUMIFS(Data!$E$2:$E$5761,Data!$I$2:$I$5761,A3,Data!$B$2:$B$5761,Control!$B$3) -> 70996.2 | D3: =SUMIFS(Data!$F$2:$F$5761,Data!$I$2:$I$5761,A3,Data!$B$2:$B$5761,Control!$B$3) -> 3826.13 | E3: =SUMIF(Calc_Bank!$B$2:$B$21,A3,Calc_Bank!$F$2:$F$21) -> 1515.29 | F3: =IFERROR(C3/B3,0) -> 17749.05 | G3: =_xlfn.MAXIFS(Calc_Bank!$C$2:$C$21,Calc_Bank!$B$2:$B$21,A3) -> 26741.1 | H3: =_xlfn.MINIFS(Calc_Bank!$C$2:$C$21,Calc_Bank!$B$2:$B$21,A3) -> 7649.6 | I3: =VLOOKUP(A3,Aree!$A$2:$C$6,3,FALSE) -> 30000 | J3: =C3-I3 -> 40996.2 | K3: =C3/SUM($C$2:$C$6) -> 0.2066485 | L3: =IF(A3=Control!$B$5,"sì","no") -> no | M3: =INDEX(Calc_Bank!$A$2:$A$21,MATCH(G3,Calc_Bank!$C$2:$C$21,0)) -> Banca Romagnola
A4: =Aree!A4 -> Centro | B4: =COUNTIF(Banks!$C$2:$C$21,A4) -> 6 | C4: =SUMIFS(Data!$E$2:$E$5761,Data!$I$2:$I$5761,A4,Data!$B$2:$B$5761,Control!$B$3) -> 101807.3 | D4: =SUMIFS(Data!$F$2:$F$5761,Data!$I$2:$I$5761,A4,Data!$B$2:$B$5761,Control!$B$3) -> 5492.58 | E4: =SUMIF(Calc_Bank!$B$2:$B$21,A4,Calc_Bank!$F$2:$F$21) -> 2172.33 | F4: =IFERROR(C4/B4,0) -> 16967.883 | G4: =_xlfn.MAXIFS(Calc_Bank!$C$2:$C$21,Calc_Bank!$B$2:$B$21,A4) -> 27692.4 | H4: =_xlfn.MINIFS(Calc_Bank!$C$2:$C$21,Calc_Bank!$B$2:$B$21,A4) -> 8739.1 | I4: =VLOOKUP(A4,Aree!$A$2:$C$6,3,FALSE) -> 47000 | J4: =C4-I4 -> 54807.3 | K4: =C4/SUM($C$2:$C$6) -> 0.29633031 | L4: =IF(A4=Control!$B$5,"sì","no") -> sì | M4: =INDEX(Calc_Bank!$A$2:$A$21,MATCH(G4,Calc_Bank!$C$2:$C$21,0)) -> Banca Città
A5: =Aree!A5 -> Sud | B5: =COUNTIF(Banks!$C$2:$C$21,A5) -> 4 | C5: =SUMIFS(Data!$E$2:$E$5761,Data!$I$2:$I$5761,A5,Data!$B$2:$B$5761,Control!$B$3) -> 75423.5 | D5: =SUMIFS(Data!$F$2:$F$5761,Data!$I$2:$I$5761,A5,Data!$B$2:$B$5761,Control!$B$3) -> 4068.55 | E5: =SUMIF(Calc_Bank!$B$2:$B$21,A5,Calc_Bank!$F$2:$F$21) -> 1611.28 | F5: =IFERROR(C5/B5,0) -> 18855.875 | G5: =_xlfn.MAXIFS(Calc_Bank!$C$2:$C$21,Calc_Bank!$B$2:$B$21,A5) -> 23396.2 | H5: =_xlfn.MINIFS(Calc_Bank!$C$2:$C$21,Calc_Bank!$B$2:$B$21,A5) -> 14379.3 | I5: =VLOOKUP(A5,Aree!$A$2:$C$6,3,FALSE) -> 26000 | J5: =C5-I5 -> 49423.5 | K5: =C5/SUM($C$2:$C$6) -> 0.21953503 | L5: =IF(A5=Control!$B$5,"sì","no") -> no | M5: =INDEX(Calc_Bank!$A$2:$A$21,MATCH(G5,Calc_Bank!$C$2:$C$21,0)) -> Banca Calabra
A6: =Aree!A6 -> Isole | B6: =COUNTIF(Banks!$C$2:$C$21,A6) -> 2 | C6: =SUMIFS(Data!$E$2:$E$5761,Data!$I$2:$I$5761,A6,Data!$B$2:$B$5761,Control!$B$3) -> 50144.8 | D6: =SUMIFS(Data!$F$2:$F$5761,Data!$I$2:$I$5761,A6,Data!$B$2:$B$5761,Control!$B$3) -> 2701.07 | E6: =SUMIF(Calc_Bank!$B$2:$B$21,A6,Calc_Bank!$F$2:$F$21) -> 1070.76 | F6: =IFERROR(C6/B6,0) -> 25072.4 | G6: =_xlfn.MAXIFS(Calc_Bank!$C$2:$C$21,Calc_Bank!$B$2:$B$21,A6) -> 25627 | H6: =_xlfn.MINIFS(Calc_Bank!$C$2:$C$21,Calc_Bank!$B$2:$B$21,A6) -> 24517.8 | I6: =VLOOKUP(A6,Aree!$A$2:$C$6,3,FALSE) -> 16000 | J6: =C6-I6 -> 34144.8 | K6: =C6/SUM($C$2:$C$6) -> 0.14595637 | L6: =IF(A6=Control!$B$5,"sì","no") -> no | M6: =INDEX(Calc_Bank!$A$2:$A$21,MATCH(G6,Calc_Bank!$C$2:$C$21,0)) -> Banca Sarda

Sheet Calc_BankMonth
A1: Volumi
A2: Banca \ mese | B2: 1 | C2: 2 | D2: 3 | E2: 4 | F2: 5 | G2: 6 | H2: 7 | I2: 8 | J2: 9 | K2: 10 | L2: 11 | M2: 12 | N2: 13 | O2: 14 | P2: 15 | Q2: 16 | R2: 17 | S2: 18 | T2: 19 | U2: 20 | V2: 21 | W2: 22 | X2: 23 | Y2: 24 | Z2: 25 | AA2: 26 | AB2: 27 | AC2: 28 | AD2: 29 | AE2: 30 | AF2: 31 | AG2: 32 | AH2: 33 | AI2: 34 | AJ2: 35 | AK2: 36
A3: Banca Alpi | B3: =SUMIFS(Data!$E$2:$E$5761,Data!$A$2:$A$5761,$A3,Data!$B$2:$B$5761,B$2) -> 5941.6 | C3: =SUMIFS(Data!$E$2:$E$5761,Data!$A$2:$A$5761,$A3,Data!$B$2:$B$5761,C$2) -> 5956.6 | D3: =SUMIFS(Data!$E$2:$E$5761,Data!$A$2:$A$5761,$A3,Data!$B$2:$B$5761,D$2) -> 6061.7 | E3: =SUMIFS(Data!$E$2:$E$5761,Data!$A$2:$A$5761,$A3,Data!$B$2:$B$5761,E$2) -> 6103 | F3: =SUMIFS(Data!$E$2:$E$5761,Data!$A$2:$A$5761,$A3,Data!$B$2:$B$5761,F$2) -> 6242.9 | G3: =SUMIFS(Data!$E$2:$E$5761,Data!$A$2:$A$5761,$A3,Data!$B$2:$B$5761,G$2) -> 6214.5 | H3: =SUMIFS(Data!$E$2:$E$5761,Data!$A$2:$A$5761,$A3,Data!$B$2:$B$5761,H$2) -> 6269.6 | I3: =SUMIFS(Data!$E$2:$E$5761,Data!$A$2:$A$5761,$A3,Data!$B$2:$B$5761,I$2) -> 6280.5 | ... AK3: =SUMIFS(Data!$E$2:$E$5761,Data!$A$2:$A$5761,$A3,Data!$B$2:$B$5761,AK$2) -> 7595.8
A4: Banca Adriatica | B4: =SUMIFS(Data!$E$2:$E$5761,Data!$A$2:$A$5761,$A4,Data!$B$2:$B$5761,B$2) -> 6980.2 | C4: =SUMIFS(Data!$E$2:$E$5761,Data!$A$2:$A$5761,$A4,Data!$B$2:$B$5761,C$2) -> 7013.2 | D4: =SUMIFS(Data!$E$2:$E$5761,Data!$A$2:$A$5761,$A4,Data!$B$2:$B$5761,D$2) -> 7134.7 | E4: =SUMIFS(Data!$E$2:$E$5761,Data!$A$2:$A$5761,$A4,Data!$B$2:$B$5761,E$2) -> 7204.9 | F4: =SUMIFS(Data!$E$2:$E$5761,Data!$A$2:$A$5761,$A4,Data!$B$2:$B$5761,F$2) -> 7244.9 | G4: =SUMIFS(Data!$E$2:$E$5761,Data!$A$2:$A$5761,$A4,Data!$B$2:$B$5761,G$2) -> 7279.3 | H4: =SUMIFS(Data!$E$2:$E$5761,Data!$A$2:$A$5761,$A4,Data!$B$2:$B$5761,H$2) -> 7201.1 | I4: =SUMIFS(Data!$E$2:$E$5761,Data!$A$2:$A$5761,$A4,Data!$B$2:$B$5761,I$2) -> 7400.1 | ... AK4: =SUMIFS(Data!$E$2:$E$5761,Data!$A$2:$A$5761,$A4,Data!$B$2:$B$5761,AK$2) -> 8954.2
A5: Banca Tirrena | B5: =SUMIFS(Data!$E$2:$E$5761,Data!$A$2:$A$5761,$A5,Data!$B$2:$B$5761,B$2) -> 8012.1 | C5: =SUMIFS(Data!$E$2:$E$5761,Data!$A$2:$A$5761,$A5,Data!$B$2:$B$5761,C$2) -> 8126.5 | D5: =SUMIFS(Data!$E$2:$E$5761,Data!$A$2:$A$5761,$A5,Data!$B$2:$B$5761,D$2) -> 8163.5 | E5: =SUMIFS(Data!$E$2:$E$5761,Data!$A$2:$A$5761,$A5,Data!$B$2:$B$5761,E$2) -> 8209.7 | F5: =SUMIFS(Data!$E$2:$E$5761,Data!$A$2:$A$5761,$A5,Data!$B$2:$B$5761,F$2) -> 8325.2 | G5: =SUMIFS(Data!$E$2:$E$5761,Data!$A$2:$A$5761,$A5,Data!$B$2:$B$5761,G$2) -> 8343.3 | H5: =SUMIFS(Data!$E$2:$E$5761,Data!$A$2:$A$5761,$A5,Data!$B$2:$B$5761,H$2) -> 8405 | I5: =SUMIFS(Data!$E$2:$E$5761,Data!$A$2:$A$5761,$A5,Data!$B$2:$B$5761,I$2) -> 8440.6 | ... AK5: =SUMIFS(Data!$E$2:$E$5761,Data!$A$2:$A$5761,$A5,Data!$B$2:$B$5761,AK$2) -> 10243.3
A6: Banca Padana | B6: =SUMIFS(Data!$E$2:$E$5761,Data!$A$2:$A$5761,$A6,Data!$B$2:$B$5761,B$2) -> 9024.4 | C6: =SUMIFS(Data!$E$2:$E$5761,Data!$A$2:$A$5761,$A6,Data!$B$2:$B$5761,C$2) -> 9114 | D6: =SUMIFS(Data!$E$2:$E$5761,Data!$A$2:$A$5761,$A6,Data!$B$2:$B$5761,D$2) -> 9162.1 | E6: =SUMIFS(Data!$E$2:$E$5761,Data!$A$2:$A$5761,$A6,Data!$B$2:$B$5761,E$2) -> 9314.4 | F6: =SUMIFS(Data!$E$2:$E$5761,Data!$A$2:$A$5761,$A6,Data!$B$2:$B$5761,F$2) -> 9320.9 | G6: =SUMIFS(Data!$E$2:$E$5761,Data!$A$2:$A$5761,$A6,Data!$B$2:$B$5761,G$2) -> 9433 | H6: =SUMIFS(Data!$E$2:$E$5761,Data!$A$2:$A$5761,$A6,Data!$B$2:$B$5761,H$2) -> 9434.4 | I6: =SUMIFS(Data!$E$2:$E$5761,Data!$A$2:$A$5761,$A6,Data!$B$2:$B$5761,I$2) -> 9470.5 | ... AK6: =SUMIFS(Data!$E$2:$E$5761,Data!$A$2:$A$5761,$A6,Data!$B$2:$B$5761,AK$2) -> 11467.1
A7: Banca Etrusca | B7: =SUMIFS(Data!$E$2:$E$5761,Data!$A$2:$A$5761,$A7,Data!$B$2:$B$5761,B$2) -> 9970.8 | C7: =SUMIFS(Data!$E$2:$E$5761,Data!$A$2:$A$5761,$A7,Data!$B$2:$B$5761,C$2) -> 10128.6 | D7: =SUMIFS(Data!$E$2:$E$5761,Data!$A$2:$A$5761,$A7,Data!$B$2:$B$5761,D$2) -> 10240 | E7: =SUMIFS(Data!$E$2:$E$5761,Data!$A$2:$A$5761,$A7,Data!$B$2:$B$5761,E$2) -> 10248.9 | F7: =SUMIFS(Data!$E$2:$E$5761,Data!$A$2:$A$5761,$A7,Data!$B$2:$B$5761,F$2) -> 10292.9 | G7: =SUMIFS(Data!$E$2:$E$5761,Data!$A$2:$A$5761,$A7,Data!$B$2:$B$5761,G$2) -> 10429.8 | H7: =SUMIFS(Data!$E$2:$E$5761,Data!$A$2:$A$5761,$A7,Data!$B$2:$B$5761,H$2) -> 10542.8 | I7: =SUMIFS(Data!$E$2:$E$5761,Data!$A$2:$A$5761,$A7,Data!$B$2:$B$5761,I$2) -> 10604.7 | ... AK7: =SUMIFS(Data!$E$2:$E$5761,Data!$A$2:$A$5761,$A7,Data!$B$2:$B$5761,AK$2) -> 12839.4
A8: Banca Lariana | B8: =SUMIFS(Data!$E$2:$E$5761,Data!$A$2:$A$5761,$A8,Data!$B$2:$B$5761,B$2) -> 11120.3 | C8: =SUMIFS(Data!$E$2:$E$5761,Data!$A$2:$A$5761,$A8,Data!$B$2:$B$5761,C$2) -> 11120.8 | D8: =SUMIFS(Data!$E$2:$E$5761,Data!$A$2:$A$5761,$A8,Data!$B$2:$B$5761,D$2) -> 11205.4 | E8: =SUMIFS(Data!$E$2:$E$5761,Data!$A$2:$A$5761,$A8,Data!$B$2:$B$5761,E$2) -> 11341.3 | F8: =SUMIFS(Data!$E$2:$E$5761,Data!$A$2:$A$5761,$A8,Data!$B$2:$B$5761,F$2) -> 11416.8 | G8: =SUMIFS(Data!$E$2:$E$5761,Data!$A$2:$A$5761,$A8,Data!$B$2:$B$5761,G$2) -> 11471.8 | H8: =SUMIFS(Data!$E$2:$E$5761,Data!$A$2:$A$5761,$A8,Data!$B$2:$B$5761,H$2) -> 11592.1 | I8: =SUMIFS(Data!$E$2:$E$5761,Data!$A$2:$A$5761,$A8,Data!$B$2:$B$5761,I$2) -> 11643.1 | ... AK8: =SUMIFS(Data!$E$2:$E$5761,Data!$A$2:$A$5761,$A8,Data!$B$2:$B$5761,AK$2) -> 14148.1
A9: Banca Sabina | B9: =SUMIFS(Data!$E$2:$E$5761,Data!$A$2:$A$5761,$A9,Data!$B$2:$B$5761,B$2) -> 12033 | C9: =SUMIFS(Data!$E$2:$E$5761,Data!$A$2:$A$5761,$A9,Data!$B$2:$B$5761,C$2) -> 12228.4 | D9: =SUMIFS(Data!$E$2:$E$5761,Data!$A$2:$A$5761,$A9,Data!$B$2:$B$5761,D$2) -> 12355 | E9: =SUMIFS(Data!$E$2:$E$5761,Data!$A$2:$A$5761,$A9,Data!$B$2:$B$5761,E$2) -> 12450.1 | F9: =SUMIFS(Data!$E$2:$E$5761,Data!$A$2:$A$5761,$A9,Data!$B$2:$B$5761,F$2) -> 12425.4 | G9: =SUMIFS(Data!$E$2:$E$5761,Data!$A$2:$A$5761,$A9,Data!$B$2:$B$5761,G$2) -> 12622.9 | H9: =SUMIFS(Data!$E$2:$E$5761,Data!$A$2:$A$5761,$A9,Data!$B$2:$B$5761,H$2) -> 12718.8 | I9: =SUMIFS(Data!$E$2:$E$5761,Data!$A$2:$A$5761,$A9,Data!$B$2:$B$5761,I$2) -> 12771.2 | ... AK9: =SUMIFS(Data!$E$2:$E$5761,Data!$A$2:$A$5761,$A9,Data!$B$2:$B$5761,AK$2) -> 15403.7
A10: Banca Irpina | B10: =SUMIFS(Data!$E$2:$E$5761,Data!$A$2:$A$5761,$A10,Data!$B$2:$B$5761,B$2) -> 13187.6 | C10: =SUMIFS(Data!$E$2:$E$5761,Data!$A$2:$A$5761,$A10,Data!$B$2:$B$5761,C$2) -> 13202.5 | D10: =SUMIFS(Data!$E$2:$E$5761,Data!$A$2:$A$5761,$A10,Data!$B$2:$B$5761,D$2) -> 13350.1 | E10: =SUMIFS(Data!$E$2:$E$5761,Data!$A$2:$A$5761,$A10,Data!$B$2:$B$5761,E$2) -> 13416.3 | F10: =SUMIFS(Data!$E$2:$E$5761,Data!$A$2:$A$5761,$A10,Data!$B$2:$B$5761,F$2) -> 13671.6 | G10: =SUMIFS(Data!$E$2:$E$5761,Data!$A$2:$A$5761,$A10,Data!$B$2:$B$5761,G$2) -> 13682.5 | H10: =SUMIFS(Data!$E$2:$E$5761,Data!$A$2:$A$5761,$A10,Data!$B$2:$B$5761,H$2) -> 13728.2 | I10: =SUMIFS(Data!$E$2:$E$5761,Data!$A$2:$A$5761,$A10,Data!$B$2:$B$5761,I$2) -> 13874.6 | ... AK10: =SUMIFS(Data!$E$2:$E$5761,Data!$A$2:$A$5761,$A10,Data!$B$2:$B$5761,AK$2) -> 16713.9
A11: Banca Sannita | B11: =SUMIFS(Data!$E$2:$E$5761,Data!$A$2:$A$5761,$A11,Data!$B$2:$B$5761,B$2) -> 14125.8 | C11: =SUMIFS(Data!$E$2:$E$5761,Data!$A$2:$A$5761,$A11,Data!$B$2:$B$5761,C$2) -> 14305 | D11: =SUMIFS(Data!$E$2:$E$5761,Data!$A$2:$A$5761,$A11,Data!$B$2:$B$5761,D$2) -> 14342 | E11: =SUMIFS(Data!$E$2:$E$5761,Data!$A$2:$A$5761,$A11,Data!$B$2:$B$5761,E$2) -> 14486.3 | F11: =SUMIFS(Data!$E$2:$E$5761,Data!$A$2:$A$5761,$A11,Data!$B$2:$B$5761,F$2) -> 14645.2 | G11: =SUMIFS(Data!$E$2:$E$5761,Data!$A$2:$A$5761,$A11,Data!$B$2:$B$5761,G$2) -> 14712.6 | H11: =SUMIFS(Data!$E$2:$E$5761,Data!$A$2:$A$5761,$A11,Data!$B$2:$B$5761,H$2) -> 14795.7 | I11: =SUMIFS(Data!$E$2:$E$5761,Data!$A$2:$A$5761,$A11,Data!$B$2:$B$5761,I$2) -> 14843.2 | ... AK11: =SUMIFS(Data!$E$2:$E$5761,Data!$A$2:$A$5761,$A11,Data!$B$2:$B$5761,AK$2) -> 17981.4
A12: Banca Ligure | B12: =SUMIFS(Data!$E$2:$E$5761,Data!$A$2:$A$5761,$A12,Data!$B$2:$B$5761,B$2) -> 15173.2 | C12: =SUMIFS(Data!$E$2:$E$5761,Data!$A$2:$A$5761,$A12,Data!$B$2:$B$5761,C$2) -> 15358.7 | D12: =SUMIFS(Data!$E$2:$E$5761,Data!$A$2:$A$5761,$A12,Data!$B$2:$B$5761,D$2) -> 15416.1 | E12: =SUMIFS(Data!$E$2:$E$5761,Data!$A$2:$A$5761,$A12,Data!$B$2:$B$5761,E$2) -> 15529.3 | F12: =SUMIFS(Data!$E$2:$E$5761,Data!$A$2:$A$5761,$A12,Data!$B$2:$B$5761,F$2) -> 15690.8 | G12: =SUMIFS(Data!$E$2:$E$5761,Data!$A$2:$A$5761,$A12,Data!$B$2:$B$5761,G$2) -> 15784.8 | H12: =SUMIFS(Data!$E$2:$E$5761,Data!$A$2:$A$5761,$A12,Data!$B$2:$B$5761,H$2) -> 15924.8 | I12: =SUMIFS(Data!$E$2:$E$5761,Data!$A$2:$A$5761,$A12,Data!$B$2:$B$5761,I$2) -> 16062.3 | ... AK12: =SUMIFS(Data!$E$2:$E$5761,Data!$A$2:$A$5761,$A12,Data!$B$2:$B$5761,AK$2) -> 19412
A13: Banca Veneta | B13: =SUMIFS(Data!$E$2:$E$5761,Data!$A$2:$A$5761,$A13,Data!$B$2:$B$5761,B$2) -> 16227.5 | C13: =SUMIFS(Data!$E$2:$E$5761,Data!$A$2:$A$5761,$A13,Data!$B$2:$B$5761,C$2) -> 16278.9 | D13: =SUMIFS(Data!$E$2:$E$5761,Data!$A$2:$A$5761,$A13,Data!$B$2:$B$5761,D$2) -> 16398.6 | E13: =SUMIFS(Data!$E$2:$E$5761,Data!$A$2:$A$5761,$A13,Data!$B$2:$B$5761,E$2) -> 16494.9 | F13: =SUMIFS(Data!$E$2:$E$5761,Data!$A$2:$A$5761,$A13,Data!$B$2:$B$5761,F$2) -> 16764.3 | G13: =SUMIFS(Data!$E$2:$E$5761,Data!$A$2:$A$5761,$A13,Data!$B$2:$B$5761,G$2) -> 16806.2 | H13: =SUMIFS(Data!$E$2:$E$5761,Data!$A$2:$A$5761,$A13,Data!$B$2:$B$5761,H$2) -> 16933.3 | I13: =SUMIFS(Data!$E$2:$E$5761,Data!$A$2:$A$5761,$A13,Data!$B$2:$B$5761,I$2) -> 17050.2 | ... AK13: =SUMIFS(Data!$E$2:$E$5761,Data!$A$2:$A$5761,$A13,Data!$B$2:$B$5761,AK$2) -> 20672.4
A14: Banca Friulana | B14: =SUMIFS(Data!$E$2:$E$5761,Data!$A$2:$A$5761,$A14,Data!$B$2:$B$5761,B$2) -> 17231.8 | C14: =SUMIFS(Data!$E$2:$E$5761,Data!$A$2:$A$5761,$A14,Data!$B$2:$B$5761,C$2) -> 17340 | D14: =SUMIFS(Data!$E$2:$E$5761,Data!$A$2:$A$5761,$A14,Data!$B$2:$B$5761,D$2) -> 17449.8 | E14: =SUMIFS(Data!$E$2:$E$5761,Data!$A$2:$A$5761,$A14,Data!$B$2:$B$5761,E$2) -> 17683.7 | F14: =SUMIFS(Data!$E$2:$E$5761,Data!$A$2:$A$5761,$A14,Data!$B$2:$B$5761,F$2) -> 17767.4 | G14: =SUMIFS(Data!$E$2:$E$5761,Data!$A$2:$A$5761,$A14,Data!$B$2:$B$5761,G$2) -> 17910.4 | H14: =SUMIFS(Data!$E$2:$E$5761,Data!$A$2:$A$5761,$A14,Data!$B$2:$B$5761,H$2) -> 17987.7 | I14: =SUMIFS(Data!$E$2:$E$5761,Data!$A$2:$A$5761,$A14,Data!$B$2:$B$5761,I$2) -> 18186.7 | ... AK14: =SUMIFS(Data!$E$2:$E$5761,Data!$A$2:$A$5761,$A14,Data!$B$2:$B$5761,AK$2) -> 21924.5
... A22: Banca Città | B22: =SUMIFS(Data!$E$2:$E$5761,Data!$A$2:$A$5761,$A22,Data!$B$2:$B$5761,B$2) -> 25464.4 | C22: =SUMIFS(Data!$E$2:$E$5761,Data!$A$2:$A$5761,$A22,Data!$B$2:$B$5761,C$2) -> 25625.6 | D22: =SUMIFS(Data!$E$2:$E$5761,Data!$A$2:$A$5761,$A22,Data!$B$2:$B$5761,D$2) -> 25746.7 | E22: =SUMIFS(Data!$E$2:$E$5761,Data!$A$2:$A$5761,$A22,Data!$B$2:$B$5761,E$2) -> 26005.2 | F22: =SUMIFS(Data!$E$2:$E$5761,Data!$A$2:$A$5761,$A22,Data!$B$2:$B$5761,F$2) -> 26185.1 | G22: =SUMIFS(Data!$E$2:$E$5761,Data!$A$2:$A$5761,$A22,Data!$B$2:$B$5761,G$2) -> 26442.4 | H22: =SUMIFS(Data!$E$2:$E$5761,Data!$A$2:$A$5761,$A22,Data!$B$2:$B$5761,H$2) -> 26633.8 | I22: =SUMIFS(Data!$E$2:$E$5761,Data!$A$2:$A$5761,$A22,Data!$B$2:$B$5761,I$2) -> 26809 | ... AK22: =SUMIFS(Data!$E$2:$E$5761,Data!$A$2:$A$5761,$A22,Data!$B$2:$B$5761,AK$2) -> 32434
A23: Totale | B23: =SUM(B3:B22) -> 313649.1 | C23: =SUM(C3:C22) -> 316027.2 | D23: =SUM(D3:D22) -> 318212.6 | E23: =SUM(E3:E22) -> 321020.5 | F23: =SUM(F3:F22) -> 323839.1 | G23: =SUM(G3:G22) -> 326227.2 | H23: =SUM(H3:H22) -> 328451.7 | I23: =SUM(I3:I22) -> 330859.4 | ... AK23: =SUM(AK3:AK22) -> 400259.1
A24: Ricavi
A25: Banca \ mese | B25: 1 | C25: 2 | D25: 3 | E25: 4 | F25: 5 | G25: 6 | H25: 7 | I25: 8 | J25: 9 | K25: 10 | L25: 11 | M25: 12 | N25: 13 | O25: 14 | P25: 15 | Q25: 16 | R25: 17 | S25: 18 | T25: 19 | U25: 20 | V25: 21 | W25: 22 | X25: 23 | Y25: 24 | Z25: 25 | AA25: 26 | AB25: 27 | AC25: 28 | AD25: 29 | AE25: 30 | AF25: 31 | AG25: 32 | AH25: 33 | AI25: 34 | AJ25: 35 | AK25: 36
A26: Banca Alpi | B26: =SUMIFS(Data!$F$2:$F$5761,Data!$A$2:$A$5761,$A26,Data!$B$2:$B$5761,B$25) -> 322.68 | C26: =SUMIFS(Data!$F$2:$F$5761,Data!$A$2:$A$5761,$A26,Data!$B$2:$B$5761,C$25) -> 324.37 | D26: =SUMIFS(Data!$F$2:$F$5761,Data!$A$2:$A$5761,$A26,Data!$B$2:$B$5761,D$25) -> 329.47 | E26: =SUMIFS(Data!$F$2:$F$5761,Data!$A$2:$A$5761,$A26,Data!$B$2:$B$5761,E$25) -> 332.94 | F26: =SUMIFS(Data!$F$2:$F$5761,Data!$A$2:$A$5761,$A26,Data!$B$2:$B$5761,F$25) -> 340.05 | G26: =SUMIFS(Data!$F$2:$F$5761,Data!$A$2:$A$5761,$A26,Data!$B$2:$B$5761,G$25) -> 337.69 | H26: =SUMIFS(Data!$F$2:$F$5761,Data!$A$2:$A$5761,$A26,Data!$B$2:$B$5761,H$25) -> 339.48 | I26: =SUMIFS(Data!$F$2:$F$5761,Data!$A$2:$A$5761,$A26,Data!$B$2:$B$5761,I$25) -> 342.5 | ... AK26: =SUMIFS(Data!$F$2:$F$5761,Data!$A$2:$A$5761,$A26,Data!$B$2:$B$5761,AK$25) -> 411.7
A27: Banca Adriatica | B27: =SUMIFS(Data!$F$2:$F$5761,Data!$A$2:$A$5761,$A27,Data!$B$2:$B$5761,B$25) -> 378.29 | C27: =SUMIFS(Data!$F$2:$F$5761,Data!$A$2:$A$5761,$A27,Data!$B$2:$B$5761,C$25) -> 381.51 | D27: =SUMIFS(Data!$F$2:$F$5761,Data!$A$2:$A$5761,$A27,Data!$B$2:$B$5761,D$25) -> 387.44 | E27: =SUMIFS(Data!$F$2:$F$5761,Data!$A$2:$A$5761,$A27,Data!$B$2:$B$5761,E$25) -> 391.29 | F27: =SUMIFS(Data!$F$2:$F$5761,Data!$A$2:$A$5761,$A27,Data!$B$2:$B$5761,F$25) -> 393.25 | G27: =SUMIFS(Data!$F$2:$F$5761,Data!$A$2:$A$5761,$A27,Data!$B$2:$B$5761,G$25) -> 393.84 | H27: =SUMIFS(Data!$F$2:$F$5761,Data!$A$2:$A$5761,$A27,Data!$B$2:$B$5761,H$25) -> 390.99 | I27: =SUMIFS(Data!$F$2:$F$5761,Data!$A$2:$A$5761,$A27,Data!$B$2:$B$5761,I$25) -> 400.4 | ... AK27: =SUMIFS(Data!$F$2:$F$5761,Data!$A$2:$A$5761,$A27,Data!$B$2:$B$5761,AK$25) -> 485.56
A28: Banca Tirrena | B28: =SUMIFS(Data!$F$2:$F$5761,Data!$A$2:$A$5761,$A28,Data!$B$2:$B$5761,B$25) -> 433.36 | C28: =SUMIFS(Data!$F$2:$F$5761,Data!$A$2:$A$5761,$A28,Data!$B$2:$B$5761,C$25) -> 440.86 | D28: =SUMIFS(Data!$F$2:$F$5761,Data!$A$2:$A$5761,$A28,Data!$B$2:$B$5761,D$25) -> 443.09 | E28: =SUMIFS(Data!$F$2:$F$5761,Data!$A$2:$A$5761,$A28,Data!$B$2:$B$5761,E$25) -> 444.15 | F28: =SUMIFS(Data!$F$2:$F$5761,Data!$A$2:$A$5761,$A28,Data!$B$2:$B$5761,F$25) -> 451.45 | G28: =SUMIFS(Data!$F$2:$F$5761,Data!$A$2:$A$5761,$A28,Data!$B$2:$B$5761,G$25) -> 451.67 | H28: =SUMIFS(Data!$F$2:$F$5761,Data!$A$2:$A$5761,$A28,Data!$B$2:$B$5761,H$25) -> 455.92 | I28: =SUMIFS(Data!$F$2:$F$5761,Data!$A$2:$A$5761,$A28,Data!$B$2:$B$5761,I$25) -> 457.53 | ... AK28: =SUMIFS(Data!$F$2:$F$5761,Data!$A$2:$A$5761,$A28,Data!$B$2:$B$5761,AK$25) -> 555.09
A29: Banca Padana | B29: =SUMIFS(Data!$F$2:$F$5761,Data!$A$2:$A$5761,$A29,Data!$B$2:$B$5761,B$25) -> 487.87 | C29: =SUMIFS(Data!$F$2:$F$5761,Data!$A$2:$A$5761,$A29,Data!$B$2:$B$5761,C$25) -> 492.44 | D29: =SUMIFS(Data!$F$2:$F$5761,Data!$A$2:$A$5761,$A29,Data!$B$2:$B$5761,D$25) -> 494.7 | E29: =SUMIFS(Data!$F$2:$F$5761,Data!$A$2:$A$5761,$A29,Data!$B$2:$B$5761,E$25) -> 504.96 | F29: =SUMIFS(Data!$F$2:$F$5761,Data!$A$2:$A$5761,$A29,Data!$B$2:$B$5761,F$25) -> 504.41 | G29: =SUMIFS(Data!$F$2:$F$5761,Data!$A$2:$A$5761,$A29,Data!$B$2:$B$5761,G$25) -> 509.68 | H29: =SUMIFS(Data!$F$2:$F$5761,Data!$A$2:$A$5761,$A29,Data!$B$2:$B$5761,H$25) -> 509.51 | I29: =SUMIFS(Data!$F$2:$F$5761,Data!$A$2:$A$5761,$A29,Data!$B$2:$B$5761,I$25) -> 512.25 | ... AK29: =SUMIFS(Data!$F$2:$F$5761,Data!$A$2:$A$5761,$A29,Data!$B$2:$B$5761,AK$25) -> 620.24
A30: Banca Etrusca | B30: =SUMIFS(Data!$F$2:$F$5761,Data!$A$2:$A$5761,$A30,Data!$B$2:$B$5761,B$25) -> 539.61 | C30: =SUMIFS(Data!$F$2:$F$5761,Data!$A$2:$A$5761,$A30,Data!$B$2:$B$5761,C$25) -> 547.82 | D30: =SUMIFS(Data!$F$2:$F$5761,Data!$A$2:$A$5761,$A30,Data!$B$2:$B$5761,D$25) -> 554.74 | E30: =SUMIFS(Data!$F$2:$F$5761,Data!$A$2:$A$5761,$A30,Data!$B$2:$B$5761,E$25) -> 555.51 | F30: =SUMIFS(Data!$F$2:$F$5761,Data!$A$2:$A$5761,$A30,Data!$B$2:$B$5761,F$25) -> 556.36 | G30: =SUMIFS(Data!$F$2:$F$5761,Data!$A$2:$A$5761,$A30,Data!$B$2:$B$5761,G$25) -> 562.34 | H30: =SUMIFS(Data!$F$2:$F$5761,Data!$A$2:$A$5761,$A30,Data!$B$2:$B$5761,H$25) -> 570.01 | I30: =SUMIFS(Data!$F$2:$F$5761,Data!$A$2:$A$5761,$A30,Data!$B$2:$B$5761,I$25) -> 573.28 | ... AK30: =SUMIFS(Data!$F$2:$F$5761,Data!$A$2:$A$5761,$A30,Data!$B$2:$B$5761,AK$25) -> 691.67
A31: Banca Lariana | B31: =SUMIFS(Data!$F$2:$F$5761,Data!$A$2:$A$5761,$A31,Data!$B$2:$B$5761,B$25) -> 601.21 | C31: =SUMIFS(Data!$F$2:$F$5761,Data!$A$2:$A$5761,$A31,Data!$B$2:$B$5761,C$25) -> 601.46 | D31: =SUMIFS(Data!$F$2:$F$5761,Data!$A$2:$A$5761,$A31,Data!$B$2:$B$5761,D$25) -> 605.82 | E31: =SUMIFS(Data!$F$2:$F$5761,Data!$A$2:$A$5761,$A31,Data!$B$2:$B$5761,E$25) -> 613.22 | F31: =SUMIFS(Data!$F$2:$F$5761,Data!$A$2:$A$5761,$A31,Data!$B$2:$B$5761,F$25) -> 617.89 | G31: =SUMIFS(Data!$F$2:$F$5761,Data!$A$2:$A$5761,$A31,Data!$B$2:$B$5761,G$25) -> 619.16 | H31: =SUMIFS(Data!$F$2:$F$5761,Data!$A$2:$A$5761,$A31,Data!$B$2:$B$5761,H$25) -> 627.17 | I31: =SUMIFS(Data!$F$2:$F$5761,Data!$A$2:$A$5761,$A31,Data!$B$2:$B$5761,I$25) -> 629.37 | ... AK31: =SUMIFS(Data!$F$2:$F$5761,Data!$A$2:$A$5761,$A31,Data!$B$2:$B$5761,AK$25) -> 763.36
A32: Banca Sabina | B32: =SUMIFS(Data!$F$2:$F$5761,Data!$A$2:$A$5761,$A32,Data!$B$2:$B$5761,B$25) -> 650.96 | C32: =SUMIFS(Data!$F$2:$F$5761,Data!$A$2:$A$5761,$A32,Data!$B$2:$B$5761,C$25) -> 660.45 | D32: =SUMIFS(Data!$F$2:$F$5761,Data!$A$2:$A$5761,$A32,Data!$B$2:$B$5761,D$25) -> 665.26 | E32: =SUMIFS(Data!$F$2:$F$5761,Data!$A$2:$A$5761,$A32,Data!$B$2:$B$5761,E$25) -> 673.75 | F32: =SUMIFS(Data!$F$2:$F$5761,Data!$A$2:$A$5761,$A32,Data!$B$2:$B$5761,F$25) -> 672.54 | G32: =SUMIFS(Data!$F$2:$F$5761,Data!$A$2:$A$5761,$A32,Data!$B$2:$B$5761,G$25) -> 682.81 | H32: =SUMIFS(Data!$F$2:$F$5761,Data!$A$2:$A$5761,$A32,Data!$B$2:$B$5761,H$25) -> 687.66 | I32: =SUMIFS(Data!$F$2:$F$5761,Data!$A$2:$A$5761,$A32,Data!$B$2:$B$5761,I$25) -> 690.55 | ... AK32: =SUMIFS(Data!$F$2:$F$5761,Data!$A$2:$A$5761,$A32,Data!$B$2:$B$5761,AK$25) -> 831.79
A33: Banca Irpina | B33: =SUMIFS(Data!$F$2:$F$5761,Data!$A$2:$A$5761,$A33,Data!$B$2:$B$5761,B$25) -> 713.57 | C33: =SUMIFS(Data!$F$2:$F$5761,Data!$A$2:$A$5761,$A33,Data!$B$2:$B$5761,C$25) -> 713.38 | D33: =SUMIFS(Data!$F$2:$F$5761,Data!$A$2:$A$5761,$A33,Data!$B$2:$B$5761,D$25) -> 721.66 | E33: =SUMIFS(Data!$F$2:$F$5761,Data!$A$2:$A$5761,$A33,Data!$B$2:$B$5761,E$25) -> 723.66 | F33: =SUMIFS(Data!$F$2:$F$5761,Data!$A$2:$A$5761,$A33,Data!$B$2:$B$5761,F$25) -> 740.29 | G33: =SUMIFS(Data!$F$2:$F$5761,Data!$A$2:$A$5761,$A33,Data!$B$2:$B$5761,G$25) -> 737.64 | H33: =SUMIFS(Data!$F$2:$F$5761,Data!$A$2:$A$5761,$A33,Data!$B$2:$B$5761,H$25) -> 741.41 | I33: =SUMIFS(Data!$F$2:$F$5761,Data!$A$2:$A$5761,$A33,Data!$B$2:$B$5761,I$25) -> 748.49 | ... AK33: =SUMIFS(Data!$F$2:$F$5761,Data!$A$2:$A$5761,$A33,Data!$B$2:$B$5761,AK$25) -> 901.97
A34: Banca Sannita | B34: =SUMIFS(Data!$F$2:$F$5761,Data!$A$2:$A$5761,$A34,Data!$B$2:$B$5761,B$25) -> 761.8 | C34: =SUMIFS(Data!$F$2:$F$5761,Data!$A$2:$A$5761,$A34,Data!$B$2:$B$5761,C$25) -> 772.28 | D34: =SUMIFS(Data!$F$2:$F$5761,Data!$A$2:$A$5761,$A34,Data!$B$2:$B$5761,D$25) -> 773.55 | E34: =SUMIFS(Data!$F$2:$F$5761,Data!$A$2:$A$5761,$A34,Data!$B$2:$B$5761,E$25) -> 781.58 | F34: =SUMIFS(Data!$F$2:$F$5761,Data!$A$2:$A$5761,$A34,Data!$B$2:$B$5761,F$25) -> 789.22 | G34: =SUMIFS(Data!$F$2:$F$5761,Data!$A$2:$A$5761,$A34,Data!$B$2:$B$5761,G$25) -> 793.95 | H34: =SUMIFS(Data!$F$2:$F$5761,Data!$A$2:$A$5761,$A34,Data!$B$2:$B$5761,H$25) -> 798.88 | I34: =SUMIFS(Data!$F$2:$F$5761,Data!$A$2:$A$5761,$A34,Data!$B$2:$B$5761,I$25) -> 802.42 | ... AK34: =SUMIFS(Data!$F$2:$F$5761,Data!$A$2:$A$5761,$A34,Data!$B$2:$B$5761,AK$25) -> 967.92
A35: Banca Ligure | B35: =SUMIFS(Data!$F$2:$F$5761,Data!$A$2:$A$5761,$A35,Data!$B$2:$B$5761,B$25) -> 817.15 | C35: =SUMIFS(Data!$F$2:$F$5761,Data!$A$2:$A$5761,$A35,Data!$B$2:$B$5761,C$25) -> 826.58 | D35: =SUMIFS(Data!$F$2:$F$5761,Data!$A$2:$A$5761,$A35,Data!$B$2:$B$5761,D$25) -> 832.02 | E35: =SUMIFS(Data!$F$2:$F$5761,Data!$A$2:$A$5761,$A35,Data!$B$2:$B$5761,E$25) -> 837.76 | F35: =SUMIFS(Data!$F$2:$F$5761,Data!$A$2:$A$5761,$A35,Data!$B$2:$B$5761,F$25) -> 846.87 | G35: =SUMIFS(Data!$F$2:$F$5761,Data!$A$2:$A$5761,$A35,Data!$B$2:$B$5761,G$25) -> 850.88 | H35: =SUMIFS(Data!$F$2:$F$5761,Data!$A$2:$A$5761,$A35,Data!$B$2:$B$5761,H$25) -> 858.43 | I35: =SUMIFS(Data!$F$2:$F$5761,Data!$A$2:$A$5761,$A35,Data!$B$2:$B$5761,I$25) -> 866.89 | ... AK35: =SUMIFS(Data!$F$2:$F$5761,Data!$A$2:$A$5761,$A35,Data!$B$2:$B$5761,AK$25) -> 1046.64
A36: Banca Veneta | B36: =SUMIFS(Data!$F$2:$F$5761,Data!$A$2:$A$5761,$A36,Data!$B$2:$B$5761,B$25) -> 874.79 | C36: =SUMIFS(Data!$F$2:$F$5761,Data!$A$2:$A$5761,$A36,Data!$B$2:$B$5761,C$25) -> 878.52 | D36: =SUMIFS(Data!$F$2:$F$5761,Data!$A$2:$A$5761,$A36,Data!$B$2:$B$5761,D$25) -> 884.74 | E36: =SUMIFS(Data!$F$2:$F$5761,Data!$A$2:$A$5761,$A36,Data!$B$2:$B$5761,E$25) -> 888.14 | F36: =SUMIFS(Data!$F$2:$F$5761,Data!$A$2:$A$5761,$A36,Data!$B$2:$B$5761,F$25) -> 902.45 | G36: =SUMIFS(Data!$F$2:$F$5761,Data!$A$2:$A$5761,$A36,Data!$B$2:$B$5761,G$25) -> 906.5 | H36: =SUMIFS(Data!$F$2:$F$5761,Data!$A$2:$A$5761,$A36,Data!$B$2:$B$5761,H$25) -> 912.47 | I36: =SUMIFS(Data!$F$2:$F$5761,Data!$A$2:$A$5761,$A36,Data!$B$2:$B$5761,I$25) -> 919.98 | ... AK36: =SUMIFS(Data!$F$2:$F$5761,Data!$A$2:$A$5761,$A36,Data!$B$2:$B$5761,AK$25) -> 1114.44
A37: Banca Friulana | B37: =SUMIFS(Data!$F$2:$F$5761,Data!$A$2:$A$5761,$A37,Data!$B$2:$B$5761,B$25) -> 931.36 | C37: =SUMIFS(Data!$F$2:$F$5761,Data!$A$2:$A$5761,$A37,Data!$B$2:$B$5761,C$25) -> 935.56 | D37: =SUMIFS(Data!$F$2:$F$5761,Data!$A$2:$A$5761,$A37,Data!$B$2:$B$5761,D$25) -> 941.54 | E37: =SUMIFS(Data!$F$2:$F$5761,Data!$A$2:$A$5761,$A37,Data!$B$2:$B$5761,E$25) -> 954.55 | F37: =SUMIFS(Data!$F$2:$F$5761,Data!$A$2:$A$5761,$A37,Data!$B$2:$B$5761,F$25) -> 957.88 | G37: =SUMIFS(Data!$F$2:$F$5761,Data!$A$2:$A$5761,$A37,Data!$B$2:$B$5761,G$25) -> 964.98 | H37: =SUMIFS(Data!$F$2:$F$5761,Data!$A$2:$A$5761,$A37,Data!$B$2:$B$5761,H$25) -> 969.94 | I37: =SUMIFS(Data!$F$2:$F$5761,Data!$A$2:$A$5761,$A37,Data!$B$2:$B$5761,I$25) -> 978.88 | ... AK37: =SUMIFS(Data!$F$2:$F$5761,Data!$A$2:$A$5761,$A37,Data!$B$2:$B$5761,AK$25) -> 1181.96
... A45: Banca Città | B45: =SUMIFS(Data!$F$2:$F$5761,Data!$A$2:$A$5761,$A45,Data!$B$2:$B$5761,B$25) -> 1369.14 | C45: =SUMIFS(Data!$F$2:$F$5761,Data!$A$2:$A$5761,$A45,Data!$B$2:$B$5761,C$25) -> 1380.21 | D45: =SUMIFS(Data!$F$2:$F$5761,Data!$A$2:$A$5761,$A45,Data!$B$2:$B$5761,D$25) -> 1385.82 | E45: =SUMIFS(Data!$F$2:$F$5761,Data!$A$2:$A$5761,$A45,Data!$B$2:$B$5761,E$25) -> 1400.76 | F45: =SUMIFS(Data!$F$2:$F$5761,Data!$A$2:$A$5761,$A45,Data!$B$2:$B$5761,F$25) -> 1408.96 | G45: =SUMIFS(Data!$F$2:$F$5761,Data!$A$2:$A$5761,$A45,Data!$B$2:$B$5761,G$25) -> 1425.71 | H45: =SUMIFS(Data!$F$2:$F$5761,Data!$A$2:$A$5761,$A45,Data!$B$2:$B$5761,H$25) -> 1433.29 | I45: =SUMIFS(Data!$F$2:$F$5761,Data!$A$2:$A$5761,$A45,Data!$B$2:$B$5761,I$25) -> 1442.27 | ... AK45: =SUMIFS(Data!$F$2:$F$5761,Data!$A$2:$A$5761,$A45,Data!$B$2:$B$5761,AK$25) -> 1744.5
A46: Totale | B46: =SUM(B26:B45) -> 16920.49 | C46: =SUM(C26:C45) -> 17053.12 | D46: =SUM(D26:D45) -> 17168.06 | E46: =SUM(E26:E45) -> 17321.04 | F46: =SUM(F26:F45) -> 17470.88 | G46: =SUM(G26:G45) -> 17594.7 | H46: =SUM(H26:H45) -> 17719.74 | I46: =SUM(I26:I45) -> 17847.07 | ... AK46: =SUM(AK26:AK45) -> 21571.92
A47: Scenario volumi
A48: Banca \ mese | B48: 1 | C48: 2 | D48: 3 | E48: 4 | F48: 5 | G48: 6 | H48: 7 | I48: 8 | J48: 9 | K48: 10 | L48: 11 | M48: 12 | N48: 13 | O48: 14 | P48: 15 | Q48: 16 | R48: 17 | S48: 18 | T48: 19 | U48: 20 | V48: 21 | W48: 22 | X48: 23 | Y48: 24 | Z48: 25 | AA48: 26 | AB48: 27 | AC48: 28 | AD48: 29 | AE48: 30 | AF48: 31 | AG48: 32 | AH48: 33 | AI48: 34 | AJ48: 35 | AK48: 36
A49: Banca Alpi | B49: =B3*(1+Control!$B$4)^(B$48/12) -> 5956.2536 | C49: =C3*(1+Control!$B$4)^(C$48/12) -> 5986.0174 | D49: =D3*(1+Control!$B$4)^(D$48/12) -> 6106.6601 | E49: =E3*(1+Control!$B$4)^(E$48/12) -> 6163.4297 | F49: =F3*(1+Control!$B$4)^(F$48/12) -> 6320.264 | G49: =G3*(1+Control!$B$4)^(G$48/12) -> 6307.0287 | H49: =H3*(1+Control!$B$4)^(H$48/12) -> 6378.6418 | I49: =I3*(1+Control!$B$4)^(I$48/12) -> 6405.4902 | ... AK49: =AK3*(1+Control!$B$4)^(AK$48/12) -> 8300.1357
A50: Banca Adriatica | B50: =B4*(1+Control!$B$4)^(B$48/12) -> 6997.4151 | C50: =C4*(1+Control!$B$4)^(C$48/12) -> 7047.8355 | D50: =D4*(1+Control!$B$4)^(D$48/12) -> 7187.6186 | E50: =E4*(1+Control!$B$4)^(E$48/12) -> 7276.2403 | F50: =F4*(1+Control!$B$4)^(F$48/12) -> 7334.6811 | G50: =G4*(1+Control!$B$4)^(G$48/12) -> 7387.6826 | H50: =H4*(1+Control!$B$4)^(H$48/12) -> 7326.3426 | I50: =I4*(1+Control!$B$4)^(I$48/12) -> 7547.3717 | ... AK50: =AK4*(1+Control!$B$4)^(AK$48/12) -> 9784.4961
A51: Banca Tirrena | B51: =B5*(1+Control!$B$4)^(B$48/12) -> 8031.86 | C51: =C5*(1+Control!$B$4)^(C$48/12) -> 8166.6337 | D51: =D5*(1+Control!$B$4)^(D$48/12) -> 8224.0493 | E51: =E5*(1+Control!$B$4)^(E$48/12) -> 8290.9894 | F51: =F5*(1+Control!$B$4)^(F$48/12) -> 8428.3686 | G51: =G5*(1+Control!$B$4)^(G$48/12) -> 8467.5247 | H51: =H5*(1+Control!$B$4)^(H$48/12) -> 8551.181 | I51: =I5*(1+Control!$B$4)^(I$48/12) -> 8608.579 | ... AK51: =AK5*(1+Control!$B$4)^(AK$48/12) -> 11193.13
A52: Banca Padana | B52: =B6*(1+Control!$B$4)^(B$48/12) -> 9046.6566 | C52: =C6*(1+Control!$B$4)^(C$48/12) -> 9159.0106 | D52: =D6*(1+Control!$B$4)^(D$48/12) -> 9230.056 | E52: =E6*(1+Control!$B$4)^(E$48/12) -> 9406.6278 | F52: =F6*(1+Control!$B$4)^(F$48/12) -> 9436.4076 | G52: =G6*(1+Control!$B$4)^(G$48/12) -> 9573.4494 | H52: =H6*(1+Control!$B$4)^(H$48/12) -> 9598.4845 | I52: =I6*(1+Control!$B$4)^(I$48/12) -> 9658.9754 | ... AK52: =AK6*(1+Control!$B$4)^(AK$48/12) -> 12530.41
A53: Banca Etrusca | B53: =B7*(1+Control!$B$4)^(B$48/12) -> 9995.3907 | C53: =C7*(1+Control!$B$4)^(C$48/12) -> 10178.621 | D53: =D7*(1+Control!$B$4)^(D$48/12) -> 10315.951 | E53: =E7*(1+Control!$B$4)^(E$48/12) -> 10350.381 | F53: =F7*(1+Control!$B$4)^(F$48/12) -> 10420.453 | G53: =G7*(1+Control!$B$4)^(G$48/12) -> 10585.091 | H53: =H7*(1+Control!$B$4)^(H$48/12) -> 10726.162 | I53: =I7*(1+Control!$B$4)^(I$48/12) -> 10815.747 | ... AK53: =AK7*(1+Control!$B$4)^(AK$48/12) -> 14029.959
A54: Banca Lariana | B54: =B8*(1+Control!$B$4)^(B$48/12) -> 11147.726 | C54: =C8*(1+Control!$B$4)^(C$48/12) -> 11175.721 | D54: =D8*(1+Control!$B$4)^(D$48/12) -> 11288.511 | E54: =E8*(1+Control!$B$4)^(E$48/12) -> 11453.597 | F54: =F8*(1+Control!$B$4)^(F$48/12) -> 11558.281 | G54: =G8*(1+Control!$B$4)^(G$48/12) -> 11642.605 | H54: =H8*(1+Control!$B$4)^(H$48/12) -> 11793.712 | I54: =I8*(1+Control!$B$4)^(I$48/12) -> 11874.813 | ... AK54: =AK8*(1+Control!$B$4)^(AK$48/12) -> 15460.011
A55: Banca Sabina | B55: =B9*(1+Control!$B$4)^(B$48/12) -> 12062.677 | C55: =C9*(1+Control!$B$4)^(C$48/12) -> 12288.791 | D55: =D9*(1+Control!$B$4)^(D$48/12) -> 12446.638 | E55: =E9*(1+Control!$B$4)^(E$48/12) -> 12573.376 | F55: =F9*(1+Control!$B$4)^(F$48/12) -> 12579.38 | G55: =G9*(1+Control!$B$4)^(G$48/12) -> 12810.844 | H55: =H9*(1+Control!$B$4)^(H$48/12) -> 12940.007 | I55: =I9*(1+Control!$B$4)^(I$48/12) -> 13025.364 | ... AK55: =AK9*(1+Control!$B$4)^(AK$48/12) -> 16832.039
A56: Banca Irpina | B56: =B10*(1+Control!$B$4)^(B$48/12) -> 13220.124 | C56: =C10*(1+Control!$B$4)^(C$48/12) -> 13267.702 | D56: =D10*(1+Control!$B$4)^(D$48/12) -> 13449.119 | E56: =E10*(1+Control!$B$4)^(E$48/12) -> 13549.143 | F56: =F10*(1+Control!$B$4)^(F$48/12) -> 13841.023 | G56: =G10*(1+Control!$B$4)^(G$48/12) -> 13886.221 | H56: =H10*(1+Control!$B$4)^(H$48/12) -> 13966.963 | I56: =I10*(1+Control!$B$4)^(I$48/12) -> 14150.723 | ... AK56: =AK10*(1+Control!$B$4)^(AK$48/12) -> 18263.73
A57: Banca Sannita | B57: =B11*(1+Control!$B$4)^(B$48/12) -> 14160.638 | C57: =C11*(1+Control!$B$4)^(C$48/12) -> 14375.647 | D57: =D11*(1+Control!$B$4)^(D$48/12) -> 14448.376 | E57: =E11*(1+Control!$B$4)^(E$48/12) -> 14629.738 | F57: =F11*(1+Control!$B$4)^(F$48/12) -> 14826.688 | G57: =G11*(1+Control!$B$4)^(G$48/12) -> 14931.658 | H57: =H11*(1+Control!$B$4)^(H$48/12) -> 15053.029 | I57: =I11*(1+Control!$B$4)^(I$48/12) -> 15138.599 | ... AK57: =AK11*(1+Control!$B$4)^(AK$48/12) -> 19648.761
A58: Banca Ligure | B58: =B12*(1+Control!$B$4)^(B$48/12) -> 15210.621 | C58: =C12*(1+Control!$B$4)^(C$48/12) -> 15434.551 | D58: =D12*(1+Control!$B$4)^(D$48/12) -> 15530.442 | E58: =E12*(1+Control!$B$4)^(E$48/12) -> 15683.065 | F58: =F12*(1+Control!$B$4)^(F$48/12) -> 15885.245 | G58: =G12*(1+Control!$B$4)^(G$48/12) -> 16019.822 | H58: =H12*(1+Control!$B$4)^(H$48/12) -> 16201.766 | I58: =I12*(1+Control!$B$4)^(I$48/12) -> 16381.961 | ... AK58: =AK12*(1+Control!$B$4)^(AK$48/12) -> 21212.017
A59: Banca Veneta | B59: =B13*(1+Control!$B$4)^(B$48/12) -> 16267.521 | C59: =C13*(1+Control!$B$4)^(C$48/12) -> 16359.295 | D59: =D13*(1+Control!$B$4)^(D$48/12) -> 16520.23 | E59: =E13*(1+Control!$B$4)^(E$48/12) -> 16658.226 | F59: =F13*(1+Control!$B$4)^(F$48/12) -> 16972.049 | G59: =G13*(1+Control!$B$4)^(G$48/12) -> 17056.43 | H59: =H13*(1+Control!$B$4)^(H$48/12) -> 17227.806 | I59: =I13*(1+Control!$B$4)^(I$48/12) -> 17389.521 | ... AK59: =AK13*(1+Control!$B$4)^(AK$48/12) -> 22589.29
A60: Banca Friulana | B60: =B14*(1+Control!$B$4)^(B$48/12) -> 17274.298 | C60: =C14*(1+Control!$B$4)^(C$48/12) -> 17425.636 | D60: =D14*(1+Control!$B$4)^(D$48/12) -> 17579.226 | E60: =E14*(1+Control!$B$4)^(E$48/12) -> 17858.798 | F60: =F14*(1+Control!$B$4)^(F$48/12) -> 17987.579 | G60: =G14*(1+Control!$B$4)^(G$48/12) -> 18177.071 | H60: =H14*(1+Control!$B$4)^(H$48/12) -> 18300.545 | I60: =I14*(1+Control!$B$4)^(I$48/12) -> 18548.639 | ... AK60: =AK14*(1+Control!$B$4)^(AK$48/12) -> 23957.493
... A68: Banca Città | B68: =B22*(1+Control!$B$4)^(B$48/12) -> 25527.202 | C68: =C22*(1+Control!$B$4)^(C$48/12) -> 25752.155 | D68: =D22*(1+Control!$B$4)^(D$48/12) -> 25937.665 | E68: =E22*(1+Control!$B$4)^(E$48/12) -> 26262.694 | F68: =F22*(1+Control!$B$4)^(F$48/12) -> 26509.594 | G68: =G22*(1+Control!$B$4)^(G$48/12) -> 26836.105 | H68: =H22*(1+Control!$B$4)^(H$48/12) -> 27097.019 | I68: =I22*(1+Control!$B$4)^(I$48/12) -> 27342.534 | ... AK68: =AK22*(1+Control!$B$4)^(AK$48/12) -> 35441.508

Sheet Calc_Growth
A2: Banca \ mese | B2: 1 | C2: 2 | D2: 3 | E2: 4 | F2: 5 | G2: 6 | H2: 7 | I2: 8 | J2: 9 | K2: 10 | L2: 11 | M2: 12 | N2: 13 | O2: 14 | P2: 15 | Q2: 16 | R2: 17 | S2: 18 | T2: 19 | U2: 20 | V2: 21 | W2: 22 | X2: 23 | Y2: 24 | Z2: 25 | AA2: 26 | AB2: 27 | AC2: 28 | AD2: 29 | AE2: 30 | AF2: 31 | AG2: 32 | AH2: 33 | AI2: 34 | AJ2: 35 | AK2: 36 | AM2: Media | AN2: Max | AO2: Min | AP2: Mese max
A3: Banca Alpi | C3: =IFERROR(Calc_BankMonth!C3/Calc_BankMonth!B3-1,0) -> 0.0025245725 | D3: =IFERROR(Calc_BankMonth!D3/Calc_BankMonth!C3-1,0) -> 0.017644294 | E3: =IFERROR(Calc_BankMonth!E3/Calc_BankMonth!D3-1,0) -> 0.0068132702 | F3: =IFERROR(Calc_BankMonth!F3/Calc_BankMonth!E3-1,0) -> 0.022923153 | G3: =IFERROR(Calc_BankMonth!G3/Calc_BankMonth!F3-1,0) -> -0.0045491679 | H3: =IFERROR(Calc_BankMonth!H3/Calc_BankMonth!G3-1,0) -> 0.0088663609 | I3: =IFERROR(Calc_BankMonth!I3/Calc_BankMonth!H3-1,0) -> 0.0017385479 | J3: =IFERROR(Calc_BankMonth!J3/Calc_BankMonth!I3-1,0) -> 0.0059867845 | ... AK3: =IFERROR(Calc_BankMonth!AK3/Calc_BankMonth!AJ3-1,0) -> 0.0015162902 | AM3: =AVERAGE(C3:AK3) -> 0.007098302 | AN3: =MAX(C3:AK3) -> 0.024233517 | AO3: =MIN(C3:AK3) -> -0.016847688 | AP3: =MATCH(AN3,C3:AK3,0)+1 -> 12
A4: Banca Adriatica | C4: =IFERROR(Calc_BankMonth!C4/Calc_BankMonth!B4-1,0) -> 0.0047276582 | D4: =IFERROR(Calc_BankMonth!D4/Calc_BankMonth!C4-1,0) -> 0.017324474 | E4: =IFERROR(Calc_BankMonth!E4/Calc_BankMonth!D4-1,0) -> 0.0098392364 | F4: =IFERROR(Calc_BankMonth!F4/Calc_BankMonth!E4-1,0) -> 0.0055517773 | G4: =IFERROR(Calc_BankMonth!G4/Calc_BankMonth!F4-1,0) -> 0.0047481677 | H4: =IFERROR(Calc_BankMonth!H4/Calc_BankMonth!G4-1,0) -> -0.010742791 | I4: =IFERROR(Calc_BankMonth!I4/Calc_BankMonth!H4-1,0) -> 0.027634667 | J4: =IFERROR(Calc_BankMonth!J4/Calc_BankMonth!I4-1,0) -> 0.012297131 | ... AK4: =IFERROR(Calc_BankMonth!AK4/Calc_BankMonth!AJ4-1,0) -> 0.0068591733 | AM4: =AVERAGE(C4:AK4) -> 0.0071750814 | AN4: =MAX(C4:AK4) -> 0.028621581 | AO4: =MIN(C4:AK4) -> -0.011296376 | AP4: =MATCH(AN4,C4:AK4,0)+1 -> 11
A5: Banca Tirrena | C5: =IFERROR(Calc_BankMonth!C5/Calc_BankMonth!B5-1,0) -> 0.014278404 | D5: =IFERROR(Calc_BankMonth!D5/Calc_BankMonth!C5-1,0) -> 0.0045530056 | E5: =IFERROR(Calc_BankMonth!E5/Calc_BankMonth!D5-1,0) -> 0.0056593373 | F5: =IFERROR(Calc_BankMonth!F5/Calc_BankMonth!E5-1,0) -> 0.014068724 | G5: =IFERROR(Calc_BankMonth!G5/Calc_BankMonth!F5-1,0) -> 0.0021741219 | H5: =IFERROR(Calc_BankMonth!H5/Calc_BankMonth!G5-1,0) -> 0.0073951554 | I5: =IFERROR(Calc_BankMonth!I5/Calc_BankMonth!H5-1,0) -> 0.0042355741 | J5: =IFERROR(Calc_BankMonth!J5/Calc_BankMonth!I5-1,0) -> 0.0069900244 | ... AK5: =IFERROR(Calc_BankMonth!AK5/Calc_BankMonth!AJ5-1,0) -> -0.00086810636 | AM5: =AVERAGE(C5:AK5) -> 0.0070587736 | AN5: =MAX(C5:AK5) -> 0.017095471 | AO5: =MIN(C5:AK5) -> -0.0065268113 | AP5: =MATCH(AN5,C5:AK5,0)+1 -> 25
A6: Banca Padana | C6: =IFERROR(Calc_BankMonth!C6/Calc_BankMonth!B6-1,0) -> 0.0099286379 | D6: =IFERROR(Calc_BankMonth!D6/Calc_BankMonth!C6-1,0) -> 0.0052775949 | E6: =IFERROR(Calc_BankMonth!E6/Calc_BankMonth!D6-1,0) -> 0.016622827 | F6: =IFERROR(Calc_BankMonth!F6/Calc_BankMonth!E6-1,0) -> 0.0006978442 | G6: =IFERROR(Calc_BankMonth!G6/Calc_BankMonth!F6-1,0) -> 0.012026736 | H6: =IFERROR(Calc_BankMonth!H6/Calc_BankMonth!G6-1,0) -> 0.00014841514 | I6: =IFERROR(Calc_BankMonth!I6/Calc_BankMonth!H6-1,0) -> 0.0038264225 | J6: =IFERROR(Calc_BankMonth!J6/Calc_BankMonth!I6-1,0) -> 0.017707618 | ... AK6: =IFERROR(Calc_BankMonth!AK6/Calc_BankMonth!AJ6-1,0) -> -0.0047302458 | AM6: =AVERAGE(C6:AK6) -> 0.0068922028 | AN6: =MAX(C6:AK6) -> 0.025439843 | AO6: =MIN(C6:AK6) -> -0.0047302458 | AP6: =MATCH(AN6,C6:AK6,0)+1 -> 17
A7: Banca Etrusca | C7: =IFERROR(Calc_BankMonth!C7/Calc_BankMonth!B7-1,0) -> 0.015826213 | D7: =IFERROR(Calc_BankMonth!D7/Calc_BankMonth!C7-1,0) -> 0.010998559 | E7: =IFERROR(Calc_BankMonth!E7/Calc_BankMonth!D7-1,0) -> 0.00086914062 | F7: =IFERROR(Calc_BankMonth!F7/Calc_BankMonth!E7-1,0) -> 0.0042931437 | G7: =IFERROR(Calc_BankMonth!G7/Calc_BankMonth!F7-1,0) -> 0.01330043 | H7: =IFERROR(Calc_BankMonth!H7/Calc_BankMonth!G7-1,0) -> 0.01083434 | I7: =IFERROR(Calc_BankMonth!I7/Calc_BankMonth!H7-1,0) -> 0.0058713055 | J7: =IFERROR(Calc_BankMonth!J7/Calc_BankMonth!I7-1,0) -> 0.01207955 | ... AK7: =IFERROR(Calc_BankMonth!AK7/Calc_BankMonth!AJ7-1,0) -> 0.0031643344 | AM7: =AVERAGE(C7:AK7) -> 0.00726045 | AN7: =MAX(C7:AK7) -> 0.015826213 | AO7: =MIN(C7:AK7) -> -0.0012095926 | AP7: =MATCH(AN7,C7:AK7,0)+1 -> 2
A8: Banca Lariana | C8: =IFERROR(Calc_BankMonth!C8/Calc_BankMonth!B8-1,0) -> 4.4962816e-05 | D8: =IFERROR(Calc_BankMonth!D8/Calc_BankMonth!C8-1,0) -> 0.0076073664 | E8: =IFERROR(Calc_BankMonth!E8/Calc_BankMonth!D8-1,0) -> 0.012128081 | F8: =IFERROR(Calc_BankMonth!F8/Calc_BankMonth!E8-1,0) -> 0.0066570852 | G8: =IFERROR(Calc_BankMonth!G8/Calc_BankMonth!F8-1,0) -> 0.004817462 | H8: =IFERROR(Calc_BankMonth!H8/Calc_BankMonth!G8-1,0) -> 0.010486584 | I8: =IFERROR(Calc_BankMonth!I8/Calc_BankMonth!H8-1,0) -> 0.004399548 | J8: =IFERROR(Calc_BankMonth!J8/Calc_BankMonth!I8-1,0) -> 0.012599737 | ... AK8: =IFERROR(Calc_BankMonth!AK8/Calc_BankMonth!AJ8-1,0) -> 0.0043159441 | AM8: =AVERAGE(C8:AK8) -> 0.006922145 | AN8: =MAX(C8:AK8) -> 0.020890712 | AO8: =MIN(C8:AK8) -> -0.0052672649 | AP8: =MATCH(AN8,C8:AK8,0)+1 -> 11
A9: Banca Sabina | C9: =IFERROR(Calc_BankMonth!C9/Calc_BankMonth!B9-1,0) -> 0.016238677 | D9: =IFERROR(Calc_BankMonth!D9/Calc_BankMonth!C9-1,0) -> 0.010352949 | E9: =IFERROR(Calc_BankMonth!E9/Calc_BankMonth!D9-1,0) -> 0.0076972885 | F9: =IFERROR(Calc_BankMonth!F9/Calc_BankMonth!E9-1,0) -> -0.0019839198 | G9: =IFERROR(Calc_BankMonth!G9/Calc_BankMonth!F9-1,0) -> 0.015894861 | H9: =IFERROR(Calc_BankMonth!H9/Calc_BankMonth!G9-1,0) -> 0.0075973033 | I9: =IFERROR(Calc_BankMonth!I9/Calc_BankMonth!H9-1,0) -> 0.0041198855 | J9: =IFERROR(Calc_BankMonth!J9/Calc_BankMonth!I9-1,0) -> 0.0085974693 | ... AK9: =IFERROR(Calc_BankMonth!AK9/Calc_BankMonth!AJ9-1,0) -> 0.0011959468 | AM9: =AVERAGE(C9:AK9) -> 0.0070963479 | AN9: =MAX(C9:AK9) -> 0.016238677 | AO9: =MIN(C9:AK9) -> -0.0072854404 | AP9: =MATCH(AN9,C9:AK9,0)+1 -> 2
A10: Banca Irpina | C10: =IFERROR(Calc_BankMonth!C10/Calc_BankMonth!B10-1,0) -> 0.0011298493 | D10: =IFERROR(Calc_BankMonth!D10/Calc_BankMonth!C10-1,0) -> 0.011179701 | E10: =IFERROR(Calc_BankMonth!E10/Calc_BankMonth!D10-1,0) -> 0.0049587644 | F10: =IFERROR(Calc_BankMonth!F10/Calc_BankMonth!E10-1,0) -> 0.019029091 | G10: =IFERROR(Calc_BankMonth!G10/Calc_BankMonth!F10-1,0) -> 0.00079727318 | H10: =IFERROR(Calc_BankMonth!H10/Calc_BankMonth!G10-1,0) -> 0.0033400329 | I10: =IFERROR(Calc_BankMonth!I10/Calc_BankMonth!H10-1,0) -> 0.01066418 | J10: =IFERROR(Calc_BankMonth!J10/Calc_BankMonth!I10-1,0) -> 0.0046631975 | ... AK10: =IFERROR(Calc_BankMonth!AK10/Calc_BankMonth!AJ10-1,0) -> 0.007025239 | AM10: =AVERAGE(C10:AK10) -> 0.0068045908 | AN10: =MAX(C10:AK10) -> 0.019029091 | AO10: =MIN(C10:AK10) -> -0.0027546415 | AP10: =MATCH(AN10,C10:AK10,0)+1 -> 5
A11: Banca Sannita | C11: =IFERROR(Calc_BankMonth!C11/Calc_BankMonth!B11-1,0) -> 0.012686007 | D11: =IFERROR(Calc_BankMonth!D11/Calc_BankMonth!C11-1,0) -> 0.0025865082 | E11: =IFERROR(Calc_BankMonth!E11/Calc_BankMonth!D11-1,0) -> 0.010061358 | F11: =IFERROR(Calc_BankMonth!F11/Calc_BankMonth!E11-1,0) -> 0.010968984 | G11: =IFERROR(Calc_BankMonth!G11/Calc_BankMonth!F11-1,0) -> 0.0046021905 | H11: =IFERROR(Calc_BankMonth!H11/Calc_BankMonth!G11-1,0) -> 0.0056482199 | I11: =IFERROR(Calc_BankMonth!I11/Calc_BankMonth!H11-1,0) -> 0.0032103922 | J11: =IFERROR(Calc_BankMonth!J11/Calc_BankMonth!I11-1,0) -> 0.016835992 | ... AK11: =IFERROR(Calc_BankMonth!AK11/Calc_BankMonth!AJ11-1,0) -> 0.0040034171 | AM11: =AVERAGE(C11:AK11) -> 0.0069290756 | AN11: =MAX(C11:AK11) -> 0.016835992 | AO11: =MIN(C11:AK11) -> 0.00050149594 | AP11: =MATCH(AN11,C11:AK11,0)+1 -> 9
A12: Banca Ligure | C12: =IFERROR(Calc_BankMonth!C12/Calc_BankMonth!B12-1,0) -> 0.012225503 | D12: =IFERROR(Calc_BankMonth!D12/Calc_BankMonth!C12-1,0) -> 0.0037372955 | E12: =IFERROR(Calc_BankMonth!E12/Calc_BankMonth!D12-1,0) -> 0.0073429726 | F12: =IFERROR(Calc_BankMonth!F12/Calc_BankMonth!E12-1,0) -> 0.010399696 | G12: =IFERROR(Calc_BankMonth!G12/Calc_BankMonth!F12-1,0) -> 0.0059907717 | H12: =IFERROR(Calc_BankMonth!H12/Calc_BankMonth!G12-1,0) -> 0.008869292 | I12: =IFERROR(Calc_BankMonth!I12/Calc_BankMonth!H12-1,0) -> 0.0086343314 | J12: =IFERROR(Calc_BankMonth!J12/Calc_BankMonth!I12-1,0) -> 0.0018365987 | ... AK12: =IFERROR(Calc_BankMonth!AK12/Calc_BankMonth!AJ12-1,0) -> 0.0053447133 | AM12: =AVERAGE(C12:AK12) -> 0.007069289 | AN12: =MAX(C12:AK12) -> 0.01265269 | AO12: =MIN(C12:AK12) -> -0.00011354672 | AP12: =MATCH(AN12,C12:AK12,0)+1 -> 19
A13: Banca Veneta | C13: =IFERROR(Calc_BankMonth!C13/Calc_BankMonth!B13-1,0) -> 0.0031674626 | D13: =IFERROR(Calc_BankMonth!D13/Calc_BankMonth!C13-1,0) -> 0.0073530767 | E13: =IFERROR(Calc_BankMonth!E13/Calc_BankMonth!D13-1,0) -> 0.0058724525 | F13: =IFERROR(Calc_BankMonth!F13/Calc_BankMonth!E13-1,0) -> 0.016332321 | G13: =IFERROR(Calc_BankMonth!G13/Calc_BankMonth!F13-1,0) -> 0.0024993588 | H13: =IFERROR(Calc_BankMonth!H13/Calc_BankMonth!G13-1,0) -> 0.0075626852 | I13: =IFERROR(Calc_BankMonth!I13/Calc_BankMonth!H13-1,0) -> 0.0069035569 | J13: =IFERROR(Calc_BankMonth!J13/Calc_BankMonth!I13-1,0) -> 0.01385321 | ... AK13: =IFERROR(Calc_BankMonth!AK13/Calc_BankMonth!AJ13-1,0) -> 0.0035876399 | AM13: =AVERAGE(C13:AK13) -> 0.0069497976 | AN13: =MAX(C13:AK13) -> 0.016332321 | AO13: =MIN(C13:AK13) -> -0.0039143882 | AP13: =MATCH(AN13,C13:AK13,0)+1 -> 5
A14: Banca Friulana | C14: =IFERROR(Calc_BankMonth!C14/Calc_BankMonth!B14-1,0) -> 0.0062790887 | D14: =IFERROR(Calc_BankMonth!D14/Calc_BankMonth!C14-1,0) -> 0.0063321799 | E14: =IFERROR(Calc_BankMonth!E14/Calc_BankMonth!D14-1,0) -> 0.013404165 | F14: =IFERROR(Calc_BankMonth!F14/Calc_BankMonth!E14-1,0) -> 0.0047331724 | G14: =IFERROR(Calc_BankMonth!G14/Calc_BankMonth!F14-1,0) -> 0.0080484483 | H14: =IFERROR(Calc_BankMonth!H14/Calc_BankMonth!G14-1,0) -> 0.0043159282 | I14: =IFERROR(Calc_BankMonth!I14/Calc_BankMonth!H14-1,0) -> 0.011063115 | J14: =IFERROR(Calc_BankMonth!J14/Calc_BankMonth!I14-1,0) -> 0.0089515965 | ... AK14: =IFERROR(Calc_BankMonth!AK14/Calc_BankMonth!AJ14-1,0) -> -0.00082943302 | AM14: =AVERAGE(C14:AK14) -> 0.006915397 | AN14: =MAX(C14:AK14) -> 0.015009512 | AO14: =MIN(C14:AK14) -> -0.0012833237 | AP14: =MATCH(AN14,C14:AK14,0)+1 -> 13
... A22: Banca Città | C22: =IFERROR(Calc_BankMonth!C22/Calc_BankMonth!B22-1,0) -> 0.0063304064 | D22: =IFERROR(Calc_BankMonth!D22/Calc_BankMonth!C22-1,0) -> 0.004725743 | E22: =IFERROR(Calc_BankMonth!E22/Calc_BankMonth!D22-1,0) -> 0.010040122 | F22: =IFERROR(Calc_BankMonth!F22/Calc_BankMonth!E22-1,0) -> 0.0069178472 | G22: =IFERROR(Calc_BankMonth!G22/Calc_BankMonth!F22-1,0) -> 0.0098261989 | H22: =IFERROR(Calc_BankMonth!H22/Calc_BankMonth!G22-1,0) -> 0.0072383747 | I22: =IFERROR(Calc_BankMonth!I22/Calc_BankMonth!H22-1,0) -> 0.0065781075 | J22: =IFERROR(Calc_BankMonth!J22/Calc_BankMonth!I22-1,0) -> 0.0065537693 | ... AK22: =IFERROR(Calc_BankMonth!AK22/Calc_BankMonth!AJ22-1,0) -> 0.0063263843 | AM22: =AVERAGE(C22:AK22) -> 0.0069397635 | AN22: =MAX(C22:AK22) -> 0.014531063 | AO22: =MIN(C22:AK22) -> 0.002426831 | AP22: =MATCH(AN22,C22:AK22,0)+1 -> 14

Sheet Calc_Scenario
B2: =Calc_BankMonth!B2 -> 1 | C2: =Calc_BankMonth!C2 -> 2 | D2: =Calc_BankMonth!D2 -> 3 | E2: =Calc_BankMonth!E2 -> 4 | F2: =Calc_BankMonth!F2 -> 5 | G2: =Calc_BankMonth!G2 -> 6 | H2: =Calc_BankMonth!H2 -> 7 | I2: =Calc_BankMonth!I2 -> 8 | ... AK2: =Calc_BankMonth!AK2 -> 36 | AL2: Mese sel.
A3: Banca Alpi | B3: =Calc_BankMonth!B3*(1+Control!$B$25)^B$2*HLOOKUP(B$2,FX!$B$40:$AK$43,2,FALSE) -> 6301.7163 | C3: =Calc_BankMonth!C3*(1+Control!$B$25)^C$2*HLOOKUP(C$2,FX!$B$40:$AK$43,2,FALSE) -> 6379.8973 | D3: =Calc_BankMonth!D3*(1+Control!$B$25)^D$2*HLOOKUP(D$2,FX!$B$40:$AK$43,2,FALSE) -> 6551.8356 | E3: =Calc_BankMonth!E3*(1+Control!$B$25)^E$2*HLOOKUP(E$2,FX!$B$40:$AK$43,2,FALSE) -> 6650.957 | F3: =Calc_BankMonth!F3*(1+Control!$B$25)^F$2*HLOOKUP(F$2,FX!$B$40:$AK$43,2,FALSE) -> 6852.4303 | G3: =Calc_BankMonth!G3*(1+Control!$B$25)^G$2*HLOOKUP(G$2,FX!$B$40:$AK$43,2,FALSE) -> 6861.4165 | H3: =Calc_BankMonth!H3*(1+Control!$B$25)^H$2*HLOOKUP(H$2,FX!$B$40:$AK$43,2,FALSE) -> 6953.3574 | I3: =Calc_BankMonth!I3*(1+Control!$B$25)^I$2*HLOOKUP(I$2,FX!$B$40:$AK$43,2,FALSE) -> 6987.1087 | ... AK3: =Calc_BankMonth!AK3*(1+Control!$B$25)^AK$2*HLOOKUP(AK$2,FX!$B$40:$AK$43,2,FALSE) -> 9008.1373 | AL3: {=INDEX(B3:AK3,Control!$B$3)} -> 7240.7755
A4: Banca Adriatica | B4: =Calc_BankMonth!B4*(1+Control!$B$25)^B$2*HLOOKUP(B$2,FX!$B$40:$AK$43,2,FALSE) -> 7403.2651 | C4: =Calc_BankMonth!C4*(1+Control!$B$25)^C$2*HLOOKUP(C$2,FX!$B$40:$AK$43,2,FALSE) -> 7511.5831 | D4: =Calc_BankMonth!D4*(1+Control!$B$25)^D$2*HLOOKUP(D$2,FX!$B$40:$AK$43,2,FALSE) -> 7711.596 | E4: =Calc_BankMonth!E4*(1+Control!$B$25)^E$2*HLOOKUP(E$2,FX!$B$40:$AK$43,2,FALSE) -> 7851.7909 | F4: =Calc_BankMonth!F4*(1+Control!$B$25)^F$2*HLOOKUP(F$2,FX!$B$40:$AK$43,2,FALSE) -> 7952.2613 | G4: =Calc_BankMonth!G4*(1+Control!$B$25)^G$2*HLOOKUP(G$2,FX!$B$40:$AK$43,2,FALSE) -> 8037.0599 | H4: =Calc_BankMonth!H4*(1+Control!$B$25)^H$2*HLOOKUP(H$2,FX!$B$40:$AK$43,2,FALSE) -> 7986.4461 | I4: =Calc_BankMonth!I4*(1+Control!$B$25)^I$2*HLOOKUP(I$2,FX!$B$40:$AK$43,2,FALSE) -> 8232.673 | ... AK4: =Calc_BankMonth!AK4*(1+Control!$B$25)^AK$2*HLOOKUP(AK$2,FX!$B$40:$AK$43,2,FALSE) -> 10619.114 | AL4: {=INDEX(B4:AK4,Control!$B$3)} -> 8466.4235
A5: Banca Tirrena | B5: =Calc_BankMonth!B5*(1+Control!$B$25)^B$2*HLOOKUP(B$2,FX!$B$40:$AK$43,2,FALSE) -> 8497.7079 | C5: =Calc_BankMonth!C5*(1+Control!$B$25)^C$2*HLOOKUP(C$2,FX!$B$40:$AK$43,2,FALSE) -> 8703.9982 | D5: =Calc_BankMonth!D5*(1+Control!$B$25)^D$2*HLOOKUP(D$2,FX!$B$40:$AK$43,2,FALSE) -> 8823.5825 | E5: =Calc_BankMonth!E5*(1+Control!$B$25)^E$2*HLOOKUP(E$2,FX!$B$40:$AK$43,2,FALSE) -> 8946.8067 | F5: =Calc_BankMonth!F5*(1+Control!$B$25)^F$2*HLOOKUP(F$2,FX!$B$40:$AK$43,2,FALSE) -> 9138.0372 | G5: =Calc_BankMonth!G5*(1+Control!$B$25)^G$2*HLOOKUP(G$2,FX!$B$40:$AK$43,2,FALSE) -> 9211.8201 | H5: =Calc_BankMonth!H5*(1+Control!$B$25)^H$2*HLOOKUP(H$2,FX!$B$40:$AK$43,2,FALSE) -> 9321.6424 | I5: =Calc_BankMonth!I5*(1+Control!$B$25)^I$2*HLOOKUP(I$2,FX!$B$40:$AK$43,2,FALSE) -> 9390.238 | ... AK5: =Calc_BankMonth!AK5*(1+Control!$B$25)^AK$2*HLOOKUP(AK$2,FX!$B$40:$AK$43,2,FALSE) -> 12147.905 | AL5: {=INDEX(B5:AK5,Control!$B$3)} -> 9672.2602
A6: Banca Padana | B6: =Calc_BankMonth!B6*(1+Control!$B$25)^B$2*HLOOKUP(B$2,FX!$B$40:$AK$43,2,FALSE) -> 9571.3627 | C6: =Calc_BankMonth!C6*(1+Control!$B$25)^C$2*HLOOKUP(C$2,FX!$B$40:$AK$43,2,FALSE) -> 9761.6735 | D6: =Calc_BankMonth!D6*(1+Control!$B$25)^D$2*HLOOKUP(D$2,FX!$B$40:$AK$43,2,FALSE) -> 9902.927 | E6: =Calc_BankMonth!E6*(1+Control!$B$25)^E$2*HLOOKUP(E$2,FX!$B$40:$AK$43,2,FALSE) -> 10150.692 | F6: =Calc_BankMonth!F6*(1+Control!$B$25)^F$2*HLOOKUP(F$2,FX!$B$40:$AK$43,2,FALSE) -> 10230.953 | G6: =Calc_BankMonth!G6*(1+Control!$B$25)^G$2*HLOOKUP(G$2,FX!$B$40:$AK$43,2,FALSE) -> 10414.956 | H6: =Calc_BankMonth!H6*(1+Control!$B$25)^H$2*HLOOKUP(H$2,FX!$B$40:$AK$43,2,FALSE) -> 10463.308 | I6: =Calc_BankMonth!I6*(1+Control!$B$25)^I$2*HLOOKUP(I$2,FX!$B$40:$AK$43,2,FALSE) -> 10536.01 | ... AK6: =Calc_BankMonth!AK6*(1+Control!$B$25)^AK$2*HLOOKUP(AK$2,FX!$B$40:$AK$43,2,FALSE) -> 13599.254 | AL6: {=INDEX(B6:AK6,Control!$B$3)} -> 10948.931
A7: Banca Etrusca | B7: =Calc_BankMonth!B7*(1+Control!$B$25)^B$2*HLOOKUP(B$2,FX!$B$40:$AK$43,2,FALSE) -> 10575.123 | C7: =Calc_BankMonth!C7*(1+Control!$B$25)^C$2*HLOOKUP(C$2,FX!$B$40:$AK$43,2,FALSE) -> 10848.375 | D7: =Calc_BankMonth!D7*(1+Control!$B$25)^D$2*HLOOKUP(D$2,FX!$B$40:$AK$43,2,FALSE) -> 11067.984 | E7: =Calc_BankMonth!E7*(1+Control!$B$25)^E$2*HLOOKUP(E$2,FX!$B$40:$AK$43,2,FALSE) -> 11169.096 | F7: =Calc_BankMonth!F7*(1+Control!$B$25)^F$2*HLOOKUP(F$2,FX!$B$40:$AK$43,2,FALSE) -> 11297.855 | G7: =Calc_BankMonth!G7*(1+Control!$B$25)^G$2*HLOOKUP(G$2,FX!$B$40:$AK$43,2,FALSE) -> 11515.52 | H7: =Calc_BankMonth!H7*(1+Control!$B$25)^H$2*HLOOKUP(H$2,FX!$B$40:$AK$43,2,FALSE) -> 11692.589 | I7: =Calc_BankMonth!I7*(1+Control!$B$25)^I$2*HLOOKUP(I$2,FX!$B$40:$AK$43,2,FALSE) -> 11797.817 | ... AK7: =Calc_BankMonth!AK7*(1+Control!$B$25)^AK$2*HLOOKUP(AK$2,FX!$B$40:$AK$43,2,FALSE) -> 15226.715 | AL7: {=INDEX(B7:AK7,Control!$B$3)} -> 12162.515
A8: Banca Lariana | B8: =Calc_BankMonth!B8*(1+Control!$B$25)^B$2*HLOOKUP(B$2,FX!$B$40:$AK$43,2,FALSE) -> 11794.294 | C8: =Calc_BankMonth!C8*(1+Control!$B$25)^C$2*HLOOKUP(C$2,FX!$B$40:$AK$43,2,FALSE) -> 11911.084 | D8: =Calc_BankMonth!D8*(1+Control!$B$25)^D$2*HLOOKUP(D$2,FX!$B$40:$AK$43,2,FALSE) -> 12111.444 | E8: =Calc_BankMonth!E8*(1+Control!$B$25)^E$2*HLOOKUP(E$2,FX!$B$40:$AK$43,2,FALSE) -> 12359.577 | F8: =Calc_BankMonth!F8*(1+Control!$B$25)^F$2*HLOOKUP(F$2,FX!$B$40:$AK$43,2,FALSE) -> 12531.488 | G8: =Calc_BankMonth!G8*(1+Control!$B$25)^G$2*HLOOKUP(G$2,FX!$B$40:$AK$43,2,FALSE) -> 12665.99 | H8: =Calc_BankMonth!H8*(1+Control!$B$25)^H$2*HLOOKUP(H$2,FX!$B$40:$AK$43,2,FALSE) -> 12856.325 | I8: =Calc_BankMonth!I8*(1+Control!$B$25)^I$2*HLOOKUP(I$2,FX!$B$40:$AK$43,2,FALSE) -> 12953.046 | ... AK8: =Calc_BankMonth!AK8*(1+Control!$B$25)^AK$2*HLOOKUP(AK$2,FX!$B$40:$AK$43,2,FALSE) -> 16778.75 | AL8: {=INDEX(B8:AK8,Control!$B$3)} -> 13398.235
A9: Banca Sabina | B9: =Calc_BankMonth!B9*(1+Control!$B$25)^B$2*HLOOKUP(B$2,FX!$B$40:$AK$43,2,FALSE) -> 12762.312 | C9: =Calc_BankMonth!C9*(1+Control!$B$25)^C$2*HLOOKUP(C$2,FX!$B$40:$AK$43,2,FALSE) -> 13097.394 | D9: =Calc_BankMonth!D9*(1+Control!$B$25)^D$2*HLOOKUP(D$2,FX!$B$40:$AK$43,2,FALSE) -> 13353.998 | E9: =Calc_BankMonth!E9*(1+Control!$B$25)^E$2*HLOOKUP(E$2,FX!$B$40:$AK$43,2,FALSE) -> 13567.93 | F9: =Calc_BankMonth!F9*(1+Control!$B$25)^F$2*HLOOKUP(F$2,FX!$B$40:$AK$43,2,FALSE) -> 13638.563 | G9: =Calc_BankMonth!G9*(1+Control!$B$25)^G$2*HLOOKUP(G$2,FX!$B$40:$AK$43,2,FALSE) -> 13936.918 | H9: =Calc_BankMonth!H9*(1+Control!$B$25)^H$2*HLOOKUP(H$2,FX!$B$40:$AK$43,2,FALSE) -> 14105.902 | I9: =Calc_BankMonth!I9*(1+Control!$B$25)^I$2*HLOOKUP(I$2,FX!$B$40:$AK$43,2,FALSE) -> 14208.067 | ... AK9: =Calc_BankMonth!AK9*(1+Control!$B$25)^AK$2*HLOOKUP(AK$2,FX!$B$40:$AK$43,2,FALSE) -> 18267.812 | AL9: {=INDEX(B9:AK9,Control!$B$3)} -> 14720.726
A10: Banca Irpina | B10: =Calc_BankMonth!B10*(1+Control!$B$25)^B$2*HLOOKUP(B$2,FX!$B$40:$AK$43,2,FALSE) -> 13986.891 | C10: =Calc_BankMonth!C10*(1+Control!$B$25)^C$2*HLOOKUP(C$2,FX!$B$40:$AK$43,2,FALSE) -> 14140.717 | D10: =Calc_BankMonth!D10*(1+Control!$B$25)^D$2*HLOOKUP(D$2,FX!$B$40:$AK$43,2,FALSE) -> 14429.559 | E10: =Calc_BankMonth!E10*(1+Control!$B$25)^E$2*HLOOKUP(E$2,FX!$B$40:$AK$43,2,FALSE) -> 14620.881 | F10: =Calc_BankMonth!F10*(1+Control!$B$25)^F$2*HLOOKUP(F$2,FX!$B$40:$AK$43,2,FALSE) -> 15006.437 | G10: =Calc_BankMonth!G10*(1+Control!$B$25)^G$2*HLOOKUP(G$2,FX!$B$40:$AK$43,2,FALSE) -> 15106.82 | H10: =Calc_BankMonth!H10*(1+Control!$B$25)^H$2*HLOOKUP(H$2,FX!$B$40:$AK$43,2,FALSE) -> 15225.386 | I10: =Calc_BankMonth!I10*(1+Control!$B$25)^I$2*HLOOKUP(I$2,FX!$B$40:$AK$43,2,FALSE) -> 15435.608 | ... AK10: =Calc_BankMonth!AK10*(1+Control!$B$25)^AK$2*HLOOKUP(AK$2,FX!$B$40:$AK$43,2,FALSE) -> 19821.626 | AL10: {=INDEX(B10:AK10,Control!$B$3)} -> 15914.72
A11: Banca Sannita | B11: =Calc_BankMonth!B11*(1+Control!$B$25)^B$2*HLOOKUP(B$2,FX!$B$40:$AK$43,2,FALSE) -> 14981.955 | C11: =Calc_BankMonth!C11*(1+Control!$B$25)^C$2*HLOOKUP(C$2,FX!$B$40:$AK$43,2,FALSE) -> 15321.565 | D11: =Calc_BankMonth!D11*(1+Control!$B$25)^D$2*HLOOKUP(D$2,FX!$B$40:$AK$43,2,FALSE) -> 15501.662 | E11: =Calc_BankMonth!E11*(1+Control!$B$25)^E$2*HLOOKUP(E$2,FX!$B$40:$AK$43,2,FALSE) -> 15786.95 | F11: =Calc_BankMonth!F11*(1+Control!$B$25)^F$2*HLOOKUP(F$2,FX!$B$40:$AK$43,2,FALSE) -> 16075.095 | G11: =Calc_BankMonth!G11*(1+Control!$B$25)^G$2*HLOOKUP(G$2,FX!$B$40:$AK$43,2,FALSE) -> 16244.151 | H11: =Calc_BankMonth!H11*(1+Control!$B$25)^H$2*HLOOKUP(H$2,FX!$B$40:$AK$43,2,FALSE) -> 16409.307 | I11: =Calc_BankMonth!I11*(1+Control!$B$25)^I$2*HLOOKUP(I$2,FX!$B$40:$AK$43,2,FALSE) -> 16513.184 | ... AK11: =Calc_BankMonth!AK11*(1+Control!$B$25)^AK$2*HLOOKUP(AK$2,FX!$B$40:$AK$43,2,FALSE) -> 21324.801 | AL11: {=INDEX(B11:AK11,Control!$B$3)} -> 17143.578
A12: Banca Ligure | B12: =Calc_BankMonth!B12*(1+Control!$B$25)^B$2*HLOOKUP(B$2,FX!$B$40:$AK$43,2,FALSE) -> 16092.837 | C12: =Calc_BankMonth!C12*(1+Control!$B$25)^C$2*HLOOKUP(C$2,FX!$B$40:$AK$43,2,FALSE) -> 16450.144 | D12: =Calc_BankMonth!D12*(1+Control!$B$25)^D$2*HLOOKUP(D$2,FX!$B$40:$AK$43,2,FALSE) -> 16662.612 | E12: =Calc_BankMonth!E12*(1+Control!$B$25)^E$2*HLOOKUP(E$2,FX!$B$40:$AK$43,2,FALSE) -> 16923.596 | F12: =Calc_BankMonth!F12*(1+Control!$B$25)^F$2*HLOOKUP(F$2,FX!$B$40:$AK$43,2,FALSE) -> 17222.783 | G12: =Calc_BankMonth!G12*(1+Control!$B$25)^G$2*HLOOKUP(G$2,FX!$B$40:$AK$43,2,FALSE) -> 17427.965 | H12: =Calc_BankMonth!H12*(1+Control!$B$25)^H$2*HLOOKUP(H$2,FX!$B$40:$AK$43,2,FALSE) -> 17661.546 | I12: =Calc_BankMonth!I12*(1+Control!$B$25)^I$2*HLOOKUP(I$2,FX!$B$40:$AK$43,2,FALSE) -> 17869.443 | ... AK12: =Calc_BankMonth!AK12*(1+Control!$B$25)^AK$2*HLOOKUP(AK$2,FX!$B$40:$AK$43,2,FALSE) -> 23021.402 | AL12: {=INDEX(B12:AK12,Control!$B$3)} -> 18425.672
A13: Banca Veneta | B13: =Calc_BankMonth!B13*(1+Control!$B$25)^B$2*HLOOKUP(B$2,FX!$B$40:$AK$43,2,FALSE) -> 17211.038 | C13: =Calc_BankMonth!C13*(1+Control!$B$25)^C$2*HLOOKUP(C$2,FX!$B$40:$AK$43,2,FALSE) -> 17435.737 | D13: =Calc_BankMonth!D13*(1+Control!$B$25)^D$2*HLOOKUP(D$2,FX!$B$40:$AK$43,2,FALSE) -> 17724.554 | E13: =Calc_BankMonth!E13*(1+Control!$B$25)^E$2*HLOOKUP(E$2,FX!$B$40:$AK$43,2,FALSE) -> 17975.892 | F13: =Calc_BankMonth!F13*(1+Control!$B$25)^F$2*HLOOKUP(F$2,FX!$B$40:$AK$43,2,FALSE) -> 18401.095 | G13: =Calc_BankMonth!G13*(1+Control!$B$25)^G$2*HLOOKUP(G$2,FX!$B$40:$AK$43,2,FALSE) -> 18555.69 | H13: =Calc_BankMonth!H13*(1+Control!$B$25)^H$2*HLOOKUP(H$2,FX!$B$40:$AK$43,2,FALSE) -> 18780.032 | I13: =Calc_BankMonth!I13*(1+Control!$B$25)^I$2*HLOOKUP(I$2,FX!$B$40:$AK$43,2,FALSE) -> 18968.49 | ... AK13: =Calc_BankMonth!AK13*(1+Control!$B$25)^AK$2*HLOOKUP(AK$2,FX!$B$40:$AK$43,2,FALSE) -> 24516.156 | AL13: {=INDEX(B13:AK13,Control!$B$3)} -> 19550.05
A14: Banca Friulana | B14: =Calc_BankMonth!B14*(1+Control!$B$25)^B$2*HLOOKUP(B$2,FX!$B$40:$AK$43,2,FALSE) -> 18276.208 | C14: =Calc_BankMonth!C14*(1+Control!$B$25)^C$2*HLOOKUP(C$2,FX!$B$40:$AK$43,2,FALSE) -> 18572.243 | D14: =Calc_BankMonth!D14*(1+Control!$B$25)^D$2*HLOOKUP(D$2,FX!$B$40:$AK$43,2,FALSE) -> 18860.752 | E14: =Calc_BankMonth!E14*(1+Control!$B$25)^E$2*HLOOKUP(E$2,FX!$B$40:$AK$43,2,FALSE) -> 19271.428 | F14: =Calc_BankMonth!F14*(1+Control!$B$25)^F$2*HLOOKUP(F$2,FX!$B$40:$AK$43,2,FALSE) -> 19502.134 | G14: =Calc_BankMonth!G14*(1+Control!$B$25)^G$2*HLOOKUP(G$2,FX!$B$40:$AK$43,2,FALSE) -> 19774.835 | H14: =Calc_BankMonth!H14*(1+Control!$B$25)^H$2*HLOOKUP(H$2,FX!$B$40:$AK$43,2,FALSE) -> 19949.424 | I14: =Calc_BankMonth!I14*(1+Control!$B$25)^I$2*HLOOKUP(I$2,FX!$B$40:$AK$43,2,FALSE) -> 20232.856 | ... AK14: =Calc_BankMonth!AK14*(1+Control!$B$25)^AK$2*HLOOKUP(AK$2,FX!$B$40:$AK$43,2,FALSE) -> 26001.067 | AL14: {=INDEX(B14:AK14,Control!$B$3)} -> 20964.182
... A22: Banca Città | B22: =Calc_BankMonth!B22*(1+Control!$B$25)^B$2*HLOOKUP(B$2,FX!$B$40:$AK$43,2,FALSE) -> 27007.78 | C22: =Calc_BankMonth!C22*(1+Control!$B$25)^C$2*HLOOKUP(C$2,FX!$B$40:$AK$43,2,FALSE) -> 27446.647 | D22: =Calc_BankMonth!D22*(1+Control!$B$25)^D$2*HLOOKUP(D$2,FX!$B$40:$AK$43,2,FALSE) -> 27828.521 | E22: =Calc_BankMonth!E22*(1+Control!$B$25)^E$2*HLOOKUP(E$2,FX!$B$40:$AK$43,2,FALSE) -> 28340.073 | F22: =Calc_BankMonth!F22*(1+Control!$B$25)^F$2*HLOOKUP(F$2,FX!$B$40:$AK$43,2,FALSE) -> 28741.702 | G22: =Calc_BankMonth!G22*(1+Control!$B$25)^G$2*HLOOKUP(G$2,FX!$B$40:$AK$43,2,FALSE) -> 29194.999 | H22: =Calc_BankMonth!H22*(1+Control!$B$25)^H$2*HLOOKUP(H$2,FX!$B$40:$AK$43,2,FALSE) -> 29538.46 | I22: =Calc_BankMonth!I22*(1+Control!$B$25)^I$2*HLOOKUP(I$2,FX!$B$40:$AK$43,2,FALSE) -> 29825.236 | ... AK22: =Calc_BankMonth!AK22*(1+Control!$B$25)^AK$2*HLOOKUP(AK$2,FX!$B$40:$AK$43,2,FALSE) -> 38464.668 | AL22: {=INDEX(B22:AK22,Control!$B$3)} -> 30649.392

Sheet Calc_Stats
A1: k | B1: Volumi | C1: Banca | D1: Regione | E1: Quota | F1: Var. %
A2: 1 | B2: =LARGE(Calc_Bank!$C$2:$C$21,A2) -> 27692.4 | C2: =INDEX(Calc_Bank!$A$2:$A$21,MATCH(B2,Calc_Bank!$C$2:$C$21,0)) -> Banca Città | D2: =_xlfn.XLOOKUP(C2,Calc_Bank!$A$2:$A$21,Calc_Bank!$B$2:$B$21) -> Centro | E2: =B2/SUM(Calc_Bank!$C$2:$C$21) -> 0.080604214 | F2: =_xlfn.XLOOKUP(C2,Calc_Bank!$A$2:$A$21,Calc_Bank!$H$2:$H$21) -> 0.004621803 | H2: Mediana | I2: =MEDIAN(Calc_Bank!C2:C21) -> 17155.95
A3: 2 | B3: =LARGE(Calc_Bank!$C$2:$C$21,A3) -> 26741.1 | C3: =INDEX(Calc_Bank!$A$2:$A$21,MATCH(B3,Calc_Bank!$C$2:$C$21,0)) -> Banca Romagnola | D3: =_xlfn.XLOOKUP(C3,Calc_Bank!$A$2:$A$21,Calc_Bank!$B$2:$B$21) -> Nord-Est | E3: =B3/SUM(Calc_Bank!$C$2:$C$21) -> 0.077835267 | F3: =_xlfn.XLOOKUP(C3,Calc_Bank!$A$2:$A$21,Calc_Bank!$H$2:$H$21) -> 0.0081660352 | H3: Dev. st. | I3: =_xlfn.STDEV.S(Calc_Bank!C2:C21) -> 6632.0285
A4: 3 | B4: =LARGE(Calc_Bank!$C$2:$C$21,A4) -> 25627 | C4: =INDEX(Calc_Bank!$A$2:$A$21,MATCH(B4,Calc_Bank!$C$2:$C$21,0)) -> Banca Sarda | D4: =_xlfn.XLOOKUP(C4,Calc_Bank!$A$2:$A$21,Calc_Bank!$B$2:$B$21) -> Isole | E4: =B4/SUM(Calc_Bank!$C$2:$C$21) -> 0.074592459 | F4: =_xlfn.XLOOKUP(C4,Calc_Bank!$A$2:$A$21,Calc_Bank!$H$2:$H$21) -> 0.0087384373 | H4: 90° percentile | I4: =_xlfn.PERCENTILE.INC(Calc_Bank!C2:C21,0.9) -> 25738.41
A5: 4 | B5: =LARGE(Calc_Bank!$C$2:$C$21,A5) -> 24517.8 | C5: =INDEX(Calc_Bank!$A$2:$A$21,MATCH(B5,Calc_Bank!$C$2:$C$21,0)) -> Banca Sicula | D5: =_xlfn.XLOOKUP(C5,Calc_Bank!$A$2:$A$21,Calc_Bank!$B$2:$B$21) -> Isole | E5: =B5/SUM(Calc_Bank!$C$2:$C$21) -> 0.071363912 | F5: =_xlfn.XLOOKUP(C5,Calc_Bank!$A$2:$A$21,Calc_Bank!$H$2:$H$21) -> 0.013852821 | H5: 1° quartile | I5: =_xlfn.QUARTILE.INC(Calc_Bank!C2:C21,1) -> 11826.475
A6: 5 | B6: =LARGE(Calc_Bank!$C$2:$C$21,A6) -> 23396.2 | C6: =INDEX(Calc_Bank!$A$2:$A$21,MATCH(B6,Calc_Bank!$C$2:$C$21,0)) -> Banca Calabra | D6: =_xlfn.XLOOKUP(C6,Calc_Bank!$A$2:$A$21,Calc_Bank!$B$2:$B$21) -> Sud | E6: =B6/SUM(Calc_Bank!$C$2:$C$21) -> 0.068099273 | F6: =_xlfn.XLOOKUP(C6,Calc_Bank!$A$2:$A$21,Calc_Bank!$H$2:$H$21) -> 0.011447643 | H6: Media | I6: =AVERAGE(Calc_Bank!C2:C21) -> 17178.01
A7: 6 | B7: =LARGE(Calc_Bank!$C$2:$C$21,A7) -> 22158.4 | C7: =INDEX(Calc_Bank!$A$2:$A$21,MATCH(B7,Calc_Bank!$C$2:$C$21,0)) -> Banca Lucana | D7: =_xlfn.XLOOKUP(C7,Calc_Bank!$A$2:$A$21,Calc_Bank!$B$2:$B$21) -> Sud | E7: =B7/SUM(Calc_Bank!$C$2:$C$21) -> 0.064496411 | F7: =_xlfn.XLOOKUP(C7,Calc_Bank!$A$2:$A$21,Calc_Bank!$H$2:$H$21) -> 0.0055362945 | H7: Campo | I7: =MAX(Calc_Bank!C2:C21)-MIN(Calc_Bank!C2:C21) -> 21150.2
A8: 7 | B8: =LARGE(Calc_Bank!$C$2:$C$21,A8) -> 21147.3 | C8: =INDEX(Calc_Bank!$A$2:$A$21,MATCH(B8,Calc_Bank!$C$2:$C$21,0)) -> Banca Marchigiana | D8: =_xlfn.XLOOKUP(C8,Calc_Bank!$A$2:$A$21,Calc_Bank!$B$2:$B$21) -> Centro | E8: =B8/SUM(Calc_Bank!$C$2:$C$21) -> 0.061553405 | F8: =_xlfn.XLOOKUP(C8,Calc_Bank!$A$2:$A$21,Calc_Bank!$H$2:$H$21) -> 0.0083251084 | H8: Banche in crescita | I8: =COUNTIF(Calc_Bank!H2:H21,">0") -> 17
A9: 8 | B9: =LARGE(Calc_Bank!$C$2:$C$21,A9) -> 19938.9 | C9: =INDEX(Calc_Bank!$A$2:$A$21,MATCH(B9,Calc_Bank!$C$2:$C$21,0)) -> Banca Umbra | D9: =_xlfn.XLOOKUP(C9,Calc_Bank!$A$2:$A$21,Calc_Bank!$B$2:$B$21) -> Centro | E9: =B9/SUM(Calc_Bank!$C$2:$C$21) -> 0.058036117 | F9: =_xlfn.XLOOKUP(C9,Calc_Bank!$A$2:$A$21,Calc_Bank!$H$2:$H$21) -> 0.01149023 | H9: Concentrazione | I9: =SUMPRODUCT(Calc_Bank!K2:K21,Calc_Bank!K2:K21) -> 0.057080121
A10: 9 | B10: =LARGE(Calc_Bank!$C$2:$C$21,A10) -> 18941.6 | C10: =INDEX(Calc_Bank!$A$2:$A$21,MATCH(B10,Calc_Bank!$C$2:$C$21,0)) -> Banca Friulana | D10: =_xlfn.XLOOKUP(C10,Calc_Bank!$A$2:$A$21,Calc_Bank!$B$2:$B$21) -> Nord-Est | E10: =B10/SUM(Calc_Bank!$C$2:$C$21) -> 0.055133278 | F10: =_xlfn.XLOOKUP(C10,Calc_Bank!$A$2:$A$21,Calc_Bank!$H$2:$H$21) -> 0.015009512 | H10: Radice | I10: =SQRT(I9) -> 0.23891446
A11: 10 | B11: =LARGE(Calc_Bank!$C$2:$C$21,A11) -> 17663.9 | C11: =INDEX(Calc_Bank!$A$2:$A$21,MATCH(B11,Calc_Bank!$C$2:$C$21,0)) -> Banca Veneta | D11: =_xlfn.XLOOKUP(C11,Calc_Bank!$A$2:$A$21,Calc_Bank!$B$2:$B$21) -> Nord-Est | E11: =B11/SUM(Calc_Bank!$C$2:$C$21) -> 0.051414279 | F11: =_xlfn.XLOOKUP(C11,Calc_Bank!$A$2:$A$21,Calc_Bank!$H$2:$H$21) -> 0.0030493691 | H11: Media arrot. | I11: =ROUNDDOWN(I6,-1) -> 17170
H12: Percent. rango sel. | I12: =PERCENTRANK(Calc_Bank!C2:C21,_xlfn.XLOOKUP(Control!B2,Calc_Bank!A2:A21,Calc_Bank!C2:C21)) -> 0.105
H13: Media prodotti | I13: =AVERAGE(Calc_Product!B2:B9) -> 1092.3875
A14: 1 | B14: =SMALL(Calc_Bank!$C$2:$C$21,A14) -> 6542.2 | C14: =INDEX(Calc_Bank!$A$2:$A$21,MATCH(B14,Calc_Bank!$C$2:$C$21,0)) -> Banca Alpi
A15: 2 | B15: =SMALL(Calc_Bank!$C$2:$C$21,A15) -> 7649.6 | C15: =INDEX(Calc_Bank!$A$2:$A$21,MATCH(B15,Calc_Bank!$C$2:$C$21,0)) -> Banca Adriatica
A16: 3 | B16: =SMALL(Calc_Bank!$C$2:$C$21,A16) -> 8739.1 | C16: =INDEX(Calc_Bank!$A$2:$A$21,MATCH(B16,Calc_Bank!$C$2:$C$21,0)) -> Banca Tirrena
A17: 4 | B17: =SMALL(Calc_Bank!$C$2:$C$21,A17) -> 9892.6 | C17: =INDEX(Calc_Bank!$A$2:$A$21,MATCH(B17,Calc_Bank!$C$2:$C$21,0)) -> Banca Padana
A18: 5 | B18: =SMALL(Calc_Bank!$C$2:$C$21,A18) -> 10989.1 | C18: =INDEX(Calc_Bank!$A$2:$A$21,MATCH(B18,Calc_Bank!$C$2:$C$21,0)) -> Banca Etrusca

Sheet Calc_Text
A1: Banca | B1: Sigla | C1: Nome | D1: Estratto | E1: Responsabile | F1: Codice | G1: Breve | H1: Email | I1: Proprio | J1: Stelle | K1: Volumi testo | L1: Elenco | M1: Numero codice | N1: Lunghezza | O1: Accento | P1: Etichetta
A2: =Banks!A2 -> Banca Alpi | B2: =UPPER(LEFT(A2,5)) -> BANCA | C2: =RIGHT(A2,LEN(A2)-FIND(" ",A2)) -> Alpi | D2: =MID(A2,7,3) -> Alp | E2: =TRIM(Banks!D2) -> Rossi | F2: =CONCATENATE(Banks!B2,"-",LEFT(Banks!C2,3)) -> B101-Nor | G2: =SUBSTITUTE(A2,"Banca","Bk") -> Bk Alpi | H2: =LOWER(C2)&"@esempio.it" -> alpi@esempio.it | I2: =PROPER(LOWER(A2)) -> Banca Alpi | J2: =REPT("*",Calc_Bank!L2) -> ******************** | K2: =TEXT(Calc_Bank!C2,"#.##0,0") -> 6.542,2 | L2: =_xlfn.TEXTJOIN(", ",TRUE,A2,B2,Calc_Bank!R2) -> Banca Alpi, BANCA, Grande | M2: =VALUE(RIGHT(Banks!B2,3)) -> 101 | N2: =LEN(E2) -> 5 | O2: =IF(ISNUMBER(FIND("à",A2)),"accento","-") -> - | P2: =A2&" ("&Calc_Bank!T2&") "&TEXT(Calc_Bank!K2,"0,0%") -> Banca Alpi (NO) 1,9%
A3: =Banks!A3 -> Banca Adriatica | B3: =UPPER(LEFT(A3,5)) -> BANCA | C3: =RIGHT(A3,LEN(A3)-FIND(" ",A3)) -> Adriatica | D3: =MID(A3,7,3) -> Adr | E3: =TRIM(Banks!D3) -> Bianchi Anna | F3: =CONCATENATE(Banks!B3,"-",LEFT(Banks!C3,3)) -> B102-Nor | G3: =SUBSTITUTE(A3,"Banca","Bk") -> Bk Adriatica | H3: =LOWER(C3)&"@esempio.it" -> adriatica@esempio.it | I3: =PROPER(LOWER(A3)) -> Banca Adriatica | J3: =REPT("*",Calc_Bank!L3) -> ******************* | K3: =TEXT(Calc_Bank!C3,"#.##0,0") -> 7.649,6 | L3: =_xlfn.TEXTJOIN(", ",TRUE,A3,B3,Calc_Bank!R3) -> Banca Adriatica, BANCA, Media | M3: =VALUE(RIGHT(Banks!B3,3)) -> 102 | N3: =LEN(E3) -> 12 | O3: =IF(ISNUMBER(FIND("à",A3)),"accento","-") -> - | P3: =A3&" ("&Calc_Bank!T3&") "&TEXT(Calc_Bank!K3,"0,0%") -> Banca Adriatica (NE) 2,2%
A4: =Banks!A4 -> Banca Tirrena | B4: =UPPER(LEFT(A4,5)) -> BANCA | C4: =RIGHT(A4,LEN(A4)-FIND(" ",A4)) -> Tirrena | D4: =MID(A4,7,3) -> Tir | E4: =TRIM(Banks!D4) -> Verdi | F4: =CONCATENATE(Banks!B4,"-",LEFT(Banks!C4,3)) -> B103-Cen | G4: =SUBSTITUTE(A4,"Banca","Bk") -> Bk Tirrena | H4: =LOWER(C4)&"@esempio.it" -> tirrena@esempio.it | I4: =PROPER(LOWER(A4)) -> Banca Tirrena | J4: =REPT("*",Calc_Bank!L4) -> ****************** | K4: =TEXT(Calc_Bank!C4,"#.##0,0") -> 8.739,1 | L4: =_xlfn.TEXTJOIN(", ",TRUE,A4,B4,Calc_Bank!R4) -> Banca Tirrena, BANCA, Grande | M4: =VALUE(RIGHT(Banks!B4,3)) -> 103 | N4: =LEN(E4) -> 5 | O4: =IF(ISNUMBER(FIND("à",A4)),"accento","-") -> - | P4: =A4&" ("&Calc_Bank!T4&") "&TEXT(Calc_Bank!K4,"0,0%") -> Banca Tirrena (CE) 2,5%
A5: =Banks!A5 -> Banca Padana | B5: =UPPER(LEFT(A5,5)) -> BANCA | C5: =RIGHT(A5,LEN(A5)-FIND(" ",A5)) -> Padana | D5: =MID(A5,7,3) -> Pad | E5: =TRIM(Banks!D5) -> Ferrari | F5: =CONCATENATE(Banks!B5,"-",LEFT(Banks!C5,3)) -> B104-Nor | G5: =SUBSTITUTE(A5,"Banca","Bk") -> Bk Padana | H5: =LOWER(C5)&"@esempio.it" -> padana@esempio.it | I5: =PROPER(LOWER(A5)) -> Banca Padana | J5: =REPT("*",Calc_Bank!L5) -> ***************** | K5: =TEXT(Calc_Bank!C5,"#.##0,0") -> 9.892,6 | L5: =_xlfn.TEXTJOIN(", ",TRUE,A5,B5,Calc_Bank!R5) -> Banca Padana, BANCA, Grande | M5: =VALUE(RIGHT(Banks!B5,3)) -> 104 | N5: =LEN(E5) -> 7 | O5: =IF(ISNUMBER(FIND("à",A5)),"accento","-") -> - | P5: =A5&" ("&Calc_Bank!T5&") "&TEXT(Calc_Bank!K5,"0,0%") -> Banca Padana (NO) 2,9%
A6: =Banks!A6 -> Banca Etrusca | B6: =UPPER(LEFT(A6,5)) -> BANCA | C6: =RIGHT(A6,LEN(A6)-FIND(" ",A6)) -> Etrusca | D6: =MID(A6,7,3) -> Etr | E6: =TRIM(Banks!D6) -> Russo | F6: =CONCATENATE(Banks!B6,"-",LEFT(Banks!C6,3)) -> B105-Cen | G6: =SUBSTITUTE(A6,"Banca","Bk") -> Bk Etrusca | H6: =LOWER(C6)&"@esempio.it" -> etrusca@esempio.it | I6: =PROPER(LOWER(A6)) -> Banca Etrusca | J6: =REPT("*",Calc_Bank!L6) -> **************** | K6: =TEXT(Calc_Bank!C6,"#.##0,0") -> 10.989,1 | L6: =_xlfn.TEXTJOIN(", ",TRUE,A6,B6,Calc_Bank!R6) -> Banca Etrusca, BANCA, Media | M6: =VALUE(RIGHT(Banks!B6,3)) -> 105 | N6: =LEN(E6) -> 5 | O6: =IF(ISNUMBER(FIND("à",A6)),"accento","-") -> - | P6: =A6&" ("&Calc_Bank!T6&") "&TEXT(Calc_Bank!K6,"0,0%") -> Banca Etrusca (CE) 3,2%
A7: =Banks!A7 -> Banca Lariana | B7: =UPPER(LEFT(A7,5)) -> BANCA | C7: =RIGHT(A7,LEN(A7)-FIND(" ",A7)) -> Lariana | D7: =MID(A7,7,3) -> Lar | E7: =TRIM(Banks!D7) -> Colombo Luca | F7: =CONCATENATE(Banks!B7,"-",LEFT(Banks!C7,3)) -> B106-Nor | G7: =SUBSTITUTE(A7,"Banca","Bk") -> Bk Lariana | H7: =LOWER(C7)&"@esempio.it" -> lariana@esempio.it | I7: =PROPER(LOWER(A7)) -> Banca Lariana | J7: =REPT("*",Calc_Bank!L7) -> *************** | K7: =TEXT(Calc_Bank!C7,"#.##0,0") -> 12.105,6 | L7: =_xlfn.TEXTJOIN(", ",TRUE,A7,B7,Calc_Bank!R7) -> Banca Lariana, BANCA, Piccola | M7: =VALUE(RIGHT(Banks!B7,3)) -> 106 | N7: =LEN(E7) -> 12 | O7: =IF(ISNUMBER(FIND("à",A7)),"accento","-") -> - | P7: =A7&" ("&Calc_Bank!T7&") "&TEXT(Calc_Bank!K7,"0,0%") -> Banca Lariana (NO) 3,5%
A8: =Banks!A8 -> Banca Sabina | B8: =UPPER(LEFT(A8,5)) -> BANCA | C8: =RIGHT(A8,LEN(A8)-FIND(" ",A8)) -> Sabina | D8: =MID(A8,7,3) -> Sab | E8: =TRIM(Banks!D8) -> Ricci | F8: =CONCATENATE(Banks!B8,"-",LEFT(Banks!C8,3)) -> B107-Cen | G8: =SUBSTITUTE(A8,"Banca","Bk") -> Bk Sabina | H8: =LOWER(C8)&"@esempio.it" -> sabina@esempio.it | I8: =PROPER(LOWER(A8)) -> Banca Sabina | J8: =REPT("*",Calc_Bank!L8) -> ************** | K8: =TEXT(Calc_Bank!C8,"#.##0,0") -> 13.300,5 | L8: =_xlfn.TEXTJOIN(", ",TRUE,A8,B8,Calc_Bank!R8) -> Banca Sabina, BANCA, Piccola | M8: =VALUE(RIGHT(Banks!B8,3)) -> 107 | N8: =LEN(E8) -> 5 | O8: =IF(ISNUMBER(FIND("à",A8)),"accento","-") -> - | P8: =A8&" ("&Calc_Bank!T8&") "&TEXT(Calc_Bank!K8,"0,0%") -> Banca Sabina (CE) 3,9%
A9: =Banks!A9 -> Banca Irpina | B9: =UPPER(LEFT(A9,5)) -> BANCA | C9: =RIGHT(A9,LEN(A9)-FIND(" ",A9)) -> Irpina | D9: =MID(A9,7,3) -> Irp | E9: =TRIM(Banks!D9) -> Marino | F9: =CONCATENATE(Banks!B9,"-",LEFT(Banks!C9,3)) -> B108-Sud | G9: =SUBSTITUTE(A9,"Banca","Bk") -> Bk Irpina | H9: =LOWER(C9)&"@esempio.it" -> irpina@esempio.it | I9: =PROPER(LOWER(A9)) -> Banca Irpina | J9: =REPT("*",Calc_Bank!L9) -> ************* | K9: =TEXT(Calc_Bank!C9,"#.##0,0") -> 14.379,3 | L9: =_xlfn.TEXTJOIN(", ",TRUE,A9,B9,Calc_Bank!R9) -> Banca Irpina, BANCA, Piccola | M9: =VALUE(RIGHT(Banks!B9,3)) -> 108 | N9: =LEN(E9) -> 6 | O9: =IF(ISNUMBER(FIND("à",A9)),"accento","-") -> - | P9: =A9&" ("&Calc_Bank!T9&") "&TEXT(Calc_Bank!K9,"0,0%") -> Banca Irpina (SU) 4,2%
A10: =Banks!A10 -> Banca Sannita | B10: =UPPER(LEFT(A10,5)) -> BANCA | C10: =RIGHT(A10,LEN(A10)-FIND(" ",A10)) -> Sannita | D10: =MID(A10,7,3) -> San | E10: =TRIM(Banks!D10) -> Greco | F10: =CONCATENATE(Banks!B10,"-",LEFT(Banks!C10,3)) -> B109-Sud | G10: =SUBSTITUTE(A10,"Banca","Bk") -> Bk Sannita | H10: =LOWER(C10)&"@esempio.it" -> sannita@esempio.it | I10: =PROPER(LOWER(A10)) -> Banca Sannita | J10: =REPT("*",Calc_Bank!L10) -> ************ | K10: =TEXT(Calc_Bank!C10,"#.##0,0") -> 15.489,6 | L10: =_xlfn.TEXTJOIN(", ",TRUE,A10,B10,Calc_Bank!R10) -> Banca Sannita, BANCA, Media | M10: =VALUE(RIGHT(Banks!B10,3)) -> 109 | N10: =LEN(E10) -> 5 | O10: =IF(ISNUMBER(FIND("à",A10)),"accento","-") -> - | P10: =A10&" ("&Calc_Bank!T10&") "&TEXT(Calc_Bank!K10,"0,0%") -> Banca Sannita (SU) 4,5%
A11: =Banks!A11 -> Banca Ligure | B11: =UPPER(LEFT(A11,5)) -> BANCA | C11: =RIGHT(A11,LEN(A11)-FIND(" ",A11)) -> Ligure | D11: =MID(A11,7,3) -> Lig | E11: =TRIM(Banks!D11) -> Bruno | F11: =CONCATENATE(Banks!B11,"-",LEFT(Banks!C11,3)) -> B110-Nor | G11: =SUBSTITUTE(A11,"Banca","Bk") -> Bk Ligure | H11: =LOWER(C11)&"@esempio.it" -> ligure@esempio.it | I11: =PROPER(LOWER(A11)) -> Banca Ligure | J11: =REPT("*",Calc_Bank!L11) -> *********** | K11: =TEXT(Calc_Bank!C11,"#.##0,0") -> 16.648,0 | L11: =_xlfn.TEXTJOIN(", ",TRUE,A11,B11,Calc_Bank!R11) -> Banca Ligure, BANCA, Media | M11: =VALUE(RIGHT(Banks!B11,3)) -> 110 | N11: =LEN(E11) -> 5 | O11: =IF(ISNUMBER(FIND("à",A11)),"accento","-") -> - | P11: =A11&" ("&Calc_Bank!T11&") "&TEXT(Calc_Bank!K11,"0,0%") -> Banca Ligure (NO) 4,8%
A12: =Banks!A12 -> Banca Veneta | B12: =UPPER(LEFT(A12,5)) -> BANCA | C12: =RIGHT(A12,LEN(A12)-FIND(" ",A12)) -> Veneta | D12: =MID(A12,7,3) -> Ven | E12: =TRIM(Banks!D12) -> Gallo | F12: =CONCATENATE(Banks!B12,"-",LEFT(Banks!C12,3)) -> B111-Nor | G12: =SUBSTITUTE(A12,"Banca","Bk") -> Bk Veneta | H12: =LOWER(C12)&"@esempio.it" -> veneta@esempio.it | I12: =PROPER(LOWER(A12)) -> Banca Veneta | J12: =REPT("*",Calc_Bank!L12) -> ********** | K12: =TEXT(Calc_Bank!C12,"#.##0,0") -> 17.663,9 | L12: =_xlfn.TEXTJOIN(", ",TRUE,A12,B12,Calc_Bank!R12) -> Banca Veneta, BANCA, Grande | M12: =VALUE(RIGHT(Banks!B12,3)) -> 111 | N12: =LEN(E12) -> 5 | O12: =IF(ISNUMBER(FIND("à",A12)),"accento","-") -> - | P12: =A12&" ("&Calc_Bank!T12&") "&TEXT(Calc_Bank!K12,"0,0%") -> Banca Veneta (NE) 5,1%
A13: =Banks!A13 -> Banca Friulana | B13: =UPPER(LEFT(A13,5)) -> BANCA | C13: =RIGHT(A13,LEN(A13)-FIND(" ",A13)) -> Friulana | D13: =MID(A13,7,3) -> Fri | E13: =TRIM(Banks!D13) -> Conti | F13: =CONCATENATE(Banks!B13,"-",LEFT(Banks!C13,3)) -> B112-Nor | G13: =SUBSTITUTE(A13,"Banca","Bk") -> Bk Friulana | H13: =LOWER(C13)&"@esempio.it" -> friulana@esempio.it | I13: =PROPER(LOWER(A13)) -> Banca Friulana | J13: =REPT("*",Calc_Bank!L13) -> ********* | K13: =TEXT(Calc_Bank!C13,"#.##0,0") -> 18.941,6 | L13: =_xlfn.TEXTJOIN(", ",TRUE,A13,B13,Calc_Bank!R13) -> Banca Friulana, BANCA, Media | M13: =VALUE(RIGHT(Banks!B13,3)) -> 112 | N13: =LEN(E13) -> 5 | O13: =IF(ISNUMBER(FIND("à",A13)),"accento","-") -> - | P13: =A13&" ("&Calc_Bank!T13&") "&TEXT(Calc_Bank!K13,"0,0%") -> Banca Friulana (NE) 5,5%
... A21: =Banks!A21 -> Banca Città | B21: =UPPER(LEFT(A21,5)) -> BANCA | C21: =RIGHT(A21,LEN(A21)-FIND(" ",A21)) -> Città | D21: =MID(A21,7,3) -> Cit | E21: =TRIM(Banks!D21) -> Barbieri | F21: =CONCATENATE(Banks!B21,"-",LEFT(Banks!C21,3)) -> B120-Cen | G21: =SUBSTITUTE(A21,"Banca","Bk") -> Bk Città | H21: =LOWER(C21)&"@esempio.it" -> città@esempio.it | I21: =PROPER(LOWER(A21)) -> Banca Città | J21: =REPT("*",Calc_Bank!L21) -> * | K21: =TEXT(Calc_Bank!C21,"#.##0,0") -> 27.692,4 | L21: =_xlfn.TEXTJOIN(", ",TRUE,A21,B21,Calc_Bank!R21) -> Banca Città, BANCA, Grande | M21: =VALUE(RIGHT(Banks!B21,3)) -> 120 | N21: =LEN(E21) -> 8 | O21: =IF(ISNUMBER(FIND("à",A21)),"accento","-") -> accento | P21: =A21&" ("&Calc_Bank!T21&") "&TEXT(Calc_Bank!K21,"0,0%") -> Banca Città (CE) 8,1%

Sheet Calc_Dates
A1: Mese | B1: Inizio | C1: Fine | D1: +12 mesi | E1: Anno | F1: Mese | G1: Giorno | H1: Giorno sett. | I1: Giorni lav. | J1: Giorni | K1: Mesi da rif. | L1: Stato | M1: Etichetta | N1: Trimestre | O1: Fine rel. | P1: Primo lav. dopo
A2: =ROW()-1 -> 1 | B2: =DATE(2024,A2,1) -> 45292 | C2: =EOMONTH(B2,0) -> 45322 | D2: =EDATE(B2,12) -> 45658 | E2: =YEAR(C2) -> 2024 | F2: =MONTH(C2) -> 1 | G2: =DAY(C2) -> 31 | H2: =WEEKDAY(C2,2) -> 3 | I2: =NETWORKDAYS(B2,C2) -> 23 | J2: =C2-B2+1 -> 31 | K2: =IF(C2<=Control!$B$9,DATEDIF(C2,Control!$B$9,"m"),-DATEDIF(Control!$B$9,C2,"m")) -> 12 | L2: =IF(C2=Control!$B$9,"corrente",IF(C2<Control!$B$9,"passato","futuro")) -> passato | M2: =TEXT(C2,"mmm-aa") -> gen-24 | N2: =INT((F2-1)/3)+1 -> 1 | O2: =EOMONTH(Control!$B$9,-(A2-1)) -> 45688 | P2: =WORKDAY(C2,1) -> 45323
A3: =ROW()-1 -> 2 | B3: =DATE(2024,A3,1) -> 45323 | C3: =EOMONTH(B3,0) -> 45351 | D3: =EDATE(B3,12) -> 45689 | E3: =YEAR(C3) -> 2024 | F3: =MONTH(C3) -> 2 | G3: =DAY(C3) -> 29 | H3: =WEEKDAY(C3,2) -> 4 | I3: =NETWORKDAYS(B3,C3) -> 21 | J3: =C3-B3+1 -> 29 | K3: =IF(C3<=Control!$B$9,DATEDIF(C3,Control!$B$9,"m"),-DATEDIF(Control!$B$9,C3,"m")) -> 11 | L3: =IF(C3=Control!$B$9,"corrente",IF(C3<Control!$B$9,"passato","futuro")) -> passato | M3: =TEXT(C3,"mmm-aa") -> feb-24 | N3: =INT((F3-1)/3)+1 -> 1 | O3: =EOMONTH(Control!$B$9,-(A3-1)) -> 45657 | P3: =WORKDAY(C3,1) -> 45352
A4: =ROW()-1 -> 3 | B4: =DATE(2024,A4,1) -> 45352 | C4: =EOMONTH(B4,0) -> 45382 | D4: =EDATE(B4,12) -> 45717 | E4: =YEAR(C4) -> 2024 | F4: =MONTH(C4) -> 3 | G4: =DAY(C4) -> 31 | H4: =WEEKDAY(C4,2) -> 7 | I4: =NETWORKDAYS(B4,C4) -> 21 | J4: =C4-B4+1 -> 31 | K4: =IF(C4<=Control!$B$9,DATEDIF(C4,Control!$B$9,"m"),-DATEDIF(Control!$B$9,C4,"m")) -> 10 | L4: =IF(C4=Control!$B$9,"corrente",IF(C4<Control!$B$9,"passato","futuro")) -> passato | M4: =TEXT(C4,"mmm-aa") -> mar-24 | N4: =INT((F4-1)/3)+1 -> 1 | O4: =EOMONTH(Control!$B$9,-(A4-1)) -> 45626 | P4: =WORKDAY(C4,1) -> 45383
A5: =ROW()-1 -> 4 | B5: =DATE(2024,A5,1) -> 45383 | C5: =EOMONTH(B5,0) -> 45412 | D5: =EDATE(B5,12) -> 45748 | E5: =YEAR(C5) -> 2024 | F5: =MONTH(C5) -> 4 | G5: =DAY(C5) -> 30 | H5: =WEEKDAY(C5,2) -> 2 | I5: =NETWORKDAYS(B5,C5) -> 22 | J5: =C5-B5+1 -> 30 | K5: =IF(C5<=Control!$B$9,DATEDIF(C5,Control!$B$9,"m"),-DATEDIF(Control!$B$9,C5,"m")) -> 9 | L5: =IF(C5=Control!$B$9,"corrente",IF(C5<Control!$B$9,"passato","futuro")) -> passato | M5: =TEXT(C5,"mmm-aa") -> apr-24 | N5: =INT((F5-1)/3)+1 -> 2 | O5: =EOMONTH(Control!$B$9,-(A5-1)) -> 45596 | P5: =WORKDAY(C5,1) -> 45413
A6: =ROW()-1 -> 5 | B6: =DATE(2024,A6,1) -> 45413 | C6: =EOMONTH(B6,0) -> 45443 | D6: =EDATE(B6,12) -> 45778 | E6: =YEAR(C6) -> 2024 | F6: =MONTH(C6) -> 5 | G6: =DAY(C6) -> 31 | H6: =WEEKDAY(C6,2) -> 5 | I6: =NETWORKDAYS(B6,C6) -> 23 | J6: =C6-B6+1 -> 31 | K6: =IF(C6<=Control!$B$9,DATEDIF(C6,Control!$B$9,"m"),-DATEDIF(Control!$B$9,C6,"m")) -> 8 | L6: =IF(C6=Control!$B$9,"corrente",IF(C6<Control!$B$9,"passato","futuro")) -> passato | M6: =TEXT(C6,"mmm-aa") -> mag-24 | N6: =INT((F6-1)/3)+1 -> 2 | O6: =EOMONTH(Control!$B$9,-(A6-1)) -> 45565 | P6: =WORKDAY(C6,1) -> 45446
A7: =ROW()-1 -> 6 | B7: =DATE(2024,A7,1) -> 45444 | C7: =EOMONTH(B7,0) -> 45473 | D7: =EDATE(B7,12) -> 45809 | E7: =YEAR(C7) -> 2024 | F7: =MONTH(C7) -> 6 | G7: =DAY(C7) -> 30 | H7: =WEEKDAY(C7,2) -> 7 | I7: =NETWORKDAYS(B7,C7) -> 20 | J7: =C7-B7+1 -> 30 | K7: =IF(C7<=Control!$B$9,DATEDIF(C7,Control!$B$9,"m"),-DATEDIF(Control!$B$9,C7,"m")) -> 7 | L7: =IF(C7=Control!$B$9,"corrente",IF(C7<Control!$B$9,"passato","futuro")) -> passato | M7: =TEXT(C7,"mmm-aa") -> giu-24 | N7: =INT((F7-1)/3)+1 -> 2 | O7: =EOMONTH(Control!$B$9,-(A7-1)) -> 45535 | P7: =WORKDAY(C7,1) -> 45474
A8: =ROW()-1 -> 7 | B8: =DATE(2024,A8,1) -> 45474 | C8: =EOMONTH(B8,0) -> 45504 | D8: =EDATE(B8,12) -> 45839 | E8: =YEAR(C8) -> 2024 | F8: =MONTH(C8) -> 7 | G8: =DAY(C8) -> 31 | H8: =WEEKDAY(C8,2) -> 3 | I8: =NETWORKDAYS(B8,C8) -> 23 | J8: =C8-B8+1 -> 31 | K8: =IF(C8<=Control!$B$9,DATEDIF(C8,Control!$B$9,"m"),-DATEDIF(Control!$B$9,C8,"m")) -> 6 | L8: =IF(C8=Control!$B$9,"corrente",IF(C8<Control!$B$9,"passato","futuro")) -> passato | M8: =TEXT(C8,"mmm-aa") -> lug-24 | N8: =INT((F8-1)/3)+1 -> 3 | O8: =EOMONTH(Control!$B$9,-(A8-1)) -> 45504 | P8: =WORKDAY(C8,1) -> 45505
A9: =ROW()-1 -> 8 | B9: =DATE(2024,A9,1) -> 45505 | C9: =EOMONTH(B9,0) -> 45535 | D9: =EDATE(B9,12) -> 45870 | E9: =YEAR(C9) -> 2024 | F9: =MONTH(C9) -> 8 | G9: =DAY(C9) -> 31 | H9: =WEEKDAY(C9,2) -> 6 | I9: =NETWORKDAYS(B9,C9) -> 22 | J9: =C9-B9+1 -> 31 | K9: =IF(C9<=Control!$B$9,DATEDIF(C9,Control!$B$9,"m"),-DATEDIF(Control!$B$9,C9,"m")) -> 5 | L9: =IF(C9=Control!$B$9,"corrente",IF(C9<Control!$B$9,"passato","futuro")) -> passato | M9: =TEXT(C9,"mmm-aa") -> ago-24 | N9: =INT((F9-1)/3)+1 -> 3 | O9: =EOMONTH(Control!$B$9,-(A9-1)) -> 45473 | P9: =WORKDAY(C9,1) -> 45537
A10: =ROW()-1 -> 9 | B10: =DATE(2024,A10,1) -> 45536 | C10: =EOMONTH(B10,0) -> 45565 | D10: =EDATE(B10,12) -> 45901 | E10: =YEAR(C10) -> 2024 | F10: =MONTH(C10) -> 9 | G10: =DAY(C10) -> 30 | H10: =WEEKDAY(C10,2) -> 1 | I10: =NETWORKDAYS(B10,C10) -> 21 | J10: =C10-B10+1 -> 30 | K10: =IF(C10<=Control!$B$9,DATEDIF(C10,Control!$B$9,"m"),-DATEDIF(Control!$B$9,C10,"m")) -> 4 | L10: =IF(C10=Control!$B$9,"corrente",IF(C10<Control!$B$9,"passato","futuro")) -> passato | M10: =TEXT(C10,"mmm-aa") -> set-24 | N10: =INT((F10-1)/3)+1 -> 3 | O10: =EOMONTH(Control!$B$9,-(A10-1)) -> 45443 | P10: =WORKDAY(C10,1) -> 45566
A11: =ROW()-1 -> 10 | B11: =DATE(2024,A11,1) -> 45566 | C11: =EOMONTH(B11,0) -> 45596 | D11: =EDATE(B11,12) -> 45931 | E11: =YEAR(C11) -> 2024 | F11: =MONTH(C11) -> 10 | G11: =DAY(C11) -> 31 | H11: =WEEKDAY(C11,2) -> 4 | I11: =NETWORKDAYS(B11,C11) -> 23 | J11: =C11-B11+1 -> 31 | K11: =IF(C11<=Control!$B$9,DATEDIF(C11,Control!$B$9,"m"),-DATEDIF(Control!$B$9,C11,"m")) -> 3 | L11: =IF(C11=Control!$B$9,"corrente",IF(C11<Control!$B$9,"passato","futuro")) -> passato | M11: =TEXT(C11,"mmm-aa") -> ott-24 | N11: =INT((F11-1)/3)+1 -> 4 | O11: =EOMONTH(Control!$B$9,-(A11-1)) -> 45412 | P11: =WORKDAY(C11,1) -> 45597
A12: =ROW()-1 -> 11 | B12: =DATE(2024,A12,1) -> 45597 | C12: =EOMONTH(B12,0) -> 45626 | D12: =EDATE(B12,12) -> 45962 | E12: =YEAR(C12) -> 2024 | F12: =MONTH(C12) -> 11 | G12: =DAY(C12) -> 30 | H12: =WEEKDAY(C12,2) -> 6 | I12: =NETWORKDAYS(B12,C12) -> 21 | J12: =C12-B12+1 -> 30 | K12: =IF(C12<=Control!$B$9,DATEDIF(C12,Control!$B$9,"m"),-DATEDIF(Control!$B$9,C12,"m")) -> 2 | L12: =IF(C12=Control!$B$9,"corrente",IF(C12<Control!$B$9,"passato","futuro")) -> passato | M12: =TEXT(C12,"mmm-aa") -> nov-24 | N12: =INT((F12-1)/3)+1 -> 4 | O12: =EOMONTH(Control!$B$9,-(A12-1)) -> 45382 | P12: =WORKDAY(C12,1) -> 45628
A13: =ROW()-1 -> 12 | B13: =DATE(2024,A13,1) -> 45627 | C13: =EOMONTH(B13,0) -> 45657 | D13: =EDATE(B13,12) -> 45992 | E13: =YEAR(C13) -> 2024 | F13: =MONTH(C13) -> 12 | G13: =DAY(C13) -> 31 | H13: =WEEKDAY(C13,2) -> 2 | I13: =NETWORKDAYS(B13,C13) -> 22 | J13: =C13-B13+1 -> 31 | K13: =IF(C13<=Control!$B$9,DATEDIF(C13,Control!$B$9,"m"),-DATEDIF(Control!$B$9,C13,"m")) -> 1 | L13: =IF(C13=Control!$B$9,"corrente",IF(C13<Control!$B$9,"passato","futuro")) -> passato | M13: =TEXT(C13,"mmm-aa") -> dic-24 | N13: =INT((F13-1)/3)+1 -> 4 | O13: =EOMONTH(Control!$B$9,-(A13-1)) -> 45351 | P13: =WORKDAY(C13,1) -> 45658
... A37: =ROW()-1 -> 36 | B37: =DATE(2024,A37,1) -> 46357 | C37: =EOMONTH(B37,0) -> 46387 | D37: =EDATE(B37,12) -> 46722 | E37: =YEAR(C37) -> 2026 | F37: =MONTH(C37) -> 12 | G37: =DAY(C37) -> 31 | H37: =WEEKDAY(C37,2) -> 4 | I37: =NETWORKDAYS(B37,C37) -> 23 | J37: =C37-B37+1 -> 31 | K37: =IF(C37<=Control!$B$9,DATEDIF(C37,Control!$B$9,"m"),-DATEDIF(Control!$B$9,C37,"m")) -> -23 | L37: =IF(C37=Control!$B$9,"corrente",IF(C37<Control!$B$9,"passato","futuro")) -> futuro | M37: =TEXT(C37,"mmm-aa") -> dic-26 | N37: =INT((F37-1)/3)+1 -> 4 | O37: =EOMONTH(Control!$B$9,-(A37-1)) -> 44620 | P37: =WORKDAY(C37,1) -> 46388

Sheet Calc_Dynamic
A1: Banche della regione | C1: Ordinate | G1: Prodotti | I1: Sequenza | J1: Ultimi 12 | L1: Per volumi
A2: {=_xlfn._xlws.FILTER(Banks!A2:A21,Banks!C2:C21=Control!B5,"nessuna")} -> Banca Tirrena | C2: {=_xlfn._xlws.SORT(Calc_Bank!A2:C21,3,-1)} -> Banca Città | D2: Centro | E2: 27692.4 | G2: {=_xlfn.UNIQUE(Data!C2:C5761)} -> Mutui | I2: {=_xlfn.SEQUENCE(12)} -> 1 | J2: {=Control!B3-12+_xlfn.SEQUENCE(12)} -> 2 | L2: {=_xlfn.SORTBY(Banks!A2:A21,Calc_Bank!C2:C21,-1)} -> Banca Città | P2: CONFRONTA.X | Q2: =_xlfn.XMATCH(Control!B2,Banks!A2:A21) -> 3
A3: Banca Etrusca | C3: Banca Romagnola | D3: Nord-Est | E3: 26741.1 | G3: Prestiti | I3: 2 | J3: 3 | L3: Banca Romagnola | P3: LET media | Q3: =_xlfn.LET(_xlpm.x,Calc_Bank!C2:C21,SUM(_xlpm.x)/COUNT(_xlpm.x)) -> 17178.01
A4: Banca Sabina | C4: Banca Sarda | D4: Isole | E4: 25627 | G4: Conti | I4: 3 | J4: 4 | L4: Banca Sarda | P4: CERCA.X non trovato | Q4: =_xlfn.XLOOKUP(Control!B3+100,FX!A2:A37,FX!C2:C37,"fuori",0) -> fuori
A5: Banca Umbra | C5: Banca Sicula | D5: Isole | E5: 24517.8 | G5: Carte | I5: 4 | J5: 5 | L5: Banca Sicula | P5: CERCA.X successivo | Q5: =_xlfn.XLOOKUP(Control!B3+0.5,FX!A2:A37,FX!C2:C37,,1) -> 1.0648
A6: Banca Marchigiana | C6: Banca Calabra | D6: Sud | E6: 23396.2 | G6: Leasing | I6: 5 | J6: 6 | L6: Banca Calabra | P6: CERCA.X precedente | Q6: =_xlfn.XLOOKUP(Control!B3-0.5,FX!A2:A37,FX!C2:C37,,-1) -> 1.0782
A7: Banca Città | C7: Banca Lucana | D7: Sud | E7: 22158.4 | G7: Factoring | I7: 6 | J7: 7 | L7: Banca Lucana | P7: CERCA.X jolly | Q7: =_xlfn.XLOOKUP("Banca T*",Banks!A2:A21,Banks!B2:B21,"n.d.",2) -> B103
C8: Banca Marchigiana | D8: Centro | E8: 21147.3 | G8: Risparmio | I8: 7 | J8: 8 | L8: Banca Marchigiana | P8: CERCA.X dal fondo | Q8: =_xlfn.XLOOKUP(Control!B2,Data!A2:A5761,Data!E2:E5761,0,0,-1) -> 2019.4
C9: Banca Umbra | D9: Centro | E9: 19938.9 | G9: Assicurazioni | I9: 8 | J9: 9 | L9: Banca Umbra | P9: SOMMA(FILTRO) | Q9: {=SUM(_xlfn._xlws.FILTER(Calc_Bank!C2:C21,Calc_Bank!B2:B21=Control!B5,0))} -> 101807.3
C10: Banca Friulana | D10: Nord-Est | E10: 18941.6 | I10: 9 | J10: 10 | L10: Banca Friulana | P10: CONTA regione | Q10: {=ROWS(_xlfn._xlws.FILTER(Banks!A2:A21,Banks!C2:C21=Control!B5))} -> 6
C11: Banca Veneta | D11: Nord-Est | E11: 17663.9 | I11: 10 | J11: 11 | L11: Banca Veneta | P11: PIÙ.SE | Q11: {=_xlfn.IFS(Q9>50000,"alto",Q9>20000,"medio",TRUE,"basso")} -> alto
C12: Banca Ligure | D12: Nord-Ovest | E12: 16648 | I12: 11 | J12: 12 | L12: Banca Ligure
C13: Banca Sannita | D13: Sud | E13: 15489.6 | I13: 12 | J13: 13 | L13: Banca Sannita
C14: Banca Irpina | D14: Sud | E14: 14379.3 | L14: Banca Irpina
C15: Banca Sabina | D15: Centro | E15: 13300.5 | L15: Banca Sabina
C16: Banca Lariana | D16: Nord-Ovest | E16: 12105.6 | L16: Banca Lariana
C17: Banca Etrusca | D17: Centro | E17: 10989.1 | L17: Banca Etrusca
C18: Banca Padana | D18: Nord-Ovest | E18: 9892.6 | L18: Banca Padana
C19: Banca Tirrena | D19: Centro | E19: 8739.1 | L19: Banca Tirrena
C20: Banca Adriatica | D20: Nord-Est | E20: 7649.6 | L20: Banca Adriatica
C21: Banca Alpi | D21: Nord-Ovest | E21: 6542.2 | L21: Banca Alpi
A30: {=TRANSPOSE(Calc_Month!C2:C13)} -> 8012.1 | B30: 8126.5 | C30: 8163.5 | D30: 8209.7 | E30: 8325.2 | F30: 8343.3 | G30: 8405 | H30: 8440.6 | I30: 8499.6 | J30: 8590.6 | K30: 8644.9 | L30: 8718.7

Sheet Calc_Names
A2: Volumi sel. | B2: =SUMIFS(D_Vol,D_Bank,SelBank,D_Month,SelMonth) -> 8739.1
A3: Scenario | B3: =B2*(1+Rate) -> 9001.273
A4: Banche regione | B4: =COUNTIF(BankRegion,SelRegion) -> 6
A5: Prima banca | B5: =INDEX(BankList,1) -> Banca Alpi
A6: Imposta | B6: =TaxRate*B2 -> 2097.384
A7: Totale netto | B7: =SUM(Calc_Bank!C2:C21)*(1-TaxRate) -> 261105.75
A8: Etichetta | B8: =SelBank&" / "&SelRegion -> Banca Tirrena / Centro
A9: Nome calcolato | B9: {=VolSel} -> 8739.1
A11: {=INDEX(BankList,ROW()-10)} -> Banca Alpi | B11: =SUMIFS(D_Vol,D_Bank,A11,D_Month,SelMonth) -> 6542.2
A12: {=INDEX(BankList,ROW()-10)} -> Banca Adriatica | B12: =SUMIFS(D_Vol,D_Bank,A12,D_Month,SelMonth) -> 7649.6
A13: {=INDEX(BankList,ROW()-10)} -> Banca Tirrena | B13: =SUMIFS(D_Vol,D_Bank,A13,D_Month,SelMonth) -> 8739.1
A14: {=INDEX(BankList,ROW()-10)} -> Banca Padana | B14: =SUMIFS(D_Vol,D_Bank,A14,D_Month,SelMonth) -> 9892.6
A15: {=INDEX(BankList,ROW()-10)} -> Banca Etrusca | B15: =SUMIFS(D_Vol,D_Bank,A15,D_Month,SelMonth) -> 10989.1
A16: {=INDEX(BankList,ROW()-10)} -> Banca Lariana | B16: =SUMIFS(D_Vol,D_Bank,A16,D_Month,SelMonth) -> 12105.6
A17: {=INDEX(BankList,ROW()-10)} -> Banca Sabina | B17: =SUMIFS(D_Vol,D_Bank,A17,D_Month,SelMonth) -> 13300.5
A18: {=INDEX(BankList,ROW()-10)} -> Banca Irpina | B18: =SUMIFS(D_Vol,D_Bank,A18,D_Month,SelMonth) -> 14379.3
A19: {=INDEX(BankList,ROW()-10)} -> Banca Sannita | B19: =SUMIFS(D_Vol,D_Bank,A19,D_Month,SelMonth) -> 15489.6
A20: {=INDEX(BankList,ROW()-10)} -> Banca Ligure | B20: =SUMIFS(D_Vol,D_Bank,A20,D_Month,SelMonth) -> 16648
A21: {=INDEX(BankList,ROW()-10)} -> Banca Veneta | B21: =SUMIFS(D_Vol,D_Bank,A21,D_Month,SelMonth) -> 17663.9
A22: {=INDEX(BankList,ROW()-10)} -> Banca Friulana | B22: =SUMIFS(D_Vol,D_Bank,A22,D_Month,SelMonth) -> 18941.6
... A30: {=INDEX(BankList,ROW()-10)} -> Banca Città | B30: =SUMIFS(D_Vol,D_Bank,A30,D_Month,SelMonth) -> 27692.4

Sheet Calc_Indirect
A2: INDIRETTO mese | B2: {=INDIRECT("Calc_Month!C"&(Control!$B$3+1))} -> 8739.1
A3: INDIRETTO slide | B3: {=INDIRECT("'SLIDE Sintesi'!D5")} -> 8739.1
A4: INDIRETTO riga | B4: =SUM(INDIRECT("Calc_BankMonth!B"&(Control!$B$6+2)&":AK"&(Control!$B$6+2))) -> 328300.7
A5: SCARTO cella | B5: =OFFSET(Calc_BankMonth!$A$2,Control!$B$6,Control!$B$3) -> 8739.1
A6: SCARTO trimestre | B6: =SUM(OFFSET(Calc_Month!$C$1,Control!$B$3-2,0,3,1)) -> 26102.7
A7: INDIRIZZO | B7: {=INDIRECT(ADDRESS(Control!$B$3+1,3,1,1,"Calc_Month"))} -> 8739.1
A8: RIGHE | B8: =ROWS(Calc_Month!A2:A37) -> 36
A12: =Banks!A2 -> Banca Alpi | B12: {=INDEX(OFFSET(Calc_BankMonth!$B$3,0,0,20,36),ROW()-11,Control!$B$3)} -> 6542.2
A13: =Banks!A3 -> Banca Adriatica | B13: {=INDEX(OFFSET(Calc_BankMonth!$B$3,0,0,20,36),ROW()-11,Control!$B$3)} -> 7649.6
A14: =Banks!A4 -> Banca Tirrena | B14: {=INDEX(OFFSET(Calc_BankMonth!$B$3,0,0,20,36),ROW()-11,Control!$B$3)} -> 8739.1
A15: =Banks!A5 -> Banca Padana | B15: {=INDEX(OFFSET(Calc_BankMonth!$B$3,0,0,20,36),ROW()-11,Control!$B$3)} -> 9892.6
A16: =Banks!A6 -> Banca Etrusca | B16: {=INDEX(OFFSET(Calc_BankMonth!$B$3,0,0,20,36),ROW()-11,Control!$B$3)} -> 10989.1
A17: =Banks!A7 -> Banca Lariana | B17: {=INDEX(OFFSET(Calc_BankMonth!$B$3,0,0,20,36),ROW()-11,Control!$B$3)} -> 12105.6
A18: =Banks!A8 -> Banca Sabina | B18: {=INDEX(OFFSET(Calc_BankMonth!$B$3,0,0,20,36),ROW()-11,Control!$B$3)} -> 13300.5
A19: =Banks!A9 -> Banca Irpina | B19: {=INDEX(OFFSET(Calc_BankMonth!$B$3,0,0,20,36),ROW()-11,Control!$B$3)} -> 14379.3
A20: =Banks!A10 -> Banca Sannita | B20: {=INDEX(OFFSET(Calc_BankMonth!$B$3,0,0,20,36),ROW()-11,Control!$B$3)} -> 15489.6
A21: =Banks!A11 -> Banca Ligure | B21: {=INDEX(OFFSET(Calc_BankMonth!$B$3,0,0,20,36),ROW()-11,Control!$B$3)} -> 16648
A22: =Banks!A12 -> Banca Veneta | B22: {=INDEX(OFFSET(Calc_BankMonth!$B$3,0,0,20,36),ROW()-11,Control!$B$3)} -> 17663.9
A23: =Banks!A13 -> Banca Friulana | B23: {=INDEX(OFFSET(Calc_BankMonth!$B$3,0,0,20,36),ROW()-11,Control!$B$3)} -> 18941.6
... A31: =Banks!A21 -> Banca Città | B31: {=INDEX(OFFSET(Calc_BankMonth!$B$3,0,0,20,36),ROW()-11,Control!$B$3)} -> 27692.4

Sheet Calc_Links
A2: Gap % peer | B2: =[1]Summary!$B$2 -> 0.057912768 | C2: =_xlfn.XLOOKUP(Control!B2,[1]Compare!$A$2:$A$21,[1]Compare!$E$2:$E$21) -> 478.4
A3: Rango peer | B3: =[1]Summary!$B$3 -> 4
A4: Gap totale | B4: =[1]Summary!$B$4 -> 16749.5
A5: Banche avanti | B5: =[1]Summary!$B$5 -> 11
A6: Codice mese | B6: =[1]Summary!$B$6 -> 13
A7: Etichetta gap | B7: =[1]Summary!$B$7 -> 06%
A8: Media peer | B8: =[1]Summary!$B$8 -> 16340.535
A10: Totale regioni | B10: =[2]Summary!B2 -> 343560.2
A11: Gap regione sel. | B11: =[2]Summary!B3 -> 51141.3
A12: Gap peer totale | B12: =[2]Summary!B4 -> 16749.5
A13: Gap peer sel. | B13: =[2]Summary!B5 -> 4594.3
A14: Rango peer | B14: =[2]Summary!B6 -> 4
A15: Regione sel. | B15: =[2]Summary!B7 -> Centro
A19: Banca | B19: Peer | C19: Gap %
A20: =Calc_Bank!A2 -> Banca Alpi | B20: =VLOOKUP(A20,[1]Compare!$A$2:$H$21,3,FALSE) -> 6339 | C20: =IFERROR(INDEX([1]Compare!$F$2:$F$21,MATCH(A20,[1]Compare!$A$2:$A$21,0)),0) -> 0.032055529
A21: =Calc_Bank!A3 -> Banca Adriatica | B21: =VLOOKUP(A21,[1]Compare!$A$2:$H$21,3,FALSE) -> 7115.9 | C21: =IFERROR(INDEX([1]Compare!$F$2:$F$21,MATCH(A21,[1]Compare!$A$2:$A$21,0)),0) -> 0.075001054
A22: =Calc_Bank!A4 -> Banca Tirrena | B22: =VLOOKUP(A22,[1]Compare!$A$2:$H$21,3,FALSE) -> 8260.7 | C22: =IFERROR(INDEX([1]Compare!$F$2:$F$21,MATCH(A22,[1]Compare!$A$2:$A$21,0)),0) -> 0.057912768
A23: =Calc_Bank!A5 -> Banca Padana | B23: =VLOOKUP(A23,[1]Compare!$A$2:$H$21,3,FALSE) -> 9250.5 | C23: =IFERROR(INDEX([1]Compare!$F$2:$F$21,MATCH(A23,[1]Compare!$A$2:$A$21,0)),0) -> 0.069412464
A24: =Calc_Bank!A6 -> Banca Etrusca | B24: =VLOOKUP(A24,[1]Compare!$A$2:$H$21,3,FALSE) -> 10605.2 | C24: =IFERROR(INDEX([1]Compare!$F$2:$F$21,MATCH(A24,[1]Compare!$A$2:$A$21,0)),0) -> 0.036199223
A25: =Calc_Bank!A7 -> Banca Lariana | B25: =VLOOKUP(A25,[1]Compare!$A$2:$H$21,3,FALSE) -> 11544 | C25: =IFERROR(INDEX([1]Compare!$F$2:$F$21,MATCH(A25,[1]Compare!$A$2:$A$21,0)),0) -> 0.048648649
A26: =Calc_Bank!A8 -> Banca Sabina | B26: =VLOOKUP(A26,[1]Compare!$A$2:$H$21,3,FALSE) -> 12804.1 | C26: =IFERROR(INDEX([1]Compare!$F$2:$F$21,MATCH(A26,[1]Compare!$A$2:$A$21,0)),0) -> 0.038768832
A27: =Calc_Bank!A9 -> Banca Irpina | B27: =VLOOKUP(A27,[1]Compare!$A$2:$H$21,3,FALSE) -> 13580.4 | C27: =IFERROR(INDEX([1]Compare!$F$2:$F$21,MATCH(A27,[1]Compare!$A$2:$A$21,0)),0) -> 0.058827428
A28: =Calc_Bank!A10 -> Banca Sannita | B28: =VLOOKUP(A28,[1]Compare!$A$2:$H$21,3,FALSE) -> 14812.8 | C28: =IFERROR(INDEX([1]Compare!$F$2:$F$21,MATCH(A28,[1]Compare!$A$2:$A$21,0)),0) -> 0.045690214
A29: =Calc_Bank!A11 -> Banca Ligure | B29: =VLOOKUP(A29,[1]Compare!$A$2:$H$21,3,FALSE) -> 15908.8 | C29: =IFERROR(INDEX([1]Compare!$F$2:$F$21,MATCH(A29,[1]Compare!$A$2:$A$21,0)),0) -> 0.04646485
A30: =Calc_Bank!A12 -> Banca Veneta | B30: =VLOOKUP(A30,[1]Compare!$A$2:$H$21,3,FALSE) -> 16773.6 | C30: =IFERROR(INDEX([1]Compare!$F$2:$F$21,MATCH(A30,[1]Compare!$A$2:$A$21,0)),0) -> 0.053077455
A31: =Calc_Bank!A13 -> Banca Friulana | B31: =VLOOKUP(A31,[1]Compare!$A$2:$H$21,3,FALSE) -> 17926.2 | C31: =IFERROR(INDEX([1]Compare!$F$2:$F$21,MATCH(A31,[1]Compare!$A$2:$A$21,0)),0) -> 0.056643349
... A39: =Calc_Bank!A21 -> Banca Città | B39: =VLOOKUP(A39,[1]Compare!$A$2:$H$21,3,FALSE) -> 26362.1 | C39: =IFERROR(INDEX([1]Compare!$F$2:$F$21,MATCH(A39,[1]Compare!$A$2:$A$21,0)),0) -> 0.050462596

Sheet Calc_Deep
A1: Banca | B1: L1 USD | C1: L2 +scenario | D1: L3 crescita | E1: L4 regione | F1: L5 statistica | G1: L6 arrot. | H1: L7 indice | I1: L8 date | J1: L9 classe | K1: L10 rango
A2: =Calc_Bank!A2 -> Banca Alpi | B2: =Calc_Bank!C2*Control!$B$15 -> 7012.5842 | C2: =B2+Calc_Scenario!AL3/100 -> 7084.9919 | D2: =C2*(1+Calc_Growth!AM3) -> 7135.2833 | E2: =D2-_xlfn.XLOOKUP(Calc_Bank!B2,Calc_Region!$A$2:$A$6,Calc_Region!$F$2:$F$6)*0.01 -> 7022.3123 | F2: =E2+Calc_Stats!$I$2*0.001 -> 7039.4683 | G2: =ROUND(F2,2) -> 7039.47 | H2: =G2/MAX(1,Calc_Month!$C$2)*1000 -> 878.60486 | I2: =H2+Calc_Dates!$J$2 -> 909.60486 | J2: =IF(I2>AVERAGE($I$2:$I$21),"alto","basso") -> basso | K2: =RANK(I2,$I$2:$I$21) -> 20
A3: =Calc_Bank!A3 -> Banca Adriatica | B3: =Calc_Bank!C3*Control!$B$15 -> 8199.6062 | C3: =B3+Calc_Scenario!AL4/100 -> 8284.2705 | D3: =C3*(1+Calc_Growth!AM4) -> 8343.7108 | E3: =D3-_xlfn.XLOOKUP(Calc_Bank!B3,Calc_Region!$A$2:$A$6,Calc_Region!$F$2:$F$6)*0.01 -> 8166.2203 | F3: =E3+Calc_Stats!$I$2*0.001 -> 8183.3762 | G3: =ROUND(F3,2) -> 8183.38 | H3: =G3/MAX(1,Calc_Month!$C$2)*1000 -> 1021.3777 | I3: =H3+Calc_Dates!$J$2 -> 1052.3777 | J3: =IF(I3>AVERAGE($I$2:$I$21),"alto","basso") -> basso | K3: =RANK(I3,$I$2:$I$21) -> 19
A4: =Calc_Bank!A4 -> Banca Tirrena | B4: =Calc_Bank!C4*Control!$B$15 -> 9367.4413 | C4: =B4+Calc_Scenario!AL5/100 -> 9464.1639 | D4: =C4*(1+Calc_Growth!AM5) -> 9530.9693 | E4: =D4-_xlfn.XLOOKUP(Calc_Bank!B4,Calc_Region!$A$2:$A$6,Calc_Region!$F$2:$F$6)*0.01 -> 9361.2904 | F4: =E4+Calc_Stats!$I$2*0.001 -> 9378.4464 | G4: =ROUND(F4,2) -> 9378.45 | H4: =G4/MAX(1,Calc_Month!$C$2)*1000 -> 1170.5358 | I4: =H4+Calc_Dates!$J$2 -> 1201.5358 | J4: =IF(I4>AVERAGE($I$2:$I$21),"alto","basso") -> basso | K4: =RANK(I4,$I$2:$I$21) -> 18
A5: =Calc_Bank!A5 -> Banca Padana | B5: =Calc_Bank!C5*Control!$B$15 -> 10603.878 | C5: =B5+Calc_Scenario!AL6/100 -> 10713.367 | D5: =C5*(1+Calc_Growth!AM6) -> 10787.206 | E5: =D5-_xlfn.XLOOKUP(Calc_Bank!B5,Calc_Region!$A$2:$A$6,Calc_Region!$F$2:$F$6)*0.01 -> 10674.235 | F5: =E5+Calc_Stats!$I$2*0.001 -> 10691.391 | G5: =ROUND(F5,2) -> 10691.39 | H5: =G5/MAX(1,Calc_Month!$C$2)*1000 -> 1334.4055 | I5: =H5+Calc_Dates!$J$2 -> 1365.4055 | J5: =IF(I5>AVERAGE($I$2:$I$21),"alto","basso") -> basso | K5: =RANK(I5,$I$2:$I$21) -> 17
A6: =Calc_Bank!A6 -> Banca Etrusca | B6: =Calc_Bank!C6*Control!$B$15 -> 11779.216 | C6: =B6+Calc_Scenario!AL7/100 -> 11900.841 | D6: =C6*(1+Calc_Growth!AM7) -> 11987.247 | E6: =D6-_xlfn.XLOOKUP(Calc_Bank!B6,Calc_Region!$A$2:$A$6,Calc_Region!$F$2:$F$6)*0.01 -> 11817.568 | F6: =E6+Calc_Stats!$I$2*0.001 -> 11834.724 | G6: =ROUND(F6,2) -> 11834.72 | H6: =G6/MAX(1,Calc_Month!$C$2)*1000 -> 1477.1059 | I6: =H6+Calc_Dates!$J$2 -> 1508.1059 | J6: =IF(I6>AVERAGE($I$2:$I$21),"alto","basso") -> basso | K6: =RANK(I6,$I$2:$I$21) -> 16
A7: =Calc_Bank!A7 -> Banca Lariana | B7: =Calc_Bank!C7*Control!$B$15 -> 12975.993 | C7: =B7+Calc_Scenario!AL8/100 -> 13109.975 | D7: =C7*(1+Calc_Growth!AM8) -> 13200.724 | E7: =D7-_xlfn.XLOOKUP(Calc_Bank!B7,Calc_Region!$A$2:$A$6,Calc_Region!$F$2:$F$6)*0.01 -> 13087.753 | F7: =E7+Calc_Stats!$I$2*0.001 -> 13104.909 | G7: =ROUND(F7,2) -> 13104.91 | H7: =G7/MAX(1,Calc_Month!$C$2)*1000 -> 1635.6398 | I7: =H7+Calc_Dates!$J$2 -> 1666.6398 | J7: =IF(I7>AVERAGE($I$2:$I$21),"alto","basso") -> basso | K7: =RANK(I7,$I$2:$I$21) -> 15
A8: =Calc_Bank!A8 -> Banca Sabina | B8: =Calc_Bank!C8*Control!$B$15 -> 14256.806 | C8: =B8+Calc_Scenario!AL9/100 -> 14404.013 | D8: =C8*(1+Calc_Growth!AM9) -> 14506.229 | E8: =D8-_xlfn.XLOOKUP(Calc_Bank!B8,Calc_Region!$A$2:$A$6,Calc_Region!$F$2:$F$6)*0.01 -> 14336.55 | F8: =E8+Calc_Stats!$I$2*0.001 -> 14353.706 | G8: =ROUND(F8,2) -> 14353.71 | H8: =G8/MAX(1,Calc_Month!$C$2)*1000 -> 1791.5041 | I8: =H8+Calc_Dates!$J$2 -> 1822.5041 | J8: =IF(I8>AVERAGE($I$2:$I$21),"alto","basso") -> basso | K8: =RANK(I8,$I$2:$I$21) -> 14
A9: =Calc_Bank!A9 -> Banca Irpina | B9: =Calc_Bank!C9*Control!$B$15 -> 15413.172 | C9: =B9+Calc_Scenario!AL10/100 -> 15572.319 | D9: =C9*(1+Calc_Growth!AM10) -> 15678.282 | E9: =D9-_xlfn.XLOOKUP(Calc_Bank!B9,Calc_Region!$A$2:$A$6,Calc_Region!$F$2:$F$6)*0.01 -> 15489.723 | F9: =E9+Calc_Stats!$I$2*0.001 -> 15506.879 | G9: =ROUND(F9,2) -> 15506.88 | H9: =G9/MAX(1,Calc_Month!$C$2)*1000 -> 1935.4327 | I9: =H9+Calc_Dates!$J$2 -> 1966.4327 | J9: =IF(I9>AVERAGE($I$2:$I$21),"alto","basso") -> basso | K9: =RANK(I9,$I$2:$I$21) -> 13
A10: =Calc_Bank!A10 -> Banca Sannita | B10: =Calc_Bank!C10*Control!$B$15 -> 16603.302 | C10: =B10+Calc_Scenario!AL11/100 -> 16774.738 | D10: =C10*(1+Calc_Growth!AM11) -> 16890.971 | E10: =D10-_xlfn.XLOOKUP(Calc_Bank!B10,Calc_Region!$A$2:$A$6,Calc_Region!$F$2:$F$6)*0.01 -> 16702.413 | F10: =E10+Calc_Stats!$I$2*0.001 -> 16719.569 | G10: =ROUND(F10,2) -> 16719.57 | H10: =G10/MAX(1,Calc_Month!$C$2)*1000 -> 2086.79 | I10: =H10+Calc_Dates!$J$2 -> 2117.79 | J10: =IF(I10>AVERAGE($I$2:$I$21),"alto","basso") -> basso | K10: =RANK(I10,$I$2:$I$21) -> 12
A11: =Calc_Bank!A11 -> Banca Ligure | B11: =Calc_Bank!C11*Control!$B$15 -> 17844.991 | C11: =B11+Calc_Scenario!AL12/100 -> 18029.248 | D11: =C11*(1+Calc_Growth!AM12) -> 18156.702 | E11: =D11-_xlfn.XLOOKUP(Calc_Bank!B11,Calc_Region!$A$2:$A$6,Calc_Region!$F$2:$F$6)*0.01 -> 18043.731 | F11: =E11+Calc_Stats!$I$2*0.001 -> 18060.887 | G11: =ROUND(F11,2) -> 18060.89 | H11: =G11/MAX(1,Calc_Month!$C$2)*1000 -> 2254.2018 | I11: =H11+Calc_Dates!$J$2 -> 2285.2018 | J11: =IF(I11>AVERAGE($I$2:$I$21),"alto","basso") -> basso | K11: =RANK(I11,$I$2:$I$21) -> 11
A12: =Calc_Bank!A12 -> Banca Veneta | B12: =Calc_Bank!C12*Control!$B$15 -> 18933.934 | C12: =B12+Calc_Scenario!AL13/100 -> 19129.435 | D12: =C12*(1+Calc_Growth!AM13) -> 19262.381 | E12: =D12-_xlfn.XLOOKUP(Calc_Bank!B12,Calc_Region!$A$2:$A$6,Calc_Region!$F$2:$F$6)*0.01 -> 19084.89 | F12: =E12+Calc_Stats!$I$2*0.001 -> 19102.046 | G12: =ROUND(F12,2) -> 19102.05 | H12: =G12/MAX(1,Calc_Month!$C$2)*1000 -> 2384.1502 | I12: =H12+Calc_Dates!$J$2 -> 2415.1502 | J12: =IF(I12>AVERAGE($I$2:$I$21),"alto","basso") -> alto | K12: =RANK(I12,$I$2:$I$21) -> 10
A13: =Calc_Bank!A13 -> Banca Friulana | B13: =Calc_Bank!C13*Control!$B$15 -> 20303.501 | C13: =B13+Calc_Scenario!AL14/100 -> 20513.143 | D13: =C13*(1+Calc_Growth!AM14) -> 20654.999 | E13: =D13-_xlfn.XLOOKUP(Calc_Bank!B13,Calc_Region!$A$2:$A$6,Calc_Region!$F$2:$F$6)*0.01 -> 20477.509 | F13: =E13+Calc_Stats!$I$2*0.001 -> 20494.665 | G13: =ROUND(F13,2) -> 20494.66 | H13: =G13/MAX(1,Calc_Month!$C$2)*1000 -> 2557.9636 | I13: =H13+Calc_Dates!$J$2 -> 2588.9636 | J13: =IF(I13>AVERAGE($I$2:$I$21),"alto","basso") -> alto | K13: =RANK(I13,$I$2:$I$21) -> 9
... A21: =Calc_Bank!A21 -> Banca Città | B21: =Calc_Bank!C21*Control!$B$15 -> 29683.484 | C21: =B21+Calc_Scenario!AL22/100 -> 29989.977 | D21: =C21*(1+Calc_Growth!AM22) -> 30198.101 | E21: =D21-_xlfn.XLOOKUP(Calc_Bank!B21,Calc_Region!$A$2:$A$6,Calc_Region!$F$2:$F$6)*0.01 -> 30028.422 | F21: =E21+Calc_Stats!$I$2*0.001 -> 30045.578 | G21: =ROUND(F21,2) -> 30045.58 | H21: =G21/MAX(1,Calc_Month!$C$2)*1000 -> 3750.0256 | I21: =H21+Calc_Dates!$J$2 -> 3781.0256 | J21: =IF(I21>AVERAGE($I$2:$I$21),"alto","basso") -> alto | K21: =RANK(I21,$I$2:$I$21) -> 1

Sheet Calc_Summary
A1: Voce | B1: Valore | C1: Riferimento | D1: Var. | E1: Var. %
A2: Volumi | B2: {=INDEX(Calc_Month!$C$2:$C$37,Control!$B$3)} -> 8739.1 | C2: {=INDEX(Calc_Month!$C$2:$C$37,Control!$B$13)} -> 8718.7 | D2: =B2-C2 -> 20.4 | E2: =IFERROR(D2/C2,0) -> 0.0023397984
A3: Ricavi | B3: {=INDEX(Calc_Month!$D$2:$D$37,Control!$B$3)} -> 472.04 | C3: {=INDEX(Calc_Month!$D$2:$D$37,Control!$B$13)} -> 472.51 | D3: =B3-C3 -> -0.47 | E3: =IFERROR(D3/C3,0) -> -0.00099468794
A4: Costi | B4: {=INDEX(Calc_Month!$E$2:$E$37,Control!$B$3)} -> 287.57 | C4: {=INDEX(Calc_Month!$E$2:$E$37,Control!$B$13)} -> 285.29 | D4: =B4-C4 -> 2.28 | E4: =IFERROR(D4/C4,0) -> 0.0079918679
A5: Margine | B5: {=INDEX(Calc_Month!$G$2:$G$37,Control!$B$3)} -> 184.47 | C5: {=INDEX(Calc_Month!$G$2:$G$37,Control!$B$13)} -> 187.22 | D5: =B5-C5 -> -2.75 | E5: =IFERROR(D5/C5,0) -> -0.014688602
A6: Clienti | B6: {=INDEX(Calc_Month!$F$2:$F$37,Control!$B$3)} -> 986 | C6: {=INDEX(Calc_Month!$F$2:$F$37,Control!$B$13)} -> 972 | D6: =B6-C6 -> 14 | E6: =IFERROR(D6/C6,0) -> 0.014403292
A7: Budget | B7: {=INDEX(Calc_Month!$H$2:$H$37,Control!$B$3)} -> 8877 | C7: =IF(ISNUMBER(B7),ROUND(B7,2),B7) -> 8877
A8: Rango | B8: =_xlfn.XLOOKUP(Control!$B$2,Calc_Bank!$A$2:$A$21,Calc_Bank!$L$2:$L$21) -> 18 | C8: =IF(ISNUMBER(B8),ROUND(B8,2),B8) -> 18
A9: Quota | B9: =_xlfn.XLOOKUP(Control!$B$2,Calc_Bank!$A$2:$A$21,Calc_Bank!$K$2:$K$21) -> 0.025436881 | C9: =IF(ISNUMBER(B9),ROUND(B9,2),B9) -> 0.03
A10: YTD | B10: {=INDEX(Calc_Month!$J$2:$J$37,Control!$B$3)} -> 8739.1 | C10: =IF(ISNUMBER(B10),ROUND(B10,2),B10) -> 8739.1
A11: Scenario | B11: {=INDEX(Calc_Scenario!$B$3:$AK$22,Control!$B$6,Control!$B$3)} -> 9672.2602 | C11: =IF(ISNUMBER(B11),ROUND(B11,2),B11) -> 9672.26
A12: Quota regione | B12: =_xlfn.XLOOKUP(Control!$B$8,Calc_Region!$A$2:$A$6,Calc_Region!$K$2:$K$6) -> 0.29633031 | C12: =IF(ISNUMBER(B12),ROUND(B12,2),B12) -> 0.3
A13: Prodotto top | B13: =INDEX(Calc_Product!$A$2:$A$9,MATCH(MAX(Calc_Product!$B$2:$B$9),Calc_Product!$B$2:$B$9,0)) -> Assicurazioni | C13: =IF(ISNUMBER(B13),ROUND(B13,2),B13) -> Assicurazioni
A14: Profondità | B14: =_xlfn.XLOOKUP(Control!$B$2,Calc_Deep!$A$2:$A$21,Calc_Deep!$I$2:$I$21) -> 1201.5358 | C14: =IF(ISNUMBER(B14),ROUND(B14,2),B14) -> 1201.54
A15: Crescita media | B15: {=INDEX(Calc_Growth!$AM$3:$AM$22,Control!$B$6)} -> 0.0070587736 | C15: =IF(ISNUMBER(B15),ROUND(B15,2),B15) -> 0.01
A16: Mediana sistema | B16: =Calc_Stats!$I$2 -> 17155.95 | C16: =IF(ISNUMBER(B16),ROUND(B16,2),B16) -> 17155.95
A17: Titolo | B17: =Control!$B$16 -> Banca Tirrena (B103) - gennaio 2025 | C17: =IF(ISNUMBER(B17),ROUND(B17,2),B17) -> Banca Tirrena (B103) - gennaio 2025
A18: Media 12m | B18: {=INDEX(Calc_Month!$U$2:$U$37,Control!$B$3)} -> 8433.8917 | C18: =IF(ISNUMBER(B18),ROUND(B18,2),B18) -> 8433.89
A19: Media mobile | B19: {=INDEX(Calc_Month!$L$2:$L$37,Control!$B$3)} -> 8700.9 | C19: =IF(ISNUMBER(B19),ROUND(B19,2),B19) -> 8700.9

Sheet SLIDE Sintesi
B2: x
C3: ="Sintesi - "&Control!$B$16 -> Sintesi - Banca Tirrena (B103) - gennaio 2025
C4: Voce | D4: Mese | E4: Mese prec. | F4: Var. | G4: Var. %
C5: Volumi | D5: =Calc_Summary!B2 -> 8739.1 | E5: =Calc_Summary!C2 -> 8718.7 | F5: =D5-E5 -> 20.4 | G5: =IFERROR(F5/E5,"-") -> 0.0023397984
C6: Ricavi | D6: =Calc_Summary!B3 -> 472.04 | E6: =Calc_Summary!C3 -> 472.51 | F6: =D6-E6 -> -0.47 | G6: =IFERROR(F6/E6,"-") -> -0.00099468794
C7: Costi | D7: =Calc_Summary!B4 -> 287.57 | E7: =Calc_Summary!C4 -> 285.29 | F7: =D7-E7 -> 2.28 | G7: =IFERROR(F7/E7,"-") -> 0.0079918679
C8: Margine | D8: =Calc_Summary!B5 -> 184.47 | E8: =Calc_Summary!C5 -> 187.22 | F8: =D8-E8 -> -2.75 | G8: =IFERROR(F8/E8,"-") -> -0.014688602
C9: Clienti | D9: =Calc_Summary!B6 -> 986 | E9: =Calc_Summary!C6 -> 972 | F9: =D9-E9 -> 14 | G9: =IFERROR(F9/E9,"-") -> 0.014403292 | H9: x

Sheet SLIDE Ranking
B2: x
C3: ="Classifica - "&Control!$B$10 -> Classifica - gennaio 2025
C4: Pos. | D4: Banca | E4: Regione | F4: Volumi | G4: Quota | H4: Var. %
C5: =Calc_Stats!A2 -> 1 | D5: =Calc_Stats!C2 -> Banca Città | E5: =Calc_Stats!D2 -> Centro | F5: =Calc_Stats!B2 -> 27692.4 | G5: =Calc_Stats!E2 -> 0.080604214 | H5: =Calc_Stats!F2 -> 0.004621803
C6: =Calc_Stats!A3 -> 2 | D6: =Calc_Stats!C3 -> Banca Romagnola | E6: =Calc_Stats!D3 -> Nord-Est | F6: =Calc_Stats!B3 -> 26741.1 | G6: =Calc_Stats!E3 -> 0.077835267 | H6: =Calc_Stats!F3 -> 0.0081660352
C7: =Calc_Stats!A4 -> 3 | D7: =Calc_Stats!C4 -> Banca Sarda | E7: =Calc_Stats!D4 -> Isole | F7: =Calc_Stats!B4 -> 25627 | G7: =Calc_Stats!E4 -> 0.074592459 | H7: =Calc_Stats!F4 -> 0.0087384373
C8: =Calc_Stats!A5 -> 4 | D8: =Calc_Stats!C5 -> Banca Sicula | E8: =Calc_Stats!D5 -> Isole | F8: =Calc_Stats!B5 -> 24517.8 | G8: =Calc_Stats!E5 -> 0.071363912 | H8: =Calc_Stats!F5 -> 0.013852821
C9: =Calc_Stats!A6 -> 5 | D9: =Calc_Stats!C6 -> Banca Calabra | E9: =Calc_Stats!D6 -> Sud | F9: =Calc_Stats!B6 -> 23396.2 | G9: =Calc_Stats!E6 -> 0.068099273 | H9: =Calc_Stats!F6 -> 0.011447643
C10: =Calc_Stats!A7 -> 6 | D10: =Calc_Stats!C7 -> Banca Lucana | E10: =Calc_Stats!D7 -> Sud | F10: =Calc_Stats!B7 -> 22158.4 | G10: =Calc_Stats!E7 -> 0.064496411 | H10: =Calc_Stats!F7 -> 0.0055362945
C11: =Calc_Stats!A8 -> 7 | D11: =Calc_Stats!C8 -> Banca Marchigiana | E11: =Calc_Stats!D8 -> Centro | F11: =Calc_Stats!B8 -> 21147.3 | G11: =Calc_Stats!E8 -> 0.061553405 | H11: =Calc_Stats!F8 -> 0.0083251084
C12: =Calc_Stats!A9 -> 8 | D12: =Calc_Stats!C9 -> Banca Umbra | E12: =Calc_Stats!D9 -> Centro | F12: =Calc_Stats!B9 -> 19938.9 | G12: =Calc_Stats!E9 -> 0.058036117 | H12: =Calc_Stats!F9 -> 0.01149023
C13: =Calc_Stats!A10 -> 9 | D13: =Calc_Stats!C10 -> Banca Friulana | E13: =Calc_Stats!D10 -> Nord-Est | F13: =Calc_Stats!B10 -> 18941.6 | G13: =Calc_Stats!E10 -> 0.055133278 | H13: =Calc_Stats!F10 -> 0.015009512
C14: =Calc_Stats!A11 -> 10 | D14: =Calc_Stats!C11 -> Banca Veneta | E14: =Calc_Stats!D11 -> Nord-Est | F14: =Calc_Stats!B11 -> 17663.9 | G14: =Calc_Stats!E11 -> 0.051414279 | H14: =Calc_Stats!F11 -> 0.0030493691 | I14: x

Sheet SLIDE Regioni
B2: x
C3: ="Regioni - mese "&Control!$B$3 -> Regioni - mese 13
C4: Regione | D4: Banche | E4: Volumi | F4: Obiettivo | G4: Gap | H4: Quota | I4: Migliore | J4: Sel.
C5: =Calc_Region!A2 -> Nord-Ovest | D5: =Calc_Region!B2 -> 4 | E5: =Calc_Region!C2 -> 45188.4 | F5: =Calc_Region!I2 -> 42000 | G5: =Calc_Region!J2 -> 3188.4 | H5: =Calc_Region!K2 -> 0.13152979 | I5: =Calc_Region!M2 -> Banca Ligure | J5: =Calc_Region!L2 -> no
C6: =Calc_Region!A3 -> Nord-Est | D6: =Calc_Region!B3 -> 4 | E6: =Calc_Region!C3 -> 70996.2 | F6: =Calc_Region!I3 -> 30000 | G6: =Calc_Region!J3 -> 40996.2 | H6: =Calc_Region!K3 -> 0.2066485 | I6: =Calc_Region!M3 -> Banca Romagnola | J6: =Calc_Region!L3 -> no
C7: =Calc_Region!A4 -> Centro | D7: =Calc_Region!B4 -> 6 | E7: =Calc_Region!C4 -> 101807.3 | F7: =Calc_Region!I4 -> 47000 | G7: =Calc_Region!J4 -> 54807.3 | H7: =Calc_Region!K4 -> 0.29633031 | I7: =Calc_Region!M4 -> Banca Città | J7: =Calc_Region!L4 -> sì
C8: =Calc_Region!A5 -> Sud | D8: =Calc_Region!B5 -> 4 | E8: =Calc_Region!C5 -> 75423.5 | F8: =Calc_Region!I5 -> 26000 | G8: =Calc_Region!J5 -> 49423.5 | H8: =Calc_Region!K5 -> 0.21953503 | I8: =Calc_Region!M5 -> Banca Calabra | J8: =Calc_Region!L5 -> no
C9: =Calc_Region!A6 -> Isole | D9: =Calc_Region!B6 -> 2 | E9: =Calc_Region!C6 -> 50144.8 | F9: =Calc_Region!I6 -> 16000 | G9: =Calc_Region!J6 -> 34144.8 | H9: =Calc_Region!K6 -> 0.14595637 | I9: =Calc_Region!M6 -> Banca Sarda | J9: =Calc_Region!L6 -> no | K9: x

Sheet SLIDE Prodotti
B2: x
C3: ="Prodotti - "&Control!$B$2 -> Prodotti - Banca Tirrena
C4: Prodotto | D4: Categoria | E4: Volumi | F4: Margine | G4: Quota | H4: Quota mercato | I4: YTD | J4: Verifica
C5: =Calc_Product!A2 -> Mutui | D5: =Calc_Product!M2 -> Credito | E5: =Calc_Product!B2 -> 497.8 | F5: =Calc_Product!E2 -> 8.27 | G5: =Calc_Product!H2 -> 0.056962387 | H5: =Calc_Product!L2 -> 0.02659188 | I5: =Calc_Product!J2 -> 497.8 | J5: =IF(Calc_Product!O2=Calc_Product!B2,"ok","diverso") -> ok
C6: =Calc_Product!A3 -> Prestiti | D6: =Calc_Product!M3 -> Credito | E6: =Calc_Product!B3 -> 663.1 | F6: =Calc_Product!E3 -> 11.62 | G6: =Calc_Product!H3 -> 0.075877379 | H6: =Calc_Product!L3 -> 0.025852356 | I6: =Calc_Product!J3 -> 663.1 | J6: =IF(Calc_Product!O3=Calc_Product!B3,"ok","diverso") -> ok
C7: =Calc_Product!A4 -> Conti | D7: =Calc_Product!M4 -> Raccolta | E7: =Calc_Product!B4 -> 855.8 | F7: =Calc_Product!E4 -> 15.88 | G7: =Calc_Product!H4 -> 0.097927704 | H7: =Calc_Product!L4 -> 0.026377027 | I7: =Calc_Product!J4 -> 855.8 | J7: =IF(Calc_Product!O4=Calc_Product!B4,"ok","diverso") -> ok
C8: =Calc_Product!A5 -> Carte | D8: =Calc_Product!M5 -> Servizi | E8: =Calc_Product!B5 -> 1001.7 | F8: =Calc_Product!E5 -> 19.93 | G8: =Calc_Product!H5 -> 0.11462279 | H8: =Calc_Product!L5 -> 0.025419084 | I8: =Calc_Product!J5 -> 1001.7 | J8: =IF(Calc_Product!O5=Calc_Product!B5,"ok","diverso") -> ok
C9: =Calc_Product!A6 -> Leasing | D9: =Calc_Product!M6 -> Credito | E9: =Calc_Product!B6 -> 1158.4 | F9: =Calc_Product!E6 -> 23.53 | G9: =Calc_Product!H6 -> 0.1325537 | H9: =Calc_Product!L6 -> 0.024969769 | I9: =Calc_Product!J6 -> 1158.4 | J9: =IF(Calc_Product!O6=Calc_Product!B6,"ok","diverso") -> ok
C10: =Calc_Product!A7 -> Factoring | D10: =Calc_Product!M7 -> Credito | E10: =Calc_Product!B7 -> 1348.1 | F10: =Calc_Product!E7 -> 30.12 | G10: =Calc_Product!H7 -> 0.15426074 | H10: =Calc_Product!L7 -> 0.02522595 | I10: =Calc_Product!J7 -> 1348.1 | J10: =IF(Calc_Product!O7=Calc_Product!B7,"ok","diverso") -> ok
C11: =Calc_Product!A8 -> Risparmio | D11: =Calc_Product!M8 -> Raccolta | E11: =Calc_Product!B8 -> 1520.9 | F11: =Calc_Product!E8 -> 34.68 | G11: =Calc_Product!H8 -> 0.17403394 | H11: =Calc_Product!L8 -> 0.025203706 | I11: =Calc_Product!J8 -> 1520.9 | J11: =IF(Calc_Product!O8=Calc_Product!B8,"ok","diverso") -> ok
C12: =Calc_Product!A9 -> Assicurazioni | D12: =Calc_Product!M9 -> Servizi | E12: =Calc_Product!B9 -> 1693.3 | F12: =Calc_Product!E9 -> 40.44 | G12: =Calc_Product!H9 -> 0.19376137 | H12: =Calc_Product!L9 -> 0.025212549 | I12: =Calc_Product!J9 -> 1693.3 | J12: =IF(Calc_Product!O9=Calc_Product!B9,"ok","diverso") -> ok | K12: x

Sheet SLIDE Budget
B2: x
C3: ="Budget - "&Control!$B$2 -> Budget - Banca Tirrena
C4: Mese | D4: Effettivo | E4: Budget | F4: Budget (ORIZZ) | G4: Scost. | H4: Ricavi budget
C5: =Control!$B$3-6+ROW()-4 -> 8 | D5: {=INDEX(Calc_Month!$C$2:$C$37,C5)} -> 8440.6 | E5: {=INDEX(Budget!$B$2:$AK$21,Control!$B$6,MATCH(C5,Budget!$B$1:$AK$1,0))} -> 8520 | F5: =HLOOKUP(C5,Budget!$B$1:$AK$21,Control!$B$6+1,FALSE) -> 8520 | G5: =IFERROR(D5/E5-1,0) -> -0.0093192488 | H5: {=INDEX(Budget!$B$25:$AK$44,MATCH(Control!$B$2,Budget!$A$25:$A$44,0),C5)} -> 443
C6: =Control!$B$3-6+ROW()-4 -> 9 | D6: {=INDEX(Calc_Month!$C$2:$C$37,C6)} -> 8499.6 | E6: {=INDEX(Budget!$B$2:$AK$21,Control!$B$6,MATCH(C6,Budget!$B$1:$AK$1,0))} -> 8591 | F6: =HLOOKUP(C6,Budget!$B$1:$AK$21,Control!$B$6+1,FALSE) -> 8591 | G6: =IFERROR(D6/E6-1,0) -> -0.010639041 | H6: {=INDEX(Budget!$B$25:$AK$44,MATCH(Control!$B$2,Budget!$A$25:$A$44,0),C6)} -> 446.8
C7: =Control!$B$3-6+ROW()-4 -> 10 | D7: {=INDEX(Calc_Month!$C$2:$C$37,C7)} -> 8590.6 | E7: {=INDEX(Budget!$B$2:$AK$21,Control!$B$6,MATCH(C7,Budget!$B$1:$AK$1,0))} -> 8663 | F7: =HLOOKUP(C7,Budget!$B$1:$AK$21,Control!$B$6+1,FALSE) -> 8663 | G7: =IFERROR(D7/E7-1,0) -> -0.008357382 | H7: {=INDEX(Budget!$B$25:$AK$44,MATCH(Control!$B$2,Budget!$A$25:$A$44,0),C7)} -> 450.5
C8: =Control!$B$3-6+ROW()-4 -> 11 | D8: {=INDEX(Calc_Month!$C$2:$C$37,C8)} -> 8644.9 | E8: {=INDEX(Budget!$B$2:$AK$21,Control!$B$6,MATCH(C8,Budget!$B$1:$AK$1,0))} -> 8734 | F8: =HLOOKUP(C8,Budget!$B$1:$AK$21,Control!$B$6+1,FALSE) -> 8734 | G8: =IFERROR(D8/E8-1,0) -> -0.010201511 | H8: {=INDEX(Budget!$B$25:$AK$44,MATCH(Control!$B$2,Budget!$A$25:$A$44,0),C8)} -> 454.2
C9: =Control!$B$3-6+ROW()-4 -> 12 | D9: {=INDEX(Calc_Month!$C$2:$C$37,C9)} -> 8718.7 | E9: {=INDEX(Budget!$B$2:$AK$21,Control!$B$6,MATCH(C9,Budget!$B$1:$AK$1,0))} -> 8806 | F9: =HLOOKUP(C9,Budget!$B$1:$AK$21,Control!$B$6+1,FALSE) -> 8806 | G9: =IFERROR(D9/E9-1,0) -> -0.0099136952 | H9: {=INDEX(Budget!$B$25:$AK$44,MATCH(Control!$B$2,Budget!$A$25:$A$44,0),C9)} -> 457.9
C10: =Control!$B$3-6+ROW()-4 -> 13 | D10: {=INDEX(Calc_Month!$C$2:$C$37,C10)} -> 8739.1 | E10: {=INDEX(Budget!$B$2:$AK$21,Control!$B$6,MATCH(C10,Budget!$B$1:$AK$1,0))} -> 8877 | F10: =HLOOKUP(C10,Budget!$B$1:$AK$21,Control!$B$6+1,FALSE) -> 8877 | G10: =IFERROR(D10/E10-1,0) -> -0.015534527 | H10: {=INDEX(Budget!$B$25:$AK$44,MATCH(Control!$B$2,Budget!$A$25:$A$44,0),C10)} -> 461.6 | I10: x

Sheet SLIDE FX
B2: x
C3: ="Volumi in valuta - "&Control!$B$2 -> Volumi in valuta - Banca Tirrena
C4: Mese | D4: EUR | E4: USD | F4: GBP | G4: CHF
C5: =Control!$B$3-6+ROW()-4 -> 8 | D5: {=INDEX(Calc_Month!$C$2:$C$37,C5)} -> 8440.6 | E5: =D5*VLOOKUP(C5,FX!$A$2:$E$37,3,FALSE) -> 9207.0065 | F5: =D5*_xlfn.XLOOKUP(C5,FX!$A$2:$A$37,FX!$D$2:$D$37) -> 7139.0595 | G5: {=D5*INDEX(FX!$E$2:$E$37,C5)} -> 7883.5204
C6: =Control!$B$3-6+ROW()-4 -> 9 | D6: {=INDEX(Calc_Month!$C$2:$C$37,C6)} -> 8499.6 | E6: =D6*VLOOKUP(C6,FX!$A$2:$E$37,3,FALSE) -> 9263.714 | F6: =D6*_xlfn.XLOOKUP(C6,FX!$A$2:$A$37,FX!$D$2:$D$37) -> 7171.1125 | G6: {=D6*INDEX(FX!$E$2:$E$37,C6)} -> 7921.6272
C7: =Control!$B$3-6+ROW()-4 -> 10 | D7: {=INDEX(Calc_Month!$C$2:$C$37,C7)} -> 8590.6 | E7: =D7*VLOOKUP(C7,FX!$A$2:$E$37,3,FALSE) -> 9341.4184 | F7: =D7*_xlfn.XLOOKUP(C7,FX!$A$2:$A$37,FX!$D$2:$D$37) -> 7233.2852 | G7: {=D7*INDEX(FX!$E$2:$E$37,C7)} -> 7989.258
C8: =Control!$B$3-6+ROW()-4 -> 11 | D8: {=INDEX(Calc_Month!$C$2:$C$37,C8)} -> 8644.9 | E8: =D8*VLOOKUP(C8,FX!$A$2:$E$37,3,FALSE) -> 9365.8847 | F8: =D8*_xlfn.XLOOKUP(C8,FX!$A$2:$A$37,FX!$D$2:$D$37) -> 7268.6319 | G8: {=D8*INDEX(FX!$E$2:$E$37,C8)} -> 8022.4672
C9: =Control!$B$3-6+ROW()-4 -> 12 | D9: {=INDEX(Calc_Month!$C$2:$C$37,C9)} -> 8718.7 | E9: =D9*VLOOKUP(C9,FX!$A$2:$E$37,3,FALSE) -> 9400.5023 | F9: =D9*_xlfn.XLOOKUP(C9,FX!$A$2:$A$37,FX!$D$2:$D$37) -> 7324.5799 | G9: {=D9*INDEX(FX!$E$2:$E$37,C9)} -> 8073.5162
C10: =Control!$B$3-6+ROW()-4 -> 13 | D10: {=INDEX(Calc_Month!$C$2:$C$37,C10)} -> 8739.1 | E10: =D10*VLOOKUP(C10,FX!$A$2:$E$37,3,FALSE) -> 9367.4413 | F10: =D10*_xlfn.XLOOKUP(C10,FX!$A$2:$A$37,FX!$D$2:$D$37) -> 7341.7179 | G10: {=D10*INDEX(FX!$E$2:$E$37,C10)} -> 8074.9284 | H10: x

Sheet SLIDE Scenario
B2: x
C3: ="Scenario al "&TEXT(Control!$B$4,"0,0%") -> Scenario al 3,0%
C4: Banca | D4: Base | E4: Scenario | F4: Delta | G4: Scenario USD
C5: =Banks!A2 -> Banca Alpi | D5: {=INDEX(Calc_BankMonth!$B3:$AK3,Control!$B$3)} -> 6542.2 | E5: {=INDEX(Calc_BankMonth!$B49:$AK49,Control!$B$3)} -> 6755.0849 | F5: =E5-D5 -> 212.88488 | G5: =Calc_Scenario!AL3 -> 7240.7755
C6: =Banks!A3 -> Banca Adriatica | D6: {=INDEX(Calc_BankMonth!$B4:$AK4,Control!$B$3)} -> 7649.6 | E6: {=INDEX(Calc_BankMonth!$B50:$AK50,Control!$B$3)} -> 7898.52 | F6: =E6-D6 -> 248.91996 | G6: =Calc_Scenario!AL4 -> 8466.4235
C7: =Banks!A4 -> Banca Tirrena | D7: {=INDEX(Calc_BankMonth!$B5:$AK5,Control!$B$3)} -> 8739.1 | E7: {=INDEX(Calc_BankMonth!$B51:$AK51,Control!$B$3)} -> 9023.4726 | F7: =E7-D7 -> 284.37257 | G7: =Calc_Scenario!AL5 -> 9672.2602
C8: =Banks!A5 -> Banca Padana | D8: {=INDEX(Calc_BankMonth!$B6:$AK6,Control!$B$3)} -> 9892.6 | E8: {=INDEX(Calc_BankMonth!$B52:$AK52,Control!$B$3)} -> 10214.508 | F8: =E8-D8 -> 321.90775 | G8: =Calc_Scenario!AL6 -> 10948.931
C9: =Banks!A6 -> Banca Etrusca | D9: {=INDEX(Calc_BankMonth!$B7:$AK7,Control!$B$3)} -> 10989.1 | E9: {=INDEX(Calc_BankMonth!$B53:$AK53,Control!$B$3)} -> 11346.688 | F9: =E9-D9 -> 357.58815 | G9: =Calc_Scenario!AL7 -> 12162.515
C10: =Banks!A7 -> Banca Lariana | D10: {=INDEX(Calc_BankMonth!$B8:$AK8,Control!$B$3)} -> 12105.6 | E10: {=INDEX(Calc_BankMonth!$B54:$AK54,Control!$B$3)} -> 12499.519 | F10: =E10-D10 -> 393.91935 | G10: =Calc_Scenario!AL8 -> 13398.235
C11: =Banks!A8 -> Banca Sabina | D11: {=INDEX(Calc_BankMonth!$B9:$AK9,Control!$B$3)} -> 13300.5 | E11: {=INDEX(Calc_BankMonth!$B55:$AK55,Control!$B$3)} -> 13733.302 | F11: =E11-D11 -> 432.8017 | G11: =Calc_Scenario!AL9 -> 14720.726
C12: =Banks!A9 -> Banca Irpina | D12: {=INDEX(Calc_BankMonth!$B10:$AK10,Control!$B$3)} -> 14379.3 | E12: {=INDEX(Calc_BankMonth!$B56:$AK56,Control!$B$3)} -> 14847.206 | F12: =E12-D12 -> 467.90613 | G12: =Calc_Scenario!AL10 -> 15914.72
C13: =Banks!A10 -> Banca Sannita | D13: {=INDEX(Calc_BankMonth!$B11:$AK11,Control!$B$3)} -> 15489.6 | E13: {=INDEX(Calc_BankMonth!$B57:$AK57,Control!$B$3)} -> 15993.636 | F13: =E13-D13 -> 504.03558 | G13: =Calc_Scenario!AL11 -> 17143.578
C14: =Banks!A11 -> Banca Ligure | D14: {=INDEX(Calc_BankMonth!$B12:$AK12,Control!$B$3)} -> 16648 | E14: {=INDEX(Calc_BankMonth!$B58:$AK58,Control!$B$3)} -> 17189.73 | F14: =E14-D14 -> 541.73021 | G14: =Calc_Scenario!AL12 -> 18425.672
C15: =Banks!A12 -> Banca Veneta | D15: {=INDEX(Calc_BankMonth!$B13:$AK13,Control!$B$3)} -> 17663.9 | E15: {=INDEX(Calc_BankMonth!$B59:$AK59,Control!$B$3)} -> 18238.688 | F15: =E15-D15 -> 574.78786 | G15: =Calc_Scenario!AL13 -> 19550.05
C16: =Banks!A13 -> Banca Friulana | D16: {=INDEX(Calc_BankMonth!$B14:$AK14,Control!$B$3)} -> 18941.6 | E16: {=INDEX(Calc_BankMonth!$B60:$AK60,Control!$B$3)} -> 19557.965 | F16: =E16-D16 -> 616.36455 | G16: =Calc_Scenario!AL14 -> 20964.182
... C23: =Banks!A20 -> Banca Romagnola | D23: {=INDEX(Calc_BankMonth!$B21:$AK21,Control!$B$3)} -> 26741.1 | E23: {=INDEX(Calc_BankMonth!$B67:$AK67,Control!$B$3)} -> 27611.262 | F23: =E23-D23 -> 870.16229 | G23: =Calc_Scenario!AL21 -> 29596.512
C24: =Banks!A21 -> Banca Città | D24: {=INDEX(Calc_BankMonth!$B22:$AK22,Control!$B$3)} -> 27692.4 | E24: {=INDEX(Calc_BankMonth!$B68:$AK68,Control!$B$3)} -> 28593.518 | F24: =E24-D24 -> 901.11784 | G24: =Calc_Scenario!AL22 -> 30649.392 | H24: x

Sheet SLIDE Heatmap
B2: x
C3: ="Crescita m/m - ultimi 6 mesi" -> Crescita m/m - ultimi 6 mesi
C4: Banca | D4: m-5 | E4: m-4 | F4: m-3 | G4: m-2 | H4: m-1 | I4: m
C5: =Banks!A2 -> Banca Alpi | D5: {=INDEX(Calc_Growth!$C3:$AK3,Control!$B$3-1-5)} -> 0.0017385479 | E5: {=INDEX(Calc_Growth!$C3:$AK3,Control!$B$3-1-4)} -> 0.0059867845 | F5: {=INDEX(Calc_Growth!$C3:$AK3,Control!$B$3-1-3)} -> 0.018454915 | G5: {=INDEX(Calc_Growth!$C3:$AK3,Control!$B$3-1-2)} -> -0.0059987257 | H5: {=INDEX(Calc_Growth!$C3:$AK3,Control!$B$3-1-1)} -> 0.024233517 | I5: {=INDEX(Calc_Growth!$C3:$AK3,Control!$B$3-1-0)} -> -0.0013585505
C6: =Banks!A3 -> Banca Adriatica | D6: {=INDEX(Calc_Growth!$C4:$AK4,Control!$B$3-1-5)} -> 0.027634667 | E6: {=INDEX(Calc_Growth!$C4:$AK4,Control!$B$3-1-4)} -> 0.012297131 | F6: {=INDEX(Calc_Growth!$C4:$AK4,Control!$B$3-1-3)} -> -0.0037644672 | G6: {=INDEX(Calc_Growth!$C4:$AK4,Control!$B$3-1-2)} -> 0.028621581 | H6: {=INDEX(Calc_Growth!$C4:$AK4,Control!$B$3-1-1)} -> -0.0012635967 | I6: {=INDEX(Calc_Growth!$C4:$AK4,Control!$B$3-1-0)} -> -0.0022434392
C7: =Banks!A4 -> Banca Tirrena | D7: {=INDEX(Calc_Growth!$C5:$AK5,Control!$B$3-1-5)} -> 0.0042355741 | E7: {=INDEX(Calc_Growth!$C5:$AK5,Control!$B$3-1-4)} -> 0.0069900244 | F7: {=INDEX(Calc_Growth!$C5:$AK5,Control!$B$3-1-3)} -> 0.010706386 | G7: {=INDEX(Calc_Growth!$C5:$AK5,Control!$B$3-1-2)} -> 0.0063208623 | H7: {=INDEX(Calc_Growth!$C5:$AK5,Control!$B$3-1-1)} -> 0.0085368252 | I7: {=INDEX(Calc_Growth!$C5:$AK5,Control!$B$3-1-0)} -> 0.0023397984
C8: =Banks!A5 -> Banca Padana | D8: {=INDEX(Calc_Growth!$C6:$AK6,Control!$B$3-1-5)} -> 0.0038264225 | E8: {=INDEX(Calc_Growth!$C6:$AK6,Control!$B$3-1-4)} -> 0.017707618 | F8: {=INDEX(Calc_Growth!$C6:$AK6,Control!$B$3-1-3)} -> 0.00043576601 | G8: {=INDEX(Calc_Growth!$C6:$AK6,Control!$B$3-1-2)} -> 0.0096656434 | H8: {=INDEX(Calc_Growth!$C6:$AK6,Control!$B$3-1-1)} -> 0.0089670899 | I8: {=INDEX(Calc_Growth!$C6:$AK6,Control!$B$3-1-0)} -> 0.0070956642
C9: =Banks!A6 -> Banca Etrusca | D9: {=INDEX(Calc_Growth!$C7:$AK7,Control!$B$3-1-5)} -> 0.0058713055 | E9: {=INDEX(Calc_Growth!$C7:$AK7,Control!$B$3-1-4)} -> 0.01207955 | F9: {=INDEX(Calc_Growth!$C7:$AK7,Control!$B$3-1-3)} -> 0.0023945289 | G9: {=INDEX(Calc_Growth!$C7:$AK7,Control!$B$3-1-2)} -> 0.007389506 | H9: {=INDEX(Calc_Growth!$C7:$AK7,Control!$B$3-1-1)} -> 0.010896844 | I9: {=INDEX(Calc_Growth!$C7:$AK7,Control!$B$3-1-0)} -> 0.0030120207
C10: =Banks!A7 -> Banca Lariana | D10: {=INDEX(Calc_Growth!$C8:$AK8,Control!$B$3-1-5)} -> 0.004399548 | E10: {=INDEX(Calc_Growth!$C8:$AK8,Control!$B$3-1-4)} -> 0.012599737 | F10: {=INDEX(Calc_Growth!$C8:$AK8,Control!$B$3-1-3)} -> -0.0052672649 | G10: {=INDEX(Calc_Growth!$C8:$AK8,Control!$B$3-1-2)} -> 0.020890712 | H10: {=INDEX(Calc_Growth!$C8:$AK8,Control!$B$3-1-1)} -> 0.011826906 | I10: {=INDEX(Calc_Growth!$C8:$AK8,Control!$B$3-1-0)} -> -0.00071815953
C11: =Banks!A8 -> Banca Sabina | D11: {=INDEX(Calc_Growth!$C9:$AK9,Control!$B$3-1-5)} -> 0.0041198855 | E11: {=INDEX(Calc_Growth!$C9:$AK9,Control!$B$3-1-4)} -> 0.0085974693 | F11: {=INDEX(Calc_Growth!$C9:$AK9,Control!$B$3-1-3)} -> 0.00662992 | G11: {=INDEX(Calc_Growth!$C9:$AK9,Control!$B$3-1-2)} -> 0.0016272828 | H11: {=INDEX(Calc_Growth!$C9:$AK9,Control!$B$3-1-1)} -> 0.010025024 | I11: {=INDEX(Calc_Growth!$C9:$AK9,Control!$B$3-1-0)} -> 0.01393537
C12: =Banks!A9 -> Banca Irpina | D12: {=INDEX(Calc_Growth!$C10:$AK10,Control!$B$3-1-5)} -> 0.01066418 | E12: {=INDEX(Calc_Growth!$C10:$AK10,Control!$B$3-1-4)} -> 0.0046631975 | F12: {=INDEX(Calc_Growth!$C10:$AK10,Control!$B$3-1-3)} -> 0.007238527 | G12: {=INDEX(Calc_Growth!$C10:$AK10,Control!$B$3-1-2)} -> 0.011559664 | H12: {=INDEX(Calc_Growth!$C10:$AK10,Control!$B$3-1-1)} -> 0.0042879775 | I12: {=INDEX(Calc_Growth!$C10:$AK10,Control!$B$3-1-0)} -> 0.0081256923
C13: =Banks!A10 -> Banca Sannita | D13: {=INDEX(Calc_Growth!$C11:$AK11,Control!$B$3-1-5)} -> 0.0032103922 | E13: {=INDEX(Calc_Growth!$C11:$AK11,Control!$B$3-1-4)} -> 0.016835992 | F13: {=INDEX(Calc_Growth!$C11:$AK11,Control!$B$3-1-3)} -> 0.002848984 | G13: {=INDEX(Calc_Growth!$C11:$AK11,Control!$B$3-1-2)} -> 0.012149761 | H13: {=INDEX(Calc_Growth!$C11:$AK11,Control!$B$3-1-1)} -> 0.0025848564 | I13: {=INDEX(Calc_Growth!$C11:$AK11,Control!$B$3-1-0)} -> 0.0084637621
C14: =Banks!A11 -> Banca Ligure | D14: {=INDEX(Calc_Growth!$C12:$AK12,Control!$B$3-1-5)} -> 0.0086343314 | E14: {=INDEX(Calc_Growth!$C12:$AK12,Control!$B$3-1-4)} -> 0.0018365987 | F14: {=INDEX(Calc_Growth!$C12:$AK12,Control!$B$3-1-3)} -> 0.0087435837 | G14: {=INDEX(Calc_Growth!$C12:$AK12,Control!$B$3-1-2)} -> 0.0035176344 | H14: {=INDEX(Calc_Growth!$C12:$AK12,Control!$B$3-1-1)} -> 0.011504273 | I14: {=INDEX(Calc_Growth!$C12:$AK12,Control!$B$3-1-0)} -> 0.010378103
C15: =Banks!A12 -> Banca Veneta | D15: {=INDEX(Calc_Growth!$C13:$AK13,Control!$B$3-1-5)} -> 0.0069035569 | E15: {=INDEX(Calc_Growth!$C13:$AK13,Control!$B$3-1-4)} -> 0.01385321 | F15: {=INDEX(Calc_Growth!$C13:$AK13,Control!$B$3-1-3)} -> 0.0011049148 | G15: {=INDEX(Calc_Growth!$C13:$AK13,Control!$B$3-1-2)} -> 0.0087486637 | H15: {=INDEX(Calc_Growth!$C13:$AK13,Control!$B$3-1-1)} -> 0.0087816279 | I15: {=INDEX(Calc_Growth!$C13:$AK13,Control!$B$3-1-0)} -> 0.0030493691
C16: =Banks!A13 -> Banca Friulana | D16: {=INDEX(Calc_Growth!$C14:$AK14,Control!$B$3-1-5)} -> 0.011063115 | E16: {=INDEX(Calc_Growth!$C14:$AK14,Control!$B$3-1-4)} -> 0.0089515965 | F16: {=INDEX(Calc_Growth!$C14:$AK14,Control!$B$3-1-3)} -> 0.004419739 | G16: {=INDEX(Calc_Growth!$C14:$AK14,Control!$B$3-1-2)} -> 0.0044925287 | H16: {=INDEX(Calc_Growth!$C14:$AK14,Control!$B$3-1-1)} -> 0.0079996111 | I16: {=INDEX(Calc_Growth!$C14:$AK14,Control!$B$3-1-0)} -> 0.015009512
... C23: =Banks!A20 -> Banca Romagnola | D23: {=INDEX(Calc_Growth!$C21:$AK21,Control!$B$3-1-5)} -> 0.0087565331 | E23: {=INDEX(Calc_Growth!$C21:$AK21,Control!$B$3-1-4)} -> 0.01049042 | F23: {=INDEX(Calc_Growth!$C21:$AK21,Control!$B$3-1-3)} -> 0.00018449192 | G23: {=INDEX(Calc_Growth!$C21:$AK21,Control!$B$3-1-2)} -> 0.014991046 | H23: {=INDEX(Calc_Growth!$C21:$AK21,Control!$B$3-1-1)} -> 0.0042480208 | I23: {=INDEX(Calc_Growth!$C21:$AK21,Control!$B$3-1-0)} -> 0.0081660352
C24: =Banks!A21 -> Banca Città | D24: {=INDEX(Calc_Growth!$C22:$AK22,Control!$B$3-1-5)} -> 0.0065781075 | E24: {=INDEX(Calc_Growth!$C22:$AK22,Control!$B$3-1-4)} -> 0.0065537693 | F24: {=INDEX(Calc_Growth!$C22:$AK22,Control!$B$3-1-3)} -> 0.0052918876 | G24: {=INDEX(Calc_Growth!$C22:$AK22,Control!$B$3-1-2)} -> 0.0099271957 | H24: {=INDEX(Calc_Growth!$C22:$AK22,Control!$B$3-1-1)} -> 0.0061394031 | I24: {=INDEX(Calc_Growth!$C22:$AK22,Control!$B$3-1-0)} -> 0.004621803 | J24: x

Sheet SLIDE Peers
B2: x
C3: ="Confronto peer - "&Control!$B$2 -> Confronto peer - Banca Tirrena
C4: Banca | D4: Volumi | E4: Peer | F4: Gap | G4: Gap %
C5: =Calc_Links!A20 -> Banca Alpi | D5: =Calc_Bank!C2 -> 6542.2 | E5: =Calc_Links!B20 -> 6339 | F5: =D5-E5 -> 203.2 | G5: =Calc_Links!C20 -> 0.032055529
C6: =Calc_Links!A21 -> Banca Adriatica | D6: =Calc_Bank!C3 -> 7649.6 | E6: =Calc_Links!B21 -> 7115.9 | F6: =D6-E6 -> 533.7 | G6: =Calc_Links!C21 -> 0.075001054
C7: =Calc_Links!A22 -> Banca Tirrena | D7: =Calc_Bank!C4 -> 8739.1 | E7: =Calc_Links!B22 -> 8260.7 | F7: =D7-E7 -> 478.4 | G7: =Calc_Links!C22 -> 0.057912768
C8: =Calc_Links!A23 -> Banca Padana | D8: =Calc_Bank!C5 -> 9892.6 | E8: =Calc_Links!B23 -> 9250.5 | F8: =D8-E8 -> 642.1 | G8: =Calc_Links!C23 -> 0.069412464
C9: =Calc_Links!A24 -> Banca Etrusca | D9: =Calc_Bank!C6 -> 10989.1 | E9: =Calc_Links!B24 -> 10605.2 | F9: =D9-E9 -> 383.9 | G9: =Calc_Links!C24 -> 0.036199223
C10: =Calc_Links!A25 -> Banca Lariana | D10: =Calc_Bank!C7 -> 12105.6 | E10: =Calc_Links!B25 -> 11544 | F10: =D10-E10 -> 561.6 | G10: =Calc_Links!C25 -> 0.048648649
C11: =Calc_Links!A26 -> Banca Sabina | D11: =Calc_Bank!C8 -> 13300.5 | E11: =Calc_Links!B26 -> 12804.1 | F11: =D11-E11 -> 496.4 | G11: =Calc_Links!C26 -> 0.038768832
C12: =Calc_Links!A27 -> Banca Irpina | D12: =Calc_Bank!C9 -> 14379.3 | E12: =Calc_Links!B27 -> 13580.4 | F12: =D12-E12 -> 798.9 | G12: =Calc_Links!C27 -> 0.058827428
C13: =Calc_Links!A28 -> Banca Sannita | D13: =Calc_Bank!C10 -> 15489.6 | E13: =Calc_Links!B28 -> 14812.8 | F13: =D13-E13 -> 676.8 | G13: =Calc_Links!C28 -> 0.045690214
C14: =Calc_Links!A29 -> Banca Ligure | D14: =Calc_Bank!C11 -> 16648 | E14: =Calc_Links!B29 -> 15908.8 | F14: =D14-E14 -> 739.2 | G14: =Calc_Links!C29 -> 0.04646485
C15: =Calc_Links!A30 -> Banca Veneta | D15: =Calc_Bank!C12 -> 17663.9 | E15: =Calc_Links!B30 -> 16773.6 | F15: =D15-E15 -> 890.3 | G15: =Calc_Links!C30 -> 0.053077455
C16: =Calc_Links!A31 -> Banca Friulana | D16: =Calc_Bank!C13 -> 18941.6 | E16: =Calc_Links!B31 -> 17926.2 | F16: =D16-E16 -> 1015.4 | G16: =Calc_Links!C31 -> 0.056643349
... C23: =Calc_Links!A38 -> Banca Romagnola | D23: =Calc_Bank!C20 -> 26741.1 | E23: =Calc_Links!B38 -> 25309.4 | F23: =D23-E23 -> 1431.7 | G23: =Calc_Links!C38 -> 0.056567915
C24: =Calc_Links!A39 -> Banca Città | D24: =Calc_Bank!C21 -> 27692.4 | E24: =Calc_Links!B39 -> 26362.1 | F24: =D24-E24 -> 1330.3 | G24: =Calc_Links!C39 -> 0.050462596 | H24: x

Sheet SLIDE Aree
B2: x
C3: ="Aree (da Regions.xlsx)" -> Aree (da Regions.xlsx)
C4: Voce | D4: Valore
C5: Totale regioni | D5: =Calc_Links!B10 -> 343560.2
C6: Gap regione sel. | D6: =Calc_Links!B11 -> 51141.3
C7: Gap peer totale | D7: =Calc_Links!B12 -> 16749.5
C8: Gap peer sel. | D8: =Calc_Links!B13 -> 4594.3
C9: Rango peer | D9: =Calc_Links!B14 -> 4
C10: Regione sel. | D10: =Calc_Links!B15 -> Centro | E10: x

Sheet SLIDE Testi
B2: x
C3: ="Anagrafica testi" -> Anagrafica testi
C4: Banca | D4: Sigla | E4: Email | F4: Elenco | G4: Volumi | H4: Etichetta | I4: Stelle
C5: =Calc_Text!A2 -> Banca Alpi | D5: =Calc_Text!B2 -> BANCA | E5: =Calc_Text!H2 -> alpi@esempio.it | F5: =Calc_Text!L2 -> Banca Alpi, BANCA, Grande | G5: =Calc_Text!K2 -> 6.542,2 | H5: =Calc_Text!P2 -> Banca Alpi (NO) 1,9% | I5: =Calc_Text!J2 -> ********************
C6: =Calc_Text!A3 -> Banca Adriatica | D6: =Calc_Text!B3 -> BANCA | E6: =Calc_Text!H3 -> adriatica@esempio.it | F6: =Calc_Text!L3 -> Banca Adriatica, BANCA, Media | G6: =Calc_Text!K3 -> 7.649,6 | H6: =Calc_Text!P3 -> Banca Adriatica (NE) 2,2% | I6: =Calc_Text!J3 -> *******************
C7: =Calc_Text!A4 -> Banca Tirrena | D7: =Calc_Text!B4 -> BANCA | E7: =Calc_Text!H4 -> tirrena@esempio.it | F7: =Calc_Text!L4 -> Banca Tirrena, BANCA, Grande | G7: =Calc_Text!K4 -> 8.739,1 | H7: =Calc_Text!P4 -> Banca Tirrena (CE) 2,5% | I7: =Calc_Text!J4 -> ******************
C8: =Calc_Text!A5 -> Banca Padana | D8: =Calc_Text!B5 -> BANCA | E8: =Calc_Text!H5 -> padana@esempio.it | F8: =Calc_Text!L5 -> Banca Padana, BANCA, Grande | G8: =Calc_Text!K5 -> 9.892,6 | H8: =Calc_Text!P5 -> Banca Padana (NO) 2,9% | I8: =Calc_Text!J5 -> *****************
C9: =Calc_Text!A6 -> Banca Etrusca | D9: =Calc_Text!B6 -> BANCA | E9: =Calc_Text!H6 -> etrusca@esempio.it | F9: =Calc_Text!L6 -> Banca Etrusca, BANCA, Media | G9: =Calc_Text!K6 -> 10.989,1 | H9: =Calc_Text!P6 -> Banca Etrusca (CE) 3,2% | I9: =Calc_Text!J6 -> ****************
C10: =Calc_Text!A7 -> Banca Lariana | D10: =Calc_Text!B7 -> BANCA | E10: =Calc_Text!H7 -> lariana@esempio.it | F10: =Calc_Text!L7 -> Banca Lariana, BANCA, Piccola | G10: =Calc_Text!K7 -> 12.105,6 | H10: =Calc_Text!P7 -> Banca Lariana (NO) 3,5% | I10: =Calc_Text!J7 -> ***************
C11: =Calc_Text!A8 -> Banca Sabina | D11: =Calc_Text!B8 -> BANCA | E11: =Calc_Text!H8 -> sabina@esempio.it | F11: =Calc_Text!L8 -> Banca Sabina, BANCA, Piccola | G11: =Calc_Text!K8 -> 13.300,5 | H11: =Calc_Text!P8 -> Banca Sabina (CE) 3,9% | I11: =Calc_Text!J8 -> **************
C12: =Calc_Text!A9 -> Banca Irpina | D12: =Calc_Text!B9 -> BANCA | E12: =Calc_Text!H9 -> irpina@esempio.it | F12: =Calc_Text!L9 -> Banca Irpina, BANCA, Piccola | G12: =Calc_Text!K9 -> 14.379,3 | H12: =Calc_Text!P9 -> Banca Irpina (SU) 4,2% | I12: =Calc_Text!J9 -> *************
C13: =Calc_Text!A10 -> Banca Sannita | D13: =Calc_Text!B10 -> BANCA | E13: =Calc_Text!H10 -> sannita@esempio.it | F13: =Calc_Text!L10 -> Banca Sannita, BANCA, Media | G13: =Calc_Text!K10 -> 15.489,6 | H13: =Calc_Text!P10 -> Banca Sannita (SU) 4,5% | I13: =Calc_Text!J10 -> ************
C14: =Calc_Text!A11 -> Banca Ligure | D14: =Calc_Text!B11 -> BANCA | E14: =Calc_Text!H11 -> ligure@esempio.it | F14: =Calc_Text!L11 -> Banca Ligure, BANCA, Media | G14: =Calc_Text!K11 -> 16.648,0 | H14: =Calc_Text!P11 -> Banca Ligure (NO) 4,8% | I14: =Calc_Text!J11 -> ***********
C15: =Calc_Text!A12 -> Banca Veneta | D15: =Calc_Text!B12 -> BANCA | E15: =Calc_Text!H12 -> veneta@esempio.it | F15: =Calc_Text!L12 -> Banca Veneta, BANCA, Grande | G15: =Calc_Text!K12 -> 17.663,9 | H15: =Calc_Text!P12 -> Banca Veneta (NE) 5,1% | I15: =Calc_Text!J12 -> **********
C16: =Calc_Text!A13 -> Banca Friulana | D16: =Calc_Text!B13 -> BANCA | E16: =Calc_Text!H13 -> friulana@esempio.it | F16: =Calc_Text!L13 -> Banca Friulana, BANCA, Media | G16: =Calc_Text!K13 -> 18.941,6 | H16: =Calc_Text!P13 -> Banca Friulana (NE) 5,5% | I16: =Calc_Text!J13 -> *********
... C23: =Calc_Text!A20 -> Banca Romagnola | D23: =Calc_Text!B20 -> BANCA | E23: =Calc_Text!H20 -> romagnola@esempio.it | F23: =Calc_Text!L20 -> Banca Romagnola, BANCA, Media | G23: =Calc_Text!K20 -> 26.741,1 | H23: =Calc_Text!P20 -> Banca Romagnola (NE) 7,8% | I23: =Calc_Text!J20 -> **
C24: =Calc_Text!A21 -> Banca Città | D24: =Calc_Text!B21 -> BANCA | E24: =Calc_Text!H21 -> città@esempio.it | F24: =Calc_Text!L21 -> Banca Città, BANCA, Grande | G24: =Calc_Text!K21 -> 27.692,4 | H24: =Calc_Text!P21 -> Banca Città (CE) 8,1% | I24: =Calc_Text!J21 -> * | J24: x

Sheet SLIDE Date
B2: x
C3: ="Calendario - "&Control!$B$10 -> Calendario - gennaio 2025
C4: Mese | D4: Fine | E4: Giorni lav. | F4: Stato | G4: Etichetta | H4: Mesi da rif.
C5: =Control!$B$3-12+ROW()-4 -> 2 | D5: {=INDEX(Calc_Dates!$C$2:$C$37,C5)} -> 45351 | E5: {=INDEX(Calc_Dates!$I$2:$I$37,C5)} -> 21 | F5: {=INDEX(Calc_Dates!$L$2:$L$37,C5)} -> passato | G5: {=INDEX(Calc_Dates!$M$2:$M$37,C5)} -> feb-24 | H5: {=INDEX(Calc_Dates!$K$2:$K$37,C5)} -> 11
C6: =Control!$B$3-12+ROW()-4 -> 3 | D6: {=INDEX(Calc_Dates!$C$2:$C$37,C6)} -> 45382 | E6: {=INDEX(Calc_Dates!$I$2:$I$37,C6)} -> 21 | F6: {=INDEX(Calc_Dates!$L$2:$L$37,C6)} -> passato | G6: {=INDEX(Calc_Dates!$M$2:$M$37,C6)} -> mar-24 | H6: {=INDEX(Calc_Dates!$K$2:$K$37,C6)} -> 10
C7: =Control!$B$3-12+ROW()-4 -> 4 | D7: {=INDEX(Calc_Dates!$C$2:$C$37,C7)} -> 45412 | E7: {=INDEX(Calc_Dates!$I$2:$I$37,C7)} -> 22 | F7: {=INDEX(Calc_Dates!$L$2:$L$37,C7)} -> passato | G7: {=INDEX(Calc_Dates!$M$2:$M$37,C7)} -> apr-24 | H7: {=INDEX(Calc_Dates!$K$2:$K$37,C7)} -> 9
C8: =Control!$B$3-12+ROW()-4 -> 5 | D8: {=INDEX(Calc_Dates!$C$2:$C$37,C8)} -> 45443 | E8: {=INDEX(Calc_Dates!$I$2:$I$37,C8)} -> 23 | F8: {=INDEX(Calc_Dates!$L$2:$L$37,C8)} -> passato | G8: {=INDEX(Calc_Dates!$M$2:$M$37,C8)} -> mag-24 | H8: {=INDEX(Calc_Dates!$K$2:$K$37,C8)} -> 8
C9: =Control!$B$3-12+ROW()-4 -> 6 | D9: {=INDEX(Calc_Dates!$C$2:$C$37,C9)} -> 45473 | E9: {=INDEX(Calc_Dates!$I$2:$I$37,C9)} -> 20 | F9: {=INDEX(Calc_Dates!$L$2:$L$37,C9)} -> passato | G9: {=INDEX(Calc_Dates!$M$2:$M$37,C9)} -> giu-24 | H9: {=INDEX(Calc_Dates!$K$2:$K$37,C9)} -> 7
C10: =Control!$B$3-12+ROW()-4 -> 7 | D10: {=INDEX(Calc_Dates!$C$2:$C$37,C10)} -> 45504 | E10: {=INDEX(Calc_Dates!$I$2:$I$37,C10)} -> 23 | F10: {=INDEX(Calc_Dates!$L$2:$L$37,C10)} -> passato | G10: {=INDEX(Calc_Dates!$M$2:$M$37,C10)} -> lug-24 | H10: {=INDEX(Calc_Dates!$K$2:$K$37,C10)} -> 6
